Workbook

Sheet TỔNG QUAN
A1: BẢNG THEO DÕI TIẾN ĐỘ KHÓA HỌC
A2: Kho khóa học: D:\Sao lưu\Udemy\Khóa học — cập nhật từ cấu trúc thư mục hiện có
A4: TỔNG KHÓA | D4: TỔNG MODULE | G4: MODULE ĐÃ XONG | J4: TIẾN ĐỘ TOÀN KHO | M4: ĐIỂM TRUNG BÌNH
A5: =COUNTA(B12:B88) -> 77 | D5: =SUM(E12:E88) -> 992 | G5: =SUM(F12:F88) -> 0 | J5: =IFERROR(AVERAGE(G12:G88),0) -> 0 | M5: =IFERROR(AVERAGE(H12:H88),"")
A8: Cập nhật trực tiếp ở các sheet khóa học. Dùng bộ lọc ở bảng dưới để xem theo lĩnh vực, trạng thái hoặc tiến độ.
A10: DANH SÁCH KHÓA HỌC | L10: TỔNG HỢP THEO LĨNH VỰC
A11: Mã | B11: Cột1 | C11: Cột2 | D11: Cột3 | E11: Cột4 | F11: Cột5 | G11: Cột6 | H11: Cột7 | I11: Cột8 | J11: Cột9 | L11: Lĩnh vực
A12: C01 | B12: AI Agent 365 Ngày | C12: 01 - AI & Dữ liệu | D12: 01 - AI Engineering & LLM | E12: ='C01 AI Agent 365 Ngày'!$A$6 -> 8 | F12: ='C01 AI Agent 365 Ngày'!$C$6 -> 0 | G12: ='C01 AI Agent 365 Ngày'!$E$6 -> 0 | H12: ='C01 AI Agent 365 Ngày'!$G$6 | I12: =IF(E12=0,"Chưa có module",IF(F12=E12,"Đã hoàn thành",IF(F12=0,"Chưa bắt đầu","Đang học"))) -> Chưa bắt đầu | J12: C01 AI Agent 365 Ngày | L12: 01 - AI & Dữ liệu | M12: =COUNTIF($C$12:$C$88,L12) -> 18 | N12: =IFERROR(AVERAGEIF($C$12:$C$88,L12,$G$12:$G$88),0) -> 0
A13: C02 | B13: AI Engineer Roadmap Course | C13: 01 - AI & Dữ liệu | D13: 01 - AI Engineering & LLM | E13: ='C02 AI Engineer Roadmap Course'!$A$6 -> 1 | F13: ='C02 AI Engineer Roadmap Course'!$C$6 -> 0 | G13: ='C02 AI Engineer Roadmap Course'!$E$6 -> 0 | H13: ='C02 AI Engineer Roadmap Course'!$G$6 | I13: =IF(E13=0,"Chưa có module",IF(F13=E13,"Đã hoàn thành",IF(F13=0,"Chưa bắt đầu","Đang học"))) -> Chưa bắt đầu | J13: C02 AI Engineer Roadmap Course | L13: 02 - Lập trình & Phát triển phần mềm | M13: =COUNTIF($C$12:$C$88,L13) -> 12 | N13: =IFERROR(AVERAGEIF($C$12:$C$88,L13,$G$12:$G$88),0) -> 0
A14: C03 | B14: LangChain - Agentic AI Engineering with LangChain & LangGraph | C14: 01 - AI & Dữ liệu | D14: 01 - AI Engineering & LLM | E14: ='C03 LangChain - Agentic AI Engi'!$A$6 -> 28 | F14: ='C03 LangChain - Agentic AI Engi'!$C$6 -> 0 | G14: ='C03 LangChain - Agentic AI Engi'!$E$6 -> 0 | H14: ='C03 LangChain - Agentic AI Engi'!$G$6 | I14: =IF(E14=0,"Chưa có module",IF(F14=E14,"Đã hoàn thành",IF(F14=0,"Chưa bắt đầu","Đang học"))) -> Chưa bắt đầu | J14: C03 LangChain - Agentic AI Engi | L14: 03 - Hạ tầng, Mạng & An ninh | M14: =COUNTIF($C$12:$C$88,L14) -> 5 | N14: =IFERROR(AVERAGEIF($C$12:$C$88,L14,$G$12:$G$88),0) -> 0
A15: C04 | B15: Basic to Advanced: Retrieval-Augmented Generation — RAG | C15: 01 - AI & Dữ liệu | D15: 01 - AI Engineering & LLM | E15: ='C04 Basic to Advanced- Retrieva'!$A$6 -> 9 | F15: ='C04 Basic to Advanced- Retrieva'!$C$6 -> 0 | G15: ='C04 Basic to Advanced- Retrieva'!$E$6 -> 0 | H15: ='C04 Basic to Advanced- Retrieva'!$G$6 | I15: =IF(E15=0,"Chưa có module",IF(F15=E15,"Đã hoàn thành",IF(F15=0,"Chưa bắt đầu","Đang học"))) -> Chưa bắt đầu | J15: C04 Basic to Advanced- Retrieva | L15: 04 - Thiết kế & Sáng tạo số | M15: =COUNTIF($C$12:$C$88,L15) -> 15 | N15: =IFERROR(AVERAGEIF($C$12:$C$88,L15,$G$12:$G$88),0) -> 0
A16: C05 | B16: Ultimate RAG Bootcamp Using LangChain, LangGraph & LangSmith | C16: 01 - AI & Dữ liệu | D16: 01 - AI Engineering & LLM | E16: ='C05 Ultimate RAG Bootcamp Using'!$A$6 -> 29 | F16: ='C05 Ultimate RAG Bootcamp Using'!$C$6 -> 0 | G16: ='C05 Ultimate RAG Bootcamp Using'!$E$6 -> 0 | H16: ='C05 Ultimate RAG Bootcamp Using'!$G$6 | I16: =IF(E16=0,"Chưa có module",IF(F16=E16,"Đã hoàn thành",IF(F16=0,"Chưa bắt đầu","Đang học"))) -> Chưa bắt đầu | J16: C05 Ultimate RAG Bootcamp Using | L16: 05 - Phát triển game | M16: =COUNTIF($C$12:$C$88,L16) -> 9 | N16: =IFERROR(AVERAGEIF($C$12:$C$88,L16,$G$12:$G$88),0) -> 0
A17: C06 | B17: AI & Data Scientist Roadmap Course | C17: 01 - AI & Dữ liệu | D17: 02 - Data Science, Analytics & ML | E17: ='C06 AI & Data Scientist Roadmap'!$A$6 -> 1 | F17: ='C06 AI & Data Scientist Roadmap'!$C$6 -> 0 | G17: ='C06 AI & Data Scientist Roadmap'!$E$6 -> 0 | H17: ='C06 AI & Data Scientist Roadmap'!$G$6 | I17: =IF(E17=0,"Chưa có module",IF(F17=E17,"Đã hoàn thành",IF(F17=0,"Chưa bắt đầu","Đang học"))) -> Chưa bắt đầu | J17: C06 AI & Data Scientist Roadmap | L17: 06 - Ngôn ngữ | M17: =COUNTIF($C$12:$C$88,L17) -> 12 | N17: =IFERROR(AVERAGEIF($C$12:$C$88,L17,$G$12:$G$88),0) -> 0
A18: C07 | B18: bi-analyst-roadmap | C18: 01 - AI & Dữ liệu | D18: 02 - Data Science, Analytics & ML | E18: ='C07 bi-analyst-roadmap'!$A$6 -> 2 | F18: ='C07 bi-analyst-roadmap'!$C$6 -> 0 | G18: ='C07 bi-analyst-roadmap'!$E$6 -> 0 | H18: ='C07 bi-analyst-roadmap'!$G$6 | I18: =IF(E18=0,"Chưa có module",IF(F18=E18,"Đã hoàn thành",IF(F18=0,"Chưa bắt đầu","Đang học"))) -> Chưa bắt đầu | J18: C07 bi-analyst-roadmap | L18: 07 - Kinh doanh & Quản lý | M18: =COUNTIF($C$12:$C$88,L18) -> 4 | N18: =IFERROR(AVERAGEIF($C$12:$C$88,L18,$G$12:$G$88),0) -> 0
A19: C08 | B19: data-analyst-roadmap | C19: 01 - AI & Dữ liệu | D19: 02 - Data Science, Analytics & ML | E19: ='C08 data-analyst-roadmap'!$A$6 -> 1 | F19: ='C08 data-analyst-roadmap'!$C$6 -> 0 | G19: ='C08 data-analyst-roadmap'!$E$6 -> 0 | H19: ='C08 data-analyst-roadmap'!$G$6 | I19: =IF(E19=0,"Chưa có module",IF(F19=E19,"Đã hoàn thành",IF(F19=0,"Chưa bắt đầu","Đang học"))) -> Chưa bắt đầu | J19: C08 data-analyst-roadmap | L19: 08 - Sức khỏe & Đời sống | M19: =COUNTIF($C$12:$C$88,L19) -> 1 | N19: =IFERROR(AVERAGEIF($C$12:$C$88,L19,$G$12:$G$88),0) -> 0
A20: C09 | B20: data-engineer-roadmap | C20: 01 - AI & Dữ liệu | D20: 02 - Data Science, Analytics & ML | E20: ='C09 data-engineer-roadmap'!$A$6 -> 1 | F20: ='C09 data-engineer-roadmap'!$C$6 -> 0 | G20: ='C09 data-engineer-roadmap'!$E$6 -> 0 | H20: ='C09 data-engineer-roadmap'!$G$6 | I20: =IF(E20=0,"Chưa có module",IF(F20=E20,"Đã hoàn thành",IF(F20=0,"Chưa bắt đầu","Đang học"))) -> Chưa bắt đầu | J20: C09 data-engineer-roadmap | L20: 09 - Viết & Sáng tác | M20: =COUNTIF($C$12:$C$88,L20) -> 1 | N20: =IFERROR(AVERAGEIF($C$12:$C$88,L20,$G$12:$G$88),0) -> 0
A21: C10 | B21: Khóa Học Tính Toán Tiến Hóa (Evolutionary Computation) | C21: 01 - AI & Dữ liệu | D21: 02 - Data Science, Analytics & ML | E21: ='C10 Khóa Học Tính Toán Tiến Hóa'!$A$6 -> 10 | F21: ='C10 Khóa Học Tính Toán Tiến Hóa'!$C$6 -> 0 | G21: ='C10 Khóa Học Tính Toán Tiến Hóa'!$E$6 -> 0 | H21: ='C10 Khóa Học Tính Toán Tiến Hóa'!$G$6 | I21: =IF(E21=0,"Chưa có module",IF(F21=E21,"Đã hoàn thành",IF(F21=0,"Chưa bắt đầu","Đang học"))) -> Chưa bắt đầu | J21: C10 Khóa Học Tính Toán Tiến Hóa
A22: C11 | B22: machine-learning-roadmap | C22: 01 - AI & Dữ liệu | D22: 02 - Data Science, Analytics & ML | E22: ='C11 machine-learning-roadmap'!$A$6 -> 1 | F22: ='C11 machine-learning-roadmap'!$C$6 -> 0 | G22: ='C11 machine-learning-roadmap'!$E$6 -> 0 | H22: ='C11 machine-learning-roadmap'!$G$6 | I22: =IF(E22=0,"Chưa có module",IF(F22=E22,"Đã hoàn thành",IF(F22=0,"Chưa bắt đầu","Đang học"))) -> Chưa bắt đầu | J22: C11 machine-learning-roadmap
A23: C12 | B23: AI Coder: Complete Claude Code & Coding Agents Course | C23: 01 - AI & Dữ liệu | D23: 03 - AI hỗ trợ phát triển phần mềm | E23: ='C12 AI Coder- Complete Claude C'!$A$6 -> 16 | F23: ='C12 AI Coder- Complete Claude C'!$C$6 -> 0 | G23: ='C12 AI Coder- Complete Claude C'!$E$6 -> 0 | H23: ='C12 AI Coder- Complete Claude C'!$G$6 | I23: =IF(E23=0,"Chưa có module",IF(F23=E23,"Đã hoàn thành",IF(F23=0,"Chưa bắt đầu","Đang học"))) -> Chưa bắt đầu | J23: C12 AI Coder- Complete Claude C
A24: C13 | B24: claude-aiagents-cowork-masterclass | C24: 01 - AI & Dữ liệu | D24: 03 - AI hỗ trợ phát triển phần mềm | E24: ='C13 claude-aiagents-cowork-mast'!$A$6 -> 13 | F24: ='C13 claude-aiagents-cowork-mast'!$C$6 -> 0 | G24: ='C13 claude-aiagents-cowork-mast'!$E$6 -> 0 | H24: ='C13 claude-aiagents-cowork-mast'!$G$6 | I24: =IF(E24=0,"Chưa có module",IF(F24=E24,"Đã hoàn thành",IF(F24=0,"Chưa bắt đầu","Đang học"))) -> Chưa bắt đầu | J24: C13 claude-aiagents-cowork-mast
A25: C14 | B25: The Complete Claude Code & Claude Cowork Masterclass [2026] | C25: 01 - AI & Dữ liệu | D25: 03 - AI hỗ trợ phát triển phần mềm | E25: ='C14 The Complete Claude Code &'!$A$6 -> 13 | F25: ='C14 The Complete Claude Code &'!$C$6 -> 0 | G25: ='C14 The Complete Claude Code &'!$E$6 -> 0 | H25: ='C14 The Complete Claude Code &'!$G$6 | I25: =IF(E25=0,"Chưa có module",IF(F25=E25,"Đã hoàn thành",IF(F25=0,"Chưa bắt đầu","Đang học"))) -> Chưa bắt đầu | J25: C14 The Complete Claude Code &
A26: C15 | B26: Claude Code - The Practical Guide | C26: 01 - AI & Dữ liệu | D26: 03 - AI hỗ trợ phát triển phần mềm | E26: ='C15 Claude Code - The Practical'!$A$6 -> 3 | F26: ='C15 Claude Code - The Practical'!$C$6 -> 0 | G26: ='C15 Claude Code - The Practical'!$E$6 -> 0 | H26: ='C15 Claude Code - The Practical'!$G$6 | I26: =IF(E26=0,"Chưa có module",IF(F26=E26,"Đã hoàn thành",IF(F26=0,"Chưa bắt đầu","Đang học"))) -> Chưa bắt đầu | J26: C15 Claude Code - The Practical
A27: C16 | B27: khoa-hoc-vibe-coding | C27: 01 - AI & Dữ liệu | D27: 03 - AI hỗ trợ phát triển phần mềm | E27: ='C16 khoa-hoc-vibe-coding'!$A$6 -> 12 | F27: ='C16 khoa-hoc-vibe-coding'!$C$6 -> 0 | G27: ='C16 khoa-hoc-vibe-coding'!$E$6 -> 0 | H27: ='C16 khoa-hoc-vibe-coding'!$G$6 | I27: =IF(E27=0,"Chưa có module",IF(F27=E27,"Đã hoàn thành",IF(F27=0,"Chưa bắt đầu","Đang học"))) -> Chưa bắt đầu | J27: C16 khoa-hoc-vibe-coding
A28: C17 | B28: Khóa Học Vibe Coding Cơ Bản Cho Người Mới Bắt Đầu | C28: 01 - AI & Dữ liệu | D28: 03 - AI hỗ trợ phát triển phần mềm | E28: ='C17 Khóa Học Vibe Coding Cơ Bản'!$A$6 -> 6 | F28: ='C17 Khóa Học Vibe Coding Cơ Bản'!$C$6 -> 0 | G28: ='C17 Khóa Học Vibe Coding Cơ Bản'!$E$6 -> 0 | H28: ='C17 Khóa Học Vibe Coding Cơ Bản'!$G$6 | I28: =IF(E28=0,"Chưa có module",IF(F28=E28,"Đã hoàn thành",IF(F28=0,"Chưa bắt đầu","Đang học"))) -> Chưa bắt đầu | J28: C17 Khóa Học Vibe Coding Cơ Bản
A29: C18 | B29: Backend Developer Roadmap Workspace | C29: 02 - Lập trình & Phát triển phần mềm | D29: 01 - Web & Backend | E29: ='C18 Backend Developer Roadmap W'!$A$6 -> 2 | F29: ='C18 Backend Developer Roadmap W'!$C$6 -> 0 | G29: ='C18 Backend Developer Roadmap W'!$E$6 -> 0 | H29: ='C18 Backend Developer Roadmap W'!$G$6 | I29: =IF(E29=0,"Chưa có module",IF(F29=E29,"Đã hoàn thành",IF(F29=0,"Chưa bắt đầu","Đang học"))) -> Chưa bắt đầu | J29: C18 Backend Developer Roadmap W
A30: C19 | B30: frontend-developer-roadmap | C30: 02 - Lập trình & Phát triển phần mềm | D30: 01 - Web & Backend | E30: ='C19 frontend-developer-roadmap'!$A$6 -> 1 | F30: ='C19 frontend-developer-roadmap'!$C$6 -> 0 | G30: ='C19 frontend-developer-roadmap'!$E$6 -> 0 | H30: ='C19 frontend-developer-roadmap'!$G$6 | I30: =IF(E30=0,"Chưa có module",IF(F30=E30,"Đã hoàn thành",IF(F30=0,"Chưa bắt đầu","Đang học"))) -> Chưa bắt đầu | J30: C19 frontend-developer-roadmap
A31: C20 | B31: full-stack-developer-roadmap | C31: 02 - Lập trình & Phát triển phần mềm | D31: 01 - Web & Backend | E31: ='C20 full-stack-developer-roadma'!$A$6 -> 1 | F31: ='C20 full-stack-developer-roadma'!$C$6 -> 0 | G31: ='C20 full-stack-developer-roadma'!$E$6 -> 0 | H31: ='C20 full-stack-developer-roadma'!$G$6 | I31: =IF(E31=0,"Chưa có module",IF(F31=E31,"Đã hoàn thành",IF(F31=0,"Chưa bắt đầu","Đang học"))) -> Chưa bắt đầu | J31: C20 full-stack-developer-roadma
A32: C21 | B32: NodeJS - The Complete Guide | C32: 02 - Lập trình & Phát triển phần mềm | D32: 01 - Web & Backend | E32: ='C21 NodeJS - The Complete Guide'!$A$6 -> 36 | F32: ='C21 NodeJS - The Complete Guide'!$C$6 -> 0 | G32: ='C21 NodeJS - The Complete Guide'!$E$6 -> 0 | H32: ='C21 NodeJS - The Complete Guide'!$G$6 | I32: =IF(E32=0,"Chưa có module",IF(F32=E32,"Đã hoàn thành",IF(F32=0,"Chưa bắt đầu","Đang học"))) -> Chưa bắt đầu | J32: C21 NodeJS - The Complete Guide
A33: C22 | B33: postgresql-dba-roadmap | C33: 02 - Lập trình & Phát triển phần mềm | D33: 01 - Web & Backend | E33: ='C22 postgresql-dba-roadmap'!$A$6 -> 1 | F33: ='C22 postgresql-dba-roadmap'!$C$6 -> 0 | G33: ='C22 postgresql-dba-roadmap'!$E$6 -> 0 | H33: ='C22 postgresql-dba-roadmap'!$G$6 | I33: =IF(E33=0,"Chưa có module",IF(F33=E33,"Đã hoàn thành",IF(F33=0,"Chưa bắt đầu","Đang học"))) -> Chưa bắt đầu | J33: C22 postgresql-dba-roadmap
A34: C23 | B34: Android Developer Roadmap Course | C34: 02 - Lập trình & Phát triển phần mềm | D34: 02 - Mobile | E34: ='C23 Android Developer Roadmap C'!$A$6 -> 1 | F34: ='C23 Android Developer Roadmap C'!$C$6 -> 0 | G34: ='C23 Android Developer Roadmap C'!$E$6 -> 0 | H34: ='C23 Android Developer Roadmap C'!$G$6 | I34: =IF(E34=0,"Chưa có module",IF(F34=E34,"Đã hoàn thành",IF(F34=0,"Chưa bắt đầu","Đang học"))) -> Chưa bắt đầu | J34: C23 Android Developer Roadmap C
A35: C24 | B35: 3-in-1 Flutter AI Masterclass: 15 Apps with Cursor & Figma | C35: 02 - Lập trình & Phát triển phần mềm | D35: 02 - Mobile | E35: ='C24 3-in-1 Flutter AI Mastercla'!$A$6 -> 22 | F35: ='C24 3-in-1 Flutter AI Mastercla'!$C$6 -> 0 | G35: ='C24 3-in-1 Flutter AI Mastercla'!$E$6 -> 0 | H35: ='C24 3-in-1 Flutter AI Mastercla'!$G$6 | I35: =IF(E35=0,"Chưa có module",IF(F35=E35,"Đã hoàn thành",IF(F35=0,"Chưa bắt đầu","Đang học"))) -> Chưa bắt đầu | J35: C24 3-in-1 Flutter AI Mastercla
A36: C25 | B36: Flutter & Dart: The Complete Guide | C36: 02 - Lập trình & Phát triển phần mềm | D36: 02 - Mobile | E36: ='C25 Flutter & Dart- The Complet'!$A$6 -> 15 | F36: ='C25 Flutter & Dart- The Complet'!$C$6 -> 0 | G36: ='C25 Flutter & Dart- The Complet'!$E$6 -> 0 | H36: ='C25 Flutter & Dart- The Complet'!$G$6 | I36: =IF(E36=0,"Chưa có module",IF(F36=E36,"Đã hoàn thành",IF(F36=0,"Chưa bắt đầu","Đang học"))) -> Chưa bắt đầu | J36: C25 Flutter & Dart- The Complet
A37: C26 | B37: ios-roadmap | C37: 02 - Lập trình & Phát triển phần mềm | D37: 02 - Mobile | E37: ='C26 ios-roadmap'!$A$6 -> 1 | F37: ='C26 ios-roadmap'!$C$6 -> 0 | G37: ='C26 ios-roadmap'!$E$6 -> 0 | H37: ='C26 ios-roadmap'!$G$6 | I37: =IF(E37=0,"Chưa có module",IF(F37=E37,"Đã hoàn thành",IF(F37=0,"Chưa bắt đầu","Đang học"))) -> Chưa bắt đầu | J37: C26 ios-roadmap
A38: C27 | B38: Enterprise Integration Engineer Course | C38: 02 - Lập trình & Phát triển phần mềm | D38: 03 - Kiến trúc & Tích hợp | E38: ='C27 Enterprise Integration Engi'!$A$6 -> 7 | F38: ='C27 Enterprise Integration Engi'!$C$6 -> 0 | G38: ='C27 Enterprise Integration Engi'!$E$6 -> 0 | H38: ='C27 Enterprise Integration Engi'!$G$6 | I38: =IF(E38=0,"Chưa có module",IF(F38=E38,"Đã hoàn thành",IF(F38=0,"Chưa bắt đầu","Đang học"))) -> Chưa bắt đầu | J38: C27 Enterprise Integration Engi
A39: C28 | B39: software-architect-roadmap | C39: 02 - Lập trình & Phát triển phần mềm | D39: 03 - Kiến trúc & Tích hợp | E39: ='C28 software-architect-roadmap'!$A$6 -> 1 | F39: ='C28 software-architect-roadmap'!$C$6 -> 0 | G39: ='C28 software-architect-roadmap'!$E$6 -> 0 | H39: ='C28 software-architect-roadmap'!$G$6 | I39: =IF(E39=0,"Chưa có module",IF(F39=E39,"Đã hoàn thành",IF(F39=0,"Chưa bắt đầu","Đang học"))) -> Chưa bắt đầu | J39: C28 software-architect-roadmap
A40: C29 | B40: qa-roadmap | C40: 02 - Lập trình & Phát triển phần mềm | D40: 04 - Kiểm thử phần mềm | E40: ='C29 qa-roadmap'!$A$6 -> 1 | F40: ='C29 qa-roadmap'!$C$6 -> 0 | G40: ='C29 qa-roadmap'!$E$6 -> 0 | H40: ='C29 qa-roadmap'!$G$6 | I40: =IF(E40=0,"Chưa có module",IF(F40=E40,"Đã hoàn thành",IF(F40=0,"Chưa bắt đầu","Đang học"))) -> Chưa bắt đầu | J40: C29 qa-roadmap
A41: C30 | B41: Fundamentals of Backend Communications & Protocols | C41: 03 - Hạ tầng, Mạng & An ninh | D41: 01 - Mạng & Giao tiếp hệ thống | E41: ='C30 Fundamentals of Backend Com'!$A$6 -> 8 | F41: ='C30 Fundamentals of Backend Com'!$C$6 -> 0 | G41: ='C30 Fundamentals of Backend Com'!$E$6 -> 0 | H41: ='C30 Fundamentals of Backend Com'!$G$6 | I41: =IF(E41=0,"Chưa có module",IF(F41=E41,"Đã hoàn thành",IF(F41=0,"Chưa bắt đầu","Đang học"))) -> Chưa bắt đầu | J41: C30 Fundamentals of Backend Com
A42: C31 | B42: network-engineer-roadmap | C42: 03 - Hạ tầng, Mạng & An ninh | D42: 01 - Mạng & Giao tiếp hệ thống | E42: ='C31 network-engineer-roadmap'!$A$6 -> 2 | F42: ='C31 network-engineer-roadmap'!$C$6 -> 0 | G42: ='C31 network-engineer-roadmap'!$E$6 -> 0 | H42: ='C31 network-engineer-roadmap'!$G$6 | I42: =IF(E42=0,"Chưa có module",IF(F42=E42,"Đã hoàn thành",IF(F42=0,"Chưa bắt đầu","Đang học"))) -> Chưa bắt đầu | J42: C31 network-engineer-roadmap
A43: C32 | B43: Cyber Security Expert Roadmap 2026 | C43: 03 - Hạ tầng, Mạng & An ninh | D43: 02 - An ninh mạng & DevSecOps | E43: ='C32 Cyber Security Expert Roadm'!$A$6 -> 1 | F43: ='C32 Cyber Security Expert Roadm'!$C$6 -> 0 | G43: ='C32 Cyber Security Expert Roadm'!$E$6 -> 0 | H43: ='C32 Cyber Security Expert Roadm'!$G$6 | I43: =IF(E43=0,"Chưa có module",IF(F43=E43,"Đã hoàn thành",IF(F43=0,"Chưa bắt đầu","Đang học"))) -> Chưa bắt đầu | J43: C32 Cyber Security Expert Roadm
A44: C33 | B44: devsecops-roadmap | C44: 03 - Hạ tầng, Mạng & An ninh | D44: 02 - An ninh mạng & DevSecOps | E44: ='C33 devsecops-roadmap'!$A$6 -> 1 | F44: ='C33 devsecops-roadmap'!$C$6 -> 0 | G44: ='C33 devsecops-roadmap'!$E$6 -> 0 | H44: ='C33 devsecops-roadmap'!$G$6 | I44: =IF(E44=0,"Chưa có module",IF(F44=E44,"Đã hoàn thành",IF(F44=0,"Chưa bắt đầu","Đang học"))) -> Chưa bắt đầu | J44: C33 devsecops-roadmap
A45: C34 | B45: blockchain-roadmap | C45: 03 - Hạ tầng, Mạng & An ninh | D45: 03 - Blockchain & Web3 | E45: ='C34 blockchain-roadmap'!$A$6 -> 1 | F45: ='C34 blockchain-roadmap'!$C$6 -> 0 | G45: ='C34 blockchain-roadmap'!$E$6 -> 0 | H45: ='C34 blockchain-roadmap'!$G$6 | I45: =IF(E45=0,"Chưa có module",IF(F45=E45,"Đã hoàn thành",IF(F45=0,"Chưa bắt đầu","Đang học"))) -> Chưa bắt đầu | J45: C34 blockchain-roadmap
A46: C35 | B46: Build a Design System - Full Course | C46: 04 - Thiết kế & Sáng tạo số | D46: 01 - UX-UI & Design Systems | E46: ='C35 Build a Design System - Ful'!$A$6 -> 9 | F46: ='C35 Build a Design System - Ful'!$C$6 -> 0 | G46: ='C35 Build a Design System - Ful'!$E$6 -> 0 | H46: ='C35 Build a Design System - Ful'!$G$6 | I46: =IF(E46=0,"Chưa có module",IF(F46=E46,"Đã hoàn thành",IF(F46=0,"Chưa bắt đầu","Đang học"))) -> Chưa bắt đầu | J46: C35 Build a Design System - Ful
A47: C36 | B47: Design System & Figma Variable Set Up - Full Tutorial | C47: 04 - Thiết kế & Sáng tạo số | D47: 01 - UX-UI & Design Systems | E47: ='C36 Design System & Figma Varia'!$A$6 -> 10 | F47: ='C36 Design System & Figma Varia'!$C$6 -> 0 | G47: ='C36 Design System & Figma Varia'!$E$6 -> 0 | H47: ='C36 Design System & Figma Varia'!$G$6 | I47: =IF(E47=0,"Chưa có module",IF(F47=E47,"Đã hoàn thành",IF(F47=0,"Chưa bắt đầu","Đang học"))) -> Chưa bắt đầu | J47: C36 Design System & Figma Varia
A48: C37 | B48: ux-design-roadmap | C48: 04 - Thiết kế & Sáng tạo số | D48: 01 - UX-UI & Design Systems | E48: ='C37 ux-design-roadmap'!$A$6 -> 1 | F48: ='C37 ux-design-roadmap'!$C$6 -> 0 | G48: ='C37 ux-design-roadmap'!$E$6 -> 0 | H48: ='C37 ux-design-roadmap'!$G$6 | I48: =IF(E48=0,"Chưa có module",IF(F48=E48,"Đã hoàn thành",IF(F48=0,"Chưa bắt đầu","Đang học"))) -> Chưa bắt đầu | J48: C37 ux-design-roadmap
A49: C38 | B49: The Complete Vibe coding for UX/UI Designers | C49: 04 - Thiết kế & Sáng tạo số | D49: 01 - UX-UI & Design Systems | E49: ='C38 The Complete Vibe coding fo'!$A$6 -> 14 | F49: ='C38 The Complete Vibe coding fo'!$C$6 -> 0 | G49: ='C38 The Complete Vibe coding fo'!$E$6 -> 0 | H49: ='C38 The Complete Vibe coding fo'!$G$6 | I49: =IF(E49=0,"Chưa có module",IF(F49=E49,"Đã hoàn thành",IF(F49=0,"Chưa bắt đầu","Đang học"))) -> Chưa bắt đầu | J49: C38 The Complete Vibe coding fo
A50: C39 | B50: Claude Code + Figma MCP Server for Design to Code | C50: 04 - Thiết kế & Sáng tạo số | D50: 02 - Figma & Design-to-Code | E50: ='C39 Claude Code + Figma MCP Ser'!$A$6 -> 1 | F50: ='C39 Claude Code + Figma MCP Ser'!$C$6 -> 0 | G50: ='C39 Claude Code + Figma MCP Ser'!$E$6 -> 0 | H50: ='C39 Claude Code + Figma MCP Ser'!$G$6 | I50: =IF(E50=0,"Chưa có module",IF(F50=E50,"Đã hoàn thành",IF(F50=0,"Chưa bắt đầu","Đang học"))) -> Chưa bắt đầu | J50: C39 Claude Code + Figma MCP Ser
A51: C40 | B51: Design to Code with Figma MCP and Cursor | C51: 04 - Thiết kế & Sáng tạo số | D51: 02 - Figma & Design-to-Code | E51: ='C40 Design to Code with Figma M'!$A$6 -> 1 | F51: ='C40 Design to Code with Figma M'!$C$6 -> 0 | G51: ='C40 Design to Code with Figma M'!$E$6 -> 0 | H51: ='C40 Design to Code with Figma M'!$G$6 | I51: =IF(E51=0,"Chưa có module",IF(F51=E51,"Đã hoàn thành",IF(F51=0,"Chưa bắt đầu","Đang học"))) -> Chưa bắt đầu | J51: C40 Design to Code with Figma M
A52: C41 | B52: Vibe-Coding Figma Design System Components with Cursor & Figma MCP | C52: 04 - Thiết kế & Sáng tạo số | D52: 02 - Figma & Design-to-Code | E52: ='C41 Vibe-Coding Figma Design Sy'!$A$6 -> 1 | F52: ='C41 Vibe-Coding Figma Design Sy'!$C$6 -> 0 | G52: ='C41 Vibe-Coding Figma Design Sy'!$E$6 -> 0 | H52: ='C41 Vibe-Coding Figma Design Sy'!$G$6 | I52: =IF(E52=0,"Chưa có module",IF(F52=E52,"Đã hoàn thành",IF(F52=0,"Chưa bắt đầu","Đang học"))) -> Chưa bắt đầu | J52: C41 Vibe-Coding Figma Design Sy
A53: C42 | B53: Figma to Angular Mastery: Design to Code with AI | C53: 04 - Thiết kế & Sáng tạo số | D53: 02 - Figma & Design-to-Code | E53: ='C42 Figma to Angular Mastery- D'!$A$6 -> 9 | F53: ='C42 Figma to Angular Mastery- D'!$C$6 -> 0 | G53: ='C42 Figma to Angular Mastery- D'!$E$6 -> 0 | H53: ='C42 Figma to Angular Mastery- D'!$G$6 | I53: =IF(E53=0,"Chưa có module",IF(F53=E53,"Đã hoàn thành",IF(F53=0,"Chưa bắt đầu","Đang học"))) -> Chưa bắt đầu | J53: C42 Figma to Angular Mastery- D
A54: C43 | B54: Converting Figma Designs to Code with Cursor + Figma MCP | C54: 04 - Thiết kế & Sáng tạo số | D54: 02 - Figma & Design-to-Code | E54: ='C43 Converting Figma Designs to'!$A$6 -> 1 | F54: ='C43 Converting Figma Designs to'!$C$6 -> 0 | G54: ='C43 Converting Figma Designs to'!$E$6 -> 0 | H54: ='C43 Converting Figma Designs to'!$G$6 | I54: =IF(E54=0,"Chưa có module",IF(F54=E54,"Đã hoàn thành",IF(F54=0,"Chưa bắt đầu","Đang học"))) -> Chưa bắt đầu | J54: C43 Converting Figma Designs to
A55: C44 | B55: From Figma to Cursor & Claude Code with MCP — Building Sidebling.com | C55: 04 - Thiết kế & Sáng tạo số | D55: 02 - Figma & Design-to-Code | E55: ='C44 From Figma to Cursor & Clau'!$A$6 -> 1 | F55: ='C44 From Figma to Cursor & Clau'!$C$6 -> 0 | G55: ='C44 From Figma to Cursor & Clau'!$E$6 -> 0 | H55: ='C44 From Figma to Cursor & Clau'!$G$6 | I55: =IF(E55=0,"Chưa có module",IF(F55=E55,"Đã hoàn thành",IF(F55=0,"Chưa bắt đầu","Đang học"))) -> Chưa bắt đầu | J55: C44 From Figma to Cursor & Clau
A56: C45 | B56: 01 - Blender tổng quát | C56: 04 - Thiết kế & Sáng tạo số | D56: 03 - Blender & 3D | E56: ='C45 01 - Blender tổng quát'!$A$6 -> 50 | F56: ='C45 01 - Blender tổng quát'!$C$6 -> 0 | G56: ='C45 01 - Blender tổng quát'!$E$6 -> 0 | H56: ='C45 01 - Blender tổng quát'!$G$6 | I56: =IF(E56=0,"Chưa có module",IF(F56=E56,"Đã hoàn thành",IF(F56=0,"Chưa bắt đầu","Đang học"))) -> Chưa bắt đầu | J56: C45 01 - Blender tổng quát
A57: C46 | B57: 02 - Animation cá trong Blender | C57: 04 - Thiết kế & Sáng tạo số | D57: 03 - Blender & 3D | E57: ='C46 02 - Animation cá trong Ble'!$A$6 -> 4 | F57: ='C46 02 - Animation cá trong Ble'!$C$6 -> 0 | G57: ='C46 02 - Animation cá trong Ble'!$E$6 -> 0 | H57: ='C46 02 - Animation cá trong Ble'!$G$6 | I57: =IF(E57=0,"Chưa có module",IF(F57=E57,"Đã hoàn thành",IF(F57=0,"Chưa bắt đầu","Đang học"))) -> Chưa bắt đầu | J57: C46 02 - Animation cá trong Ble
A58: C47 | B58: 03 - VFX & mô phỏng Blender | C58: 04 - Thiết kế & Sáng tạo số | D58: 03 - Blender & 3D | E58: ='C47 03 - VFX & mô phỏng Blender'!$A$6 -> 4 | F58: ='C47 03 - VFX & mô phỏng Blender'!$C$6 -> 0 | G58: ='C47 03 - VFX & mô phỏng Blender'!$E$6 -> 0 | H58: ='C47 03 - VFX & mô phỏng Blender'!$G$6 | I58: =IF(E58=0,"Chưa có module",IF(F58=E58,"Đã hoàn thành",IF(F58=0,"Chưa bắt đầu","Đang học"))) -> Chưa bắt đầu | J58: C47 03 - VFX & mô phỏng Blender
A59: C48 | B59: 04 - Giải phẫu & phát triển bộ xương cá | C59: 04 - Thiết kế & Sáng tạo số | D59: 03 - Blender & 3D | E59: ='C48 04 - Giải phẫu & phát triển'!$A$6 -> 12 | F59: ='C48 04 - Giải phẫu & phát triển'!$C$6 -> 0 | G59: ='C48 04 - Giải phẫu & phát triển'!$E$6 -> 0 | H59: ='C48 04 - Giải phẫu & phát triển'!$G$6 | I59: =IF(E59=0,"Chưa có module",IF(F59=E59,"Đã hoàn thành",IF(F59=0,"Chưa bắt đầu","Đang học"))) -> Chưa bắt đầu | J59: C48 04 - Giải phẫu & phát triển
A60: C49 | B60: 05 - Cơ học & thủy động lực học bơi cá | C60: 04 - Thiết kế & Sáng tạo số | D60: 03 - Blender & 3D | E60: ='C49 05 - Cơ học & thủy động lực'!$A$6 -> 19 | F60: ='C49 05 - Cơ học & thủy động lực'!$C$6 -> 0 | G60: ='C49 05 - Cơ học & thủy động lực'!$E$6 -> 0 | H60: ='C49 05 - Cơ học & thủy động lực'!$G$6 | I60: =IF(E60=0,"Chưa có module",IF(F60=E60,"Đã hoàn thành",IF(F60=0,"Chưa bắt đầu","Đang học"))) -> Chưa bắt đầu | J60: C49 05 - Cơ học & thủy động lực
A61: C50 | B61: Complete C# Unity 2D Game Development - Updated To Unity 6 | C61: 05 - Phát triển game | D61: 01 - Unity & C# | E61: ='C50 Complete C# Unity 2D Game D'!$A$6 -> 6 | F61: ='C50 Complete C# Unity 2D Game D'!$C$6 -> 0 | G61: ='C50 Complete C# Unity 2D Game D'!$E$6 -> 0 | H61: ='C50 Complete C# Unity 2D Game D'!$G$6 | I61: =IF(E61=0,"Chưa có module",IF(F61=E61,"Đã hoàn thành",IF(F61=0,"Chưa bắt đầu","Đang học"))) -> Chưa bắt đầu | J61: C50 Complete C# Unity 2D Game D
A62: C51 | B62: Complete C# Unity 3D Game Development in Unity 6 | C62: 05 - Phát triển game | D62: 01 - Unity & C# | E62: ='C51 Complete C# Unity 3D Game D'!$A$6 -> 7 | F62: ='C51 Complete C# Unity 3D Game D'!$C$6 -> 0 | G62: ='C51 Complete C# Unity 3D Game D'!$E$6 -> 0 | H62: ='C51 Complete C# Unity 3D Game D'!$G$6 | I62: =IF(E62=0,"Chưa có module",IF(F62=E62,"Đã hoàn thành",IF(F62=0,"Chưa bắt đầu","Đang học"))) -> Chưa bắt đầu | J62: C51 Complete C# Unity 3D Game D
A63: C52 | B63: Mastering Ren'Py: Create Visual Novels Like a Pro | C63: 05 - Phát triển game | D63: 02 - Ren'Py & Visual Novels | E63: ='C52 Mastering Ren''Py- Create Vi'!$A$6 -> 2 | F63: ='C52 Mastering Ren''Py- Create Vi'!$C$6 -> 0 | G63: ='C52 Mastering Ren''Py- Create Vi'!$E$6 -> 0 | H63: ='C52 Mastering Ren''Py- Create Vi'!$G$6 | I63: =IF(E63=0,"Chưa có module",IF(F63=E63,"Đã hoàn thành",IF(F63=0,"Chưa bắt đầu","Đang học"))) -> Chưa bắt đầu | J63: C52 Mastering Ren'Py- Create Vi
A64: C53 | B64: Python Basics for Ren'Py Developers | C64: 05 - Phát triển game | D64: 02 - Ren'Py & Visual Novels | E64: ='C53 Python Basics for Ren''Py De'!$A$6 -> 6 | F64: ='C53 Python Basics for Ren''Py De'!$C$6 -> 0 | G64: ='C53 Python Basics for Ren''Py De'!$E$6 -> 0 | H64: ='C53 Python Basics for Ren''Py De'!$G$6 | I64: =IF(E64=0,"Chưa có module",IF(F64=E64,"Đã hoàn thành",IF(F64=0,"Chưa bắt đầu","Đang học"))) -> Chưa bắt đầu | J64: C53 Python Basics for Ren'Py De
A65: C54 | B65: Ren'Py Minigames 101 | C65: 05 - Phát triển game | D65: 02 - Ren'Py & Visual Novels | E65: ='C54 Ren''Py Minigames 101'!$A$6 -> 4 | F65: ='C54 Ren''Py Minigames 101'!$C$6 -> 0 | G65: ='C54 Ren''Py Minigames 101'!$E$6 -> 0 | H65: ='C54 Ren''Py Minigames 101'!$G$6 | I65: =IF(E65=0,"Chưa có module",IF(F65=E65,"Đã hoàn thành",IF(F65=0,"Chưa bắt đầu","Đang học"))) -> Chưa bắt đầu | J65: C54 Ren'Py Minigames 101
A66: C55 | B66: Indie Game Design - Build Your Game's Core System | C66: 05 - Phát triển game | D66: 03 - Game Design | E66: ='C55 Indie Game Design - Build Y'!$A$6 -> 8 | F66: ='C55 Indie Game Design - Build Y'!$C$6 -> 0 | G66: ='C55 Indie Game Design - Build Y'!$E$6 -> 0 | H66: ='C55 Indie Game Design - Build Y'!$G$6 | I66: =IF(E66=0,"Chưa có module",IF(F66=E66,"Đã hoàn thành",IF(F66=0,"Chưa bắt đầu","Đang học"))) -> Chưa bắt đầu | J66: C55 Indie Game Design - Build Y
A67: C56 | B67: game-developer-roadmap | C67: 05 - Phát triển game | D67: 04 - Game Development Roadmaps | E67: ='C56 game-developer-roadmap'!$A$6 -> 1 | F67: ='C56 game-developer-roadmap'!$C$6 -> 0 | G67: ='C56 game-developer-roadmap'!$E$6 -> 0 | H67: ='C56 game-developer-roadmap'!$G$6 | I67: =IF(E67=0,"Chưa có module",IF(F67=E67,"Đã hoàn thành",IF(F67=0,"Chưa bắt đầu","Đang học"))) -> Chưa bắt đầu | J67: C56 game-developer-roadmap
A68: C57 | B68: server-side-game-developer-roadmap | C68: 05 - Phát triển game | D68: 04 - Game Development Roadmaps | E68: ='C57 server-side-game-developer-'!$A$6 -> 1 | F68: ='C57 server-side-game-developer-'!$C$6 -> 0 | G68: ='C57 server-side-game-developer-'!$E$6 -> 0 | H68: ='C57 server-side-game-developer-'!$G$6 | I68: =IF(E68=0,"Chưa có module",IF(F68=E68,"Đã hoàn thành",IF(F68=0,"Chưa bắt đầu","Đang học"))) -> Chưa bắt đầu | J68: C57 server-side-game-developer-
A69: C58 | B69: Pixel Art Master Course - Beginner to Professional/Freelance | C69: 05 - Phát triển game | D69: 05 - Game Art | E69: ='C58 Pixel Art Master Course - B'!$A$6 -> 20 | F69: ='C58 Pixel Art Master Course - B'!$C$6 -> 0 | G69: ='C58 Pixel Art Master Course - B'!$E$6 -> 0 | H69: ='C58 Pixel Art Master Course - B'!$G$6 | I69: =IF(E69=0,"Chưa có module",IF(F69=E69,"Đã hoàn thành",IF(F69=0,"Chưa bắt đầu","Đang học"))) -> Chưa bắt đầu | J69: C58 Pixel Art Master Course - B
A70: C59 | B70: The English Master Course: English Grammar, English Speaking | C70: 06 - Ngôn ngữ | D70: 01 - Tiếng Anh | E70: ='C59 The English Master Course-'!$A$6 -> 6 | F70: ='C59 The English Master Course-'!$C$6 -> 0 | G70: ='C59 The English Master Course-'!$E$6 -> 0 | H70: ='C59 The English Master Course-'!$G$6 | I70: =IF(E70=0,"Chưa có module",IF(F70=E70,"Đã hoàn thành",IF(F70=0,"Chưa bắt đầu","Đang học"))) -> Chưa bắt đầu | J70: C59 The English Master Course-
A71: C60 | B71: Tự học 2.000 từ vựng tiếng Anh | C71: 06 - Ngôn ngữ | D71: 01 - Tiếng Anh | E71: ='C60 Tự học 2.000 từ vựng tiếng'!$A$6 -> 6 | F71: ='C60 Tự học 2.000 từ vựng tiếng'!$C$6 -> 0 | G71: ='C60 Tự học 2.000 từ vựng tiếng'!$E$6 -> 0 | H71: ='C60 Tự học 2.000 từ vựng tiếng'!$G$6 | I71: =IF(E71=0,"Chưa có module",IF(F71=E71,"Đã hoàn thành",IF(F71=0,"Chưa bắt đầu","Đang học"))) -> Chưa bắt đầu | J71: C60 Tự học 2.000 từ vựng tiếng
A72: C61 | B72: Từ vựng tiếng Anh cơ bản | C72: 06 - Ngôn ngữ | D72: 01 - Tiếng Anh | E72: ='C61 Từ vựng tiếng Anh cơ bản'!$A$6 -> 1 | F72: ='C61 Từ vựng tiếng Anh cơ bản'!$C$6 -> 0 | G72: ='C61 Từ vựng tiếng Anh cơ bản'!$E$6 -> 0 | H72: ='C61 Từ vựng tiếng Anh cơ bản'!$G$6 | I72: =IF(E72=0,"Chưa có module",IF(F72=E72,"Đã hoàn thành",IF(F72=0,"Chưa bắt đầu","Đang học"))) -> Chưa bắt đầu | J72: C61 Từ vựng tiếng Anh cơ bản
A73: C62 | B73: Khóa học Tiếng Trung — Giáo trình Hán Ngữ Quyển 1–6 | C73: 06 - Ngôn ngữ | D73: 02 - Tiếng Trung | E73: ='C62 Khóa học Tiếng Trung — Giáo'!$A$6 -> 6 | F73: ='C62 Khóa học Tiếng Trung — Giáo'!$C$6 -> 0 | G73: ='C62 Khóa học Tiếng Trung — Giáo'!$E$6 -> 0 | H73: ='C62 Khóa học Tiếng Trung — Giáo'!$G$6 | I73: =IF(E73=0,"Chưa có module",IF(F73=E73,"Đã hoàn thành",IF(F73=0,"Chưa bắt đầu","Đang học"))) -> Chưa bắt đầu | J73: C62 Khóa học Tiếng Trung — Giáo
A74: C63 | B74: Mandarin Mastery Path — Tiếng Trung từ Nền tảng đến HSK 3 | C74: 06 - Ngôn ngữ | D74: 02 - Tiếng Trung | E74: ='C63 Mandarin Mastery Path — Tiế'!$A$6 -> 56 | F74: ='C63 Mandarin Mastery Path — Tiế'!$C$6 -> 0 | G74: ='C63 Mandarin Mastery Path — Tiế'!$E$6 -> 0 | H74: ='C63 Mandarin Mastery Path — Tiế'!$G$6 | I74: =IF(E74=0,"Chưa có module",IF(F74=E74,"Đã hoàn thành",IF(F74=0,"Chưa bắt đầu","Đang học"))) -> Chưa bắt đầu | J74: C63 Mandarin Mastery Path — Tiế
A75: C64 | B75: Learn Japanese for Beginners — Khóa học Markdown | C75: 06 - Ngôn ngữ | D75: 03 - Tiếng Nhật | E75: ='C64 Learn Japanese for Beginner'!$A$6 -> 15 | F75: ='C64 Learn Japanese for Beginner'!$C$6 -> 0 | G75: ='C64 Learn Japanese for Beginner'!$E$6 -> 0 | H75: ='C64 Learn Japanese for Beginner'!$G$6 | I75: =IF(E75=0,"Chưa có module",IF(F75=E75,"Đã hoàn thành",IF(F75=0,"Chưa bắt đầu","Đang học"))) -> Chưa bắt đầu | J75: C64 Learn Japanese for Beginner
A76: C65 | B76: Complete French Course — Khóa học Markdown | C76: 06 - Ngôn ngữ | D76: 04 - Tiếng Pháp | E76: ='C65 Complete French Course — Kh'!$A$6 -> 7 | F76: ='C65 Complete French Course — Kh'!$C$6 -> 0 | G76: ='C65 Complete French Course — Kh'!$E$6 -> 0 | H76: ='C65 Complete French Course — Kh'!$G$6 | I76: =IF(E76=0,"Chưa có module",IF(F76=E76,"Đã hoàn thành",IF(F76=0,"Chưa bắt đầu","Đang học"))) -> Chưa bắt đầu | J76: C65 Complete French Course — Kh
A77: C66 | B77: Tiếng Đức giao tiếp từ A1 đến B1 | C77: 06 - Ngôn ngữ | D77: 05 - Tiếng Đức | E77: ='C66 Tiếng Đức giao tiếp từ A1 đ'!$A$6 -> 321 | F77: ='C66 Tiếng Đức giao tiếp từ A1 đ'!$C$6 -> 0 | G77: ='C66 Tiếng Đức giao tiếp từ A1 đ'!$E$6 -> 0 | H77: ='C66 Tiếng Đức giao tiếp từ A1 đ'!$G$6 | I77: =IF(E77=0,"Chưa có module",IF(F77=E77,"Đã hoàn thành",IF(F77=0,"Chưa bắt đầu","Đang học"))) -> Chưa bắt đầu | J77: C66 Tiếng Đức giao tiếp từ A1 đ
A78: C67 | B78: Khóa học Tiếng Hàn toàn diện cho người mới bắt đầu | C78: 06 - Ngôn ngữ | D78: 06 - Tiếng Hàn | E78: ='C67 Khóa học Tiếng Hàn toàn diệ'!$A$6 -> 82 | F78: ='C67 Khóa học Tiếng Hàn toàn diệ'!$C$6 -> 0 | G78: ='C67 Khóa học Tiếng Hàn toàn diệ'!$E$6 -> 0 | H78: ='C67 Khóa học Tiếng Hàn toàn diệ'!$G$6 | I78: =IF(E78=0,"Chưa có module",IF(F78=E78,"Đã hoàn thành",IF(F78=0,"Chưa bắt đầu","Đang học"))) -> Chưa bắt đầu | J78: C67 Khóa học Tiếng Hàn toàn diệ
A79: C68 | B79: engineering-manager-roadmap | C79: 07 - Kinh doanh & Quản lý | D79: 01 - Product & Engineering Management | E79: ='C68 engineering-manager-roadmap'!$A$6 -> 1 | F79: ='C68 engineering-manager-roadmap'!$C$6 -> 0 | G79: ='C68 engineering-manager-roadmap'!$E$6 -> 0 | H79: ='C68 engineering-manager-roadmap'!$G$6 | I79: =IF(E79=0,"Chưa có module",IF(F79=E79,"Đã hoàn thành",IF(F79=0,"Chưa bắt đầu","Đang học"))) -> Chưa bắt đầu | J79: C68 engineering-manager-roadmap
A80: C69 | B80: product-manager-roadmap | C80: 07 - Kinh doanh & Quản lý | D80: 01 - Product & Engineering Management | E80: ='C69 product-manager-roadmap'!$A$6 -> 2 | F80: ='C69 product-manager-roadmap'!$C$6 -> 0 | G80: ='C69 product-manager-roadmap'!$E$6 -> 0 | H80: ='C69 product-manager-roadmap'!$G$6 | I80: =IF(E80=0,"Chưa có module",IF(F80=E80,"Đã hoàn thành",IF(F80=0,"Chưa bắt đầu","Đang học"))) -> Chưa bắt đầu | J80: C69 product-manager-roadmap
A81: C70 | B81: devrel-roadmap | C81: 07 - Kinh doanh & Quản lý | D81: 02 - Developer Relations & Technical Writing | E81: ='C70 devrel-roadmap'!$A$6 -> 2 | F81: ='C70 devrel-roadmap'!$C$6 -> 0 | G81: ='C70 devrel-roadmap'!$E$6 -> 0 | H81: ='C70 devrel-roadmap'!$G$6 | I81: =IF(E81=0,"Chưa có module",IF(F81=E81,"Đã hoàn thành",IF(F81=0,"Chưa bắt đầu","Đang học"))) -> Chưa bắt đầu | J81: C70 devrel-roadmap
A82: C71 | B82: technical-writer-roadmap | C82: 07 - Kinh doanh & Quản lý | D82: 02 - Developer Relations & Technical Writing | E82: ='C71 technical-writer-roadmap'!$A$6 -> 1 | F82: ='C71 technical-writer-roadmap'!$C$6 -> 0 | G82: ='C71 technical-writer-roadmap'!$E$6 -> 0 | H82: ='C71 technical-writer-roadmap'!$G$6 | I82: =IF(E82=0,"Chưa có module",IF(F82=E82,"Đã hoàn thành",IF(F82=0,"Chưa bắt đầu","Đang học"))) -> Chưa bắt đầu | J82: C71 technical-writer-roadmap
A83: C72 | B83: nutrition-masterclass-build-your-perfect-diet-meal-plan | C83: 08 - Sức khỏe & Đời sống | D83: 01 - Dinh dưỡng | E83: ='C72 nutrition-masterclass-build'!$A$6 -> 10 | F83: ='C72 nutrition-masterclass-build'!$C$6 -> 0 | G83: ='C72 nutrition-masterclass-build'!$E$6 -> 0 | H83: ='C72 nutrition-masterclass-build'!$G$6 | I83: =IF(E83=0,"Chưa có module",IF(F83=E83,"Đã hoàn thành",IF(F83=0,"Chưa bắt đầu","Đang học"))) -> Chưa bắt đầu | J83: C72 nutrition-masterclass-build
A84: C73 | B84: Creative Writing: How to Write a Novel - The Full Course | C84: 09 - Viết & Sáng tác | D84: 01 - Viết tiểu thuyết | E84: ='C73 Creative Writing- How to Wr'!$A$6 -> 4 | F84: ='C73 Creative Writing- How to Wr'!$C$6 -> 0 | G84: ='C73 Creative Writing- How to Wr'!$E$6 -> 0 | H84: ='C73 Creative Writing- How to Wr'!$G$6 | I84: =IF(E84=0,"Chưa có module",IF(F84=E84,"Đã hoàn thành",IF(F84=0,"Chưa bắt đầu","Đang học"))) -> Chưa bắt đầu | J84: C73 Creative Writing- How to Wr
A85: C74 | B85: Tự học phát âm tiếng Anh | C85: 06 - Ngôn ngữ | D85: 01 - Tiếng Anh | E85: ='C74 Tự học phát âm tiếng Anh'!$A$6 -> 7 | F85: ='C74 Tự học phát âm tiếng Anh'!$C$6 -> 0 | G85: ='C74 Tự học phát âm tiếng Anh'!$E$6 -> 0 | H85: ='C74 Tự học phát âm tiếng Anh'!$G$6 | I85: =IF(E85=0,"Chưa có module",IF(F85=E85,"Đã hoàn thành",IF(F85=0,"Chưa bắt đầu","Đang học"))) -> Chưa bắt đầu | J85: C74 Tự học phát âm tiếng Anh
A86: C75 | B86: English Pronunciation — Khóa học Markdown | C86: 06 - Ngôn ngữ | D86: 01 - Tiếng Anh | E86: ='C75 English Pronunciation'!$A$6 -> 7 | F86: ='C75 English Pronunciation'!$C$6 -> 0 | G86: ='C75 English Pronunciation'!$E$6 -> 0 | H86: ='C75 English Pronunciation'!$G$6 | I86: =IF(E86=0,"Chưa có module",IF(F86=E86,"Đã hoàn thành",IF(F86=0,"Chưa bắt đầu","Đang học"))) -> Chưa bắt đầu | J86: C75 English Pronunciation
A87: C76 | B87: Tự học phát âm tiếng Anh — Nền tảng cho kỹ năng đọc | C87: 06 - Ngôn ngữ | D87: 01 - Tiếng Anh | E87: ='C76 Phát âm — Kỹ năng đọc'!$A$6 -> 9 | F87: ='C76 Phát âm — Kỹ năng đọc'!$C$6 -> 0 | G87: ='C76 Phát âm — Kỹ năng đọc'!$E$6 -> 0 | H87: ='C76 Phát âm — Kỹ năng đọc'!$G$6 | I87: =IF(E87=0,"Chưa có module",IF(F87=E87,"Đã hoàn thành",IF(F87=0,"Chưa bắt đầu","Đang học"))) -> Chưa bắt đầu | J87: C76 Phát âm — Kỹ năng đọc
A88: C77 | B88: AlphaAgent — LLM-Driven Alpha Mining và chống Alpha Decay | C88: 01 - AI & Dữ liệu | D88: 01 - AI Engineering & LLM | E88: ='C77 AlphaAgent — Alpha Mining'!$A$6 -> 1 | F88: ='C77 AlphaAgent — Alpha Mining'!$C$6 -> 0 | G88: ='C77 AlphaAgent — Alpha Mining'!$E$6 -> 0 | H88: ='C77 AlphaAgent — Alpha Mining'!$G$6 | I88: =IF(E88=0,"Chưa có module",IF(F88=E88,"Đã hoàn thành",IF(F88=0,"Chưa bắt đầu","Đang học"))) -> Chưa bắt đầu | J88: C77 AlphaAgent — Alpha Mining

Sheet HƯỚNG DẪN
A1: HƯỚNG DẪN SỬ DỤNG
A3: Mục đích
A4: Workbook này theo dõi tiến độ theo khóa học và module. Các ô nền vàng là nơi nhập liệu; các ô KPI và Tổng quan tự tính bằng công thức.
A6: Cách cập nhật tiến độ
A7: 1 | B7: Mở sheet của khóa học cần học trong danh sách tab phía dưới.
A8: 2 | B8: Ở từng module, chọn Trạng thái, nhập Tiến độ (%) và Điểm /10; điền Ngày hoàn thành khi kết thúc.
A9: 3 | B9: Xem sheet TỔNG QUAN để biết tiến độ toàn bộ kho và tiến độ theo từng lĩnh vực.
A10: 4 | B10: Không sửa các ô KPI/công thức; chỉ sửa các ô nền vàng và cột Ghi chú.
A11: 5 | B11: Điểm dùng thang 0–10; Tiến độ dùng phần trăm 0%–100%.
A13: Quy ước trạng thái
A14: Trạng thái
A15: Chưa bắt đầu | B15: Chưa học module
A16: Đang học | B16: Đang học hoặc đã học một phần
A17: Đã hoàn thành | B17: Đã hoàn thành module
A18: Tạm dừng | B18: Tạm thời chưa học tiếp
A20: Thêm khóa học mới
A21: Khi thêm một thư mục khóa học mới vào kho, hãy tạo một sheet mới bằng cách sao chép MẪU_KHÓA_MỚI, đổi tên theo mã khóa và nhập các module. Khi bạn báo có khóa mới, mình sẽ tạo sheet tương ứng và cập nhật TỔNG QUAN.
A25: Lưu ý: file .xlsx không tự theo dõi thay đổi của thư mục Windows. Sheet MẪU_KHÓA_MỚI giúp thêm sheet mới thống nhất và không phá công thức.

Sheet C74 Tự học phát âm tiếng Anh
A1: THEO DÕI KHÓA HỌC — Tự học phát âm tiếng Anh
A2: Mã khóa | B2: C74 | C2: Lĩnh vực | D2: 06 - Ngôn ngữ | E2: Chuyên ngành | F2: 01 - Tiếng Anh
A3: Thư mục nguồn | B3: D:\Sao lưu\Udemy\Khóa học\06 - Ngôn ngữ\01 - Tiếng Anh\tu-hoc-phat-am-tieng-anh-markdown.zip
A5: TỔNG MODULE | C5: ĐÃ HOÀN THÀNH | E5: TIẾN ĐỘ TRUNG BÌNH | G5: ĐIỂM TRUNG BÌNH
A6: =COUNTA(B10:B16) -> 7 | C6: =COUNTIF(D10:D16,"Đã hoàn thành") -> 0 | E6: =IFERROR(AVERAGE(E10:E16),0) -> 0 | G6: =IFERROR(AVERAGE(F10:F16),"")
A8: Sao chép sheet này khi thêm khóa mới. Mỗi dòng là một module; nhập trạng thái, tiến độ, điểm và ngày hoàn thành.
A9: STT | B9: Module | C9: Số bài | D9: Trạng thái | E9: Tiến độ (%) | F9: Điểm /10 | G9: Ngày hoàn thành | H9: Ghi chú
A10: =1 -> 1 | B10: Module 01 — Nền tảng và nguyên âm đơn | C10: =4 -> 4 | D10: Chưa bắt đầu | E10: =0 -> 0
A11: =2 -> 2 | B11: Module 02 — Nguyên âm đôi và tổng kết nguyên âm | C11: =4 -> 4 | D11: Chưa bắt đầu | E11: =0 -> 0
A12: =3 -> 3 | B12: Module 03 — Hệ thống phụ âm tiếng Anh | C12: =7 -> 7 | D12: Chưa bắt đầu | E12: =0 -> 0
A13: =4 -> 4 | B13: Module 04 — Biến thể và tổ hợp phụ âm | C13: =3 -> 3 | D13: Chưa bắt đầu | E13: =0 -> 0
A14: =5 -> 5 | B14: Module 05 — Nói tự nhiên: nối âm, trọng âm và ngữ điệu | C14: =5 -> 5 | D14: Chưa bắt đầu | E14: =0 -> 0
A15: =6 -> 6 | B15: Module 06 — Luyện tập tổng hợp | C15: =8 -> 8 | D15: Chưa bắt đầu | E15: =0 -> 0
A16: =7 -> 7 | B16: Module 07 — So sánh giọng Anh–Anh và Anh–Mỹ | C16: =1 -> 1 | D16: Chưa bắt đầu | E16: =0 -> 0
A17: 8 | D17: Chưa bắt đầu | E17: 0
A18: 9 | D18: Chưa bắt đầu | E18: 0
A19: 10 | D19: Chưa bắt đầu | E19: 0
A20: 11 | D20: Chưa bắt đầu | E20: 0
A21: 12 | D21: Chưa bắt đầu | E21: 0
A22: 13 | D22: Chưa bắt đầu | E22: 0
A23: 14 | D23: Chưa bắt đầu | E23: 0
A24: 15 | D24: Chưa bắt đầu | E24: 0
A25: 16 | D25: Chưa bắt đầu | E25: 0
A26: 17 | D26: Chưa bắt đầu | E26: 0
A27: 18 | D27: Chưa bắt đầu | E27: 0
A28: 19 | D28: Chưa bắt đầu | E28: 0
... A209: 200 | D209: Chưa bắt đầu | E209: 0

Sheet MẪU_KHÓA_MỚI
A1: MẪU THEO DÕI KHÓA MỚI
A2: Mã khóa | B2: Cxx | C2: Lĩnh vực | E2: Chuyên ngành
A3: Thư mục nguồn | B3: Dán đường dẫn thư mục khóa học tại đây
A5: TỔNG MODULE | C5: ĐÃ HOÀN THÀNH | E5: TIẾN ĐỘ TRUNG BÌNH | G5: ĐIỂM TRUNG BÌNH
A6: =COUNTA(B10:B209) -> 0 | C6: =COUNTIF(D10:D209,"Đã hoàn thành") -> 0 | E6: =IFERROR(AVERAGE(E10:E209),0) -> 0 | G6: =IFERROR(AVERAGE(F10:F209),"")
A8: Sao chép sheet này khi thêm khóa mới. Mỗi dòng là một module; nhập trạng thái, tiến độ, điểm và ngày hoàn thành.
A9: STT | B9: Module | C9: Số bài | D9: Trạng thái | E9: Tiến độ (%) | F9: Điểm /10 | G9: Ngày hoàn thành | H9: Ghi chú
A10: 1 | D10: Chưa bắt đầu | E10: 0
A11: 2 | D11: Chưa bắt đầu | E11: 0
A12: 3 | D12: Chưa bắt đầu | E12: 0
A13: 4 | D13: Chưa bắt đầu | E13: 0
A14: 5 | D14: Chưa bắt đầu | E14: 0
A15: 6 | D15: Chưa bắt đầu | E15: 0
A16: 7 | D16: Chưa bắt đầu | E16: 0
A17: 8 | D17: Chưa bắt đầu | E17: 0
A18: 9 | D18: Chưa bắt đầu | E18: 0
A19: 10 | D19: Chưa bắt đầu | E19: 0
A20: 11 | D20: Chưa bắt đầu | E20: 0
A21: 12 | D21: Chưa bắt đầu | E21: 0
... A209: 200 | D209: Chưa bắt đầu | E209: 0

Sheet C73 Creative Writing- How to Wr
A1: THEO DÕI KHÓA HỌC — Creative Writing: How to Write a Novel - The Full Course
A2: Mã khóa | B2: C73 | C2: Lĩnh vực | D2: 09 - Viết & Sáng tác | E2: Chuyên ngành | F2: 01 - Viết tiểu thuyết
A3: Thư mục nguồn | B3: D:\Sao lưu\Udemy\Khóa học\09 - Viết & Sáng tác\01 - Viết tiểu thuyết\creative-writing-how-to-write-a-novel
A5: TỔNG MODULE | C5: ĐÃ HOÀN THÀNH | E5: TIẾN ĐỘ TRUNG BÌNH | G5: ĐIỂM TRUNG BÌNH
A6: =COUNTA(B10:B13) -> 4 | C6: =COUNTIF(D10:D13,"Đã hoàn thành") -> 0 | E6: =IFERROR(AVERAGE(E10:E13),0) -> 0 | G6: =IFERROR(AVERAGE(F10:F13),"")
A8: Nhập Trạng thái, Tiến độ và Điểm ở các ô nền vàng. Tiến độ nhập từ 0% đến 100%; điểm từ 0 đến 10.
A9: STT | B9: Module | C9: Số bài | D9: Trạng thái | E9: Tiến độ (%) | F9: Điểm /10 | G9: Ngày hoàn thành | H9: Ghi chú
A10: 1 | B10: 01 - The Character | C10: 31 | D10: Chưa bắt đầu | E10: 0
A11: 2 | B11: 02 - The 3 Act Narrative Structure | C11: 20 | D11: Chưa bắt đầu | E11: 0
A12: 3 | B12: 03 - Show, Don't Tell | C12: 14 | D12: Chưa bắt đầu | E12: 0
A13: 4 | B13: 04 - Dialogue | C13: 12 | D13: Chưa bắt đầu | E13: 0

Sheet C72 nutrition-masterclass-build
A1: THEO DÕI KHÓA HỌC — nutrition-masterclass-build-your-perfect-diet-meal-plan
A2: Mã khóa | B2: C72 | C2: Lĩnh vực | D2: 08 - Sức khỏe & Đời sống | E2: Chuyên ngành | F2: 01 - Dinh dưỡng
A3: Thư mục nguồn | B3: D:\Sao lưu\Udemy\Khóa học\08 - Sức khỏe & Đời sống\01 - Dinh dưỡng\nutrition-masterclass-build-your-perfect-diet-meal-plan
A5: TỔNG MODULE | C5: ĐÃ HOÀN THÀNH | E5: TIẾN ĐỘ TRUNG BÌNH | G5: ĐIỂM TRUNG BÌNH
A6: =COUNTA(B10:B19) -> 10 | C6: =COUNTIF(D10:D19,"Đã hoàn thành") -> 0 | E6: =IFERROR(AVERAGE(E10:E19),0) -> 0 | G6: =IFERROR(AVERAGE(F10:F19),"")
A8: Nhập Trạng thái, Tiến độ và Điểm ở các ô nền vàng. Tiến độ nhập từ 0% đến 100%; điểm từ 0 đến 10.
A9: STT | B9: Module | C9: Số bài | D9: Trạng thái | E9: Tiến độ (%) | F9: Điểm /10 | G9: Ngày hoàn thành | H9: Ghi chú
A10: 1 | B10: 01 - Introduction | C10: 3 | D10: Chưa bắt đầu | E10: 0
A11: 2 | B11: 02 - Meal Planning Basics | C11: 21 | D11: Chưa bắt đầu | E11: 0
A12: 3 | B12: 03 - Supplements | C12: 7 | D12: Chưa bắt đầu | E12: 0
A13: 4 | B13: 04 - Setting Up Your Diet | C13: 13 | D13: Chưa bắt đầu | E13: 0
A14: 5 | B14: 05 - Adjusting Your Diet for Weight Loss and Muscle Gains | C14: 7 | D14: Chưa bắt đầu | E14: 0
A15: 6 | B15: 06 - Healthy Dieting | C15: 9 | D15: Chưa bắt đầu | E15: 0
A16: 7 | B16: 07 - Common Dieting Trends Explained | C16: 7 | D16: Chưa bắt đầu | E16: 0
A17: 8 | B17: 08 - Micronutrients | C17: 16 | D17: Chưa bắt đầu | E17: 0
A18: 9 | B18: 09 - More Dieting Tips and Strategies | C18: 7 | D18: Chưa bắt đầu | E18: 0
A19: 10 | B19: 10 - Bonus Lessons on Muscle Growth | C19: 4 | D19: Chưa bắt đầu | E19: 0

Sheet C71 technical-writer-roadmap
A1: THEO DÕI KHÓA HỌC — technical-writer-roadmap
A2: Mã khóa | B2: C71 | C2: Lĩnh vực | D2: 07 - Kinh doanh & Quản lý | E2: Chuyên ngành | F2: 02 - Developer Relations & Technical Writing
A3: Thư mục nguồn | B3: D:\Sao lưu\Udemy\Khóa học\07 - Kinh doanh & Quản lý\02 - Developer Relations & Technical Writing\technical-writer-roadmap
A5: TỔNG MODULE | C5: ĐÃ HOÀN THÀNH | E5: TIẾN ĐỘ TRUNG BÌNH | G5: ĐIỂM TRUNG BÌNH
A6: =COUNTA(B10:B10) -> 1 | C6: =COUNTIF(D10:D10,"Đã hoàn thành") -> 0 | E6: =IFERROR(AVERAGE(E10:E10),0) -> 0 | G6: =IFERROR(AVERAGE(F10:F10),"")
A8: Nhập Trạng thái, Tiến độ và Điểm ở các ô nền vàng. Tiến độ nhập từ 0% đến 100%; điểm từ 0 đến 10.
A9: STT | B9: Module | C9: Số bài | D9: Trạng thái | E9: Tiến độ (%) | F9: Điểm /10 | G9: Ngày hoàn thành | H9: Ghi chú
A10: 1 | B10: 00 - Roadmap.sh Technical Writer Official | C10: 59 | D10: Chưa bắt đầu | E10: 0

Sheet C70 devrel-roadmap
A1: THEO DÕI KHÓA HỌC — devrel-roadmap
A2: Mã khóa | B2: C70 | C2: Lĩnh vực | D2: 07 - Kinh doanh & Quản lý | E2: Chuyên ngành | F2: 02 - Developer Relations & Technical Writing
A3: Thư mục nguồn | B3: D:\Sao lưu\Udemy\Khóa học\07 - Kinh doanh & Quản lý\02 - Developer Relations & Technical Writing\devrel-roadmap
A5: TỔNG MODULE | C5: ĐÃ HOÀN THÀNH | E5: TIẾN ĐỘ TRUNG BÌNH | G5: ĐIỂM TRUNG BÌNH
A6: =COUNTA(B10:B11) -> 2 | C6: =COUNTIF(D10:D11,"Đã hoàn thành") -> 0 | E6: =IFERROR(AVERAGE(E10:E11),0) -> 0 | G6: =IFERROR(AVERAGE(F10:F11),"")
A8: Nhập Trạng thái, Tiến độ và Điểm ở các ô nền vàng. Tiến độ nhập từ 0% đến 100%; điểm từ 0 đến 10.
A9: STT | B9: Module | C9: Số bài | D9: Trạng thái | E9: Tiến độ (%) | F9: Điểm /10 | G9: Ngày hoàn thành | H9: Ghi chú
A10: 1 | B10: 00 - Roadmap.sh Developer Relations Official | C10: 33 | D10: Chưa bắt đầu | E10: 0
A11: 2 | B11: 99 - Portfolio Capstone Projects | C11: 5 | D11: Chưa bắt đầu | E11: 0

Sheet C69 product-manager-roadmap
A1: THEO DÕI KHÓA HỌC — product-manager-roadmap
A2: Mã khóa | B2: C69 | C2: Lĩnh vực | D2: 07 - Kinh doanh & Quản lý | E2: Chuyên ngành | F2: 01 - Product & Engineering Management
A3: Thư mục nguồn | B3: D:\Sao lưu\Udemy\Khóa học\07 - Kinh doanh & Quản lý\01 - Product & Engineering Management\product-manager-roadmap
A5: TỔNG MODULE | C5: ĐÃ HOÀN THÀNH | E5: TIẾN ĐỘ TRUNG BÌNH | G5: ĐIỂM TRUNG BÌNH
A6: =COUNTA(B10:B11) -> 2 | C6: =COUNTIF(D10:D11,"Đã hoàn thành") -> 0 | E6: =IFERROR(AVERAGE(E10:E11),0) -> 0 | G6: =IFERROR(AVERAGE(F10:F11),"")
A8: Nhập Trạng thái, Tiến độ và Điểm ở các ô nền vàng. Tiến độ nhập từ 0% đến 100%; điểm từ 0 đến 10.
A9: STT | B9: Module | C9: Số bài | D9: Trạng thái | E9: Tiến độ (%) | F9: Điểm /10 | G9: Ngày hoàn thành | H9: Ghi chú
A10: 1 | B10: 00 - Roadmap.sh Product Manager Official | C10: 148 | D10: Chưa bắt đầu | E10: 0
A11: 2 | B11: 99 - Portfolio Capstone Projects | C11: 5 | D11: Chưa bắt đầu | E11: 0

Sheet C68 engineering-manager-roadmap
A1: THEO DÕI KHÓA HỌC — engineering-manager-roadmap
A2: Mã khóa | B2: C68 | C2: Lĩnh vực | D2: 07 - Kinh doanh & Quản lý | E2: Chuyên ngành | F2: 01 - Product & Engineering Management
A3: Thư mục nguồn | B3: D:\Sao lưu\Udemy\Khóa học\07 - Kinh doanh & Quản lý\01 - Product & Engineering Management\engineering-manager-roadmap
A5: TỔNG MODULE | C5: ĐÃ HOÀN THÀNH | E5: TIẾN ĐỘ TRUNG BÌNH | G5: ĐIỂM TRUNG BÌNH
A6: =COUNTA(B10:B10) -> 1 | C6: =COUNTIF(D10:D10,"Đã hoàn thành") -> 0 | E6: =IFERROR(AVERAGE(E10:E10),0) -> 0 | G6: =IFERROR(AVERAGE(F10:F10),"")
A8: Nhập Trạng thái, Tiến độ và Điểm ở các ô nền vàng. Tiến độ nhập từ 0% đến 100%; điểm từ 0 đến 10.
A9: STT | B9: Module | C9: Số bài | D9: Trạng thái | E9: Tiến độ (%) | F9: Điểm /10 | G9: Ngày hoàn thành | H9: Ghi chú
A10: 1 | B10: 00 - Roadmap.sh Engineering Manager Official | C10: 98 | D10: Chưa bắt đầu | E10: 0

Sheet C67 Khóa học Tiếng Hàn toàn diệ
A1: THEO DÕI KHÓA HỌC — Khóa học Tiếng Hàn toàn diện cho người mới bắt đầu
A2: Mã khóa | B2: C67 | C2: Lĩnh vực | D2: 06 - Ngôn ngữ | E2: Chuyên ngành | F2: 06 - Tiếng Hàn
A3: Thư mục nguồn | B3: D:\Sao lưu\Udemy\Khóa học\06 - Ngôn ngữ\06 - Tiếng Hàn\complete-korean-course-for-beginners
A5: TỔNG MODULE | C5: ĐÃ HOÀN THÀNH | E5: TIẾN ĐỘ TRUNG BÌNH | G5: ĐIỂM TRUNG BÌNH
A6: =COUNTA(B10:B91) -> 82 | C6: =COUNTIF(D10:D91,"Đã hoàn thành") -> 0 | E6: =IFERROR(AVERAGE(E10:E91),0) -> 0 | G6: =IFERROR(AVERAGE(F10:F91),"")
A8: Nhập Trạng thái, Tiến độ và Điểm ở các ô nền vàng. Tiến độ nhập từ 0% đến 100%; điểm từ 0 đến 10.
A9: STT | B9: Module | C9: Số bài | D9: Trạng thái | E9: Tiến độ (%) | F9: Điểm /10 | G9: Ngày hoàn thành | H9: Ghi chú
A10: 1 | B10: 01 - Giới thiệu | C10: 4 | D10: Chưa bắt đầu | E10: 0
A11: 2 | B11: 02 - Phụ âm | C11: 10 | D11: Chưa bắt đầu | E11: 0
A12: 3 | B12: 03 - Nguyên âm | C12: 9 | D12: Chưa bắt đầu | E12: 0
A13: 4 | B13: 04 - Phụ âm căng, Nguyên âm đôi W và Tổ hợp CVC | C13: 19 | D13: Chưa bắt đầu | E13: 0
A14: 5 | B14: 05 - Cấu trúc Câu tiếng Hàn | C14: 11 | D14: Chưa bắt đầu | E14: 0
A15: 6 | B15: 06 - Các cụm từ tiếng Hàn cơ bản | C15: 12 | D15: Chưa bắt đầu | E15: 0
A16: 7 | B16: 07 - Tiếng Hàn Cho Người Mới Bắt Đầu Tuyệt Đối 2 | C16: 2 | D16: Chưa bắt đầu | E16: 0
A17: 8 | B17: 08 - Số đếm tiếng Hàn | C17: 7 | D17: Chưa bắt đầu | E17: 0
A18: 9 | B18: 09 - Thời gian & Ngày tháng | C18: 6 | D18: Chưa bắt đầu | E18: 0
A19: 10 | B19: 10 - Đại từ | C19: 4 | D19: Chưa bắt đầu | E19: 0
A20: 11 | B20: 11 - Cấu trúc Câu - Thì Hiện tại | C20: 10 | D20: Chưa bắt đầu | E20: 0
A21: 12 | B21: 12 - Động từ bất quy tắc | C21: 7 | D21: Chưa bắt đầu | E21: 0
... A91: 82 | B91: 82 - Bài 11 Sắp xếp kế hoạch | C91: 8 | D91: Chưa bắt đầu | E91: 0

Sheet C66 Tiếng Đức giao tiếp từ A1 đ
A1: THEO DÕI KHÓA HỌC — Tiếng Đức giao tiếp từ A1 đến B1
A2: Mã khóa | B2: C66 | C2: Lĩnh vực | D2: 06 - Ngôn ngữ | E2: Chuyên ngành | F2: 05 - Tiếng Đức
A3: Thư mục nguồn | B3: D:\Sao lưu\Udemy\Khóa học\06 - Ngôn ngữ\05 - Tiếng Đức\complete-german-course-speaking
A5: TỔNG MODULE | C5: ĐÃ HOÀN THÀNH | E5: TIẾN ĐỘ TRUNG BÌNH | G5: ĐIỂM TRUNG BÌNH
A6: =COUNTA(B10:B330) -> 321 | C6: =COUNTIF(D10:D330,"Đã hoàn thành") -> 0 | E6: =IFERROR(AVERAGE(E10:E330),0) -> 0 | G6: =IFERROR(AVERAGE(F10:F330),"")
A8: Nhập Trạng thái, Tiến độ và Điểm ở các ô nền vàng. Tiến độ nhập từ 0% đến 100%; điểm từ 0 đến 10.
A9: STT | B9: Module | C9: Số bài | D9: Trạng thái | E9: Tiến độ (%) | F9: Điểm /10 | G9: Ngày hoàn thành | H9: Ghi chú
A10: 1 | B10: Introduction | C10: 0 | D10: Chưa bắt đầu | E10: 0
A11: 2 | B11: A1 Unit 1 - Getting started | C11: 0 | D11: Chưa bắt đầu | E11: 0
A12: 3 | B12: A1 Unit 2 - Introducing yourself | C12: 0 | D12: Chưa bắt đầu | E12: 0
A13: 4 | B13: A1 Unit 3 - Talking about family and friends | C13: 0 | D13: Chưa bắt đầu | E13: 0
A14: 5 | B14: A1 Unit 4 - Talking about home | C14: 0 | D14: Chưa bắt đầu | E14: 0
A15: 6 | B15: A1 Unit 5 - Talking about routines | C15: 0 | D15: Chưa bắt đầu | E15: 0
A16: 7 | B16: A1 Unit 6 - Talking about work | C16: 0 | D16: Chưa bắt đầu | E16: 0
A17: 8 | B17: A1 Unit 7 - Talking about likes & dislikes | C17: 0 | D17: Chưa bắt đầu | E17: 0
A18: 9 | B18: A1 Unit 8 - Talking about free time activities | C18: 0 | D18: Chưa bắt đầu | E18: 0
A19: 10 | B19: A1 Unit 9 - Talking about your town or village | C19: 0 | D19: Chưa bắt đầu | E19: 0
A20: 11 | B20: A1 Unit 10 - Talking about the weather | C20: 0 | D20: Chưa bắt đầu | E20: 0
A21: 12 | B21: A1 Unit 11 - Talking about transport | C21: 0 | D21: Chưa bắt đầu | E21: 0
... A330: 321 | B330: Quiz và nhiệm vụ đầu ra. | C330: 0 | D330: Chưa bắt đầu | E330: 0

Sheet C65 Complete French Course — Kh
A1: THEO DÕI KHÓA HỌC — Complete French Course — Khóa học Markdown
A2: Mã khóa | B2: C65 | C2: Lĩnh vực | D2: 06 - Ngôn ngữ | E2: Chuyên ngành | F2: 04 - Tiếng Pháp
A3: Thư mục nguồn | B3: D:\Sao lưu\Udemy\Khóa học\06 - Ngôn ngữ\04 - Tiếng Pháp\complete-french-course
A5: TỔNG MODULE | C5: ĐÃ HOÀN THÀNH | E5: TIẾN ĐỘ TRUNG BÌNH | G5: ĐIỂM TRUNG BÌNH
A6: =COUNTA(B10:B16) -> 7 | C6: =COUNTIF(D10:D16,"Đã hoàn thành") -> 0 | E6: =IFERROR(AVERAGE(E10:E16),0) -> 0 | G6: =IFERROR(AVERAGE(F10:F16),"")
A8: Nhập Trạng thái, Tiến độ và Điểm ở các ô nền vàng. Tiến độ nhập từ 0% đến 100%; điểm từ 0 đến 10.
A9: STT | B9: Module | C9: Số bài | D9: Trạng thái | E9: Tiến độ (%) | F9: Điểm /10 | G9: Ngày hoàn thành | H9: Ghi chú
A10: 1 | B10: 01 - Beginner Course Chapter 1 | C10: 64 | D10: Chưa bắt đầu | E10: 0
A11: 2 | B11: 02 - Beginner Course Chapter 2 | C11: 20 | D11: Chưa bắt đầu | E11: 0
A12: 3 | B12: 03 - Beginner Course Chapter 3 | C12: 40 | D12: Chưa bắt đầu | E12: 0
A13: 4 | B13: 04 - Intermediate Course Chapter 1 | C13: 44 | D13: Chưa bắt đầu | E13: 0
A14: 5 | B14: 05 - 500 Most Useful French Words | C14: 4 | D14: Chưa bắt đầu | E14: 0
A15: 6 | B15: 06 - 500 Most Useful French Phrases | C15: 5 | D15: Chưa bắt đầu | E15: 0
A16: 7 | B16: 07 - Bonus Learn French with Music | C16: 14 | D16: Chưa bắt đầu | E16: 0

Sheet C64 Learn Japanese for Beginner
A1: THEO DÕI KHÓA HỌC — Learn Japanese for Beginners — Khóa học Markdown
A2: Mã khóa | B2: C64 | C2: Lĩnh vực | D2: 06 - Ngôn ngữ | E2: Chuyên ngành | F2: 03 - Tiếng Nhật
A3: Thư mục nguồn | B3: D:\Sao lưu\Udemy\Khóa học\06 - Ngôn ngữ\03 - Tiếng Nhật\learn-japanese-for-beginners-course
A5: TỔNG MODULE | C5: ĐÃ HOÀN THÀNH | E5: TIẾN ĐỘ TRUNG BÌNH | G5: ĐIỂM TRUNG BÌNH
A6: =COUNTA(B10:B24) -> 15 | C6: =COUNTIF(D10:D24,"Đã hoàn thành") -> 0 | E6: =IFERROR(AVERAGE(E10:E24),0) -> 0 | G6: =IFERROR(AVERAGE(F10:F24),"")
A8: Nhập Trạng thái, Tiến độ và Điểm ở các ô nền vàng. Tiến độ nhập từ 0% đến 100%; điểm từ 0 đến 10.
A9: STT | B9: Module | C9: Số bài | D9: Trạng thái | E9: Tiến độ (%) | F9: Điểm /10 | G9: Ngày hoàn thành | H9: Ghi chú
A10: 1 | B10: 01 - Introduction to Japanese | C10: 5 | D10: Chưa bắt đầu | E10: 0
A11: 2 | B11: 02 - Hiragana | C11: 20 | D11: Chưa bắt đầu | E11: 0
A12: 3 | B12: 03 - Katakana | C12: 20 | D12: Chưa bắt đầu | E12: 0
A13: 4 | B13: 04 - Pronunciation Basics | C13: 5 | D13: Chưa bắt đầu | E13: 0
A14: 5 | B14: 05 - Pronunciation Sound Changes and Pitch | C14: 5 | D14: Chưa bắt đầu | E14: 0
A15: 6 | B15: 06 - Self-Introduction, Greetings, and Manners | C15: 15 | D15: Chưa bắt đầu | E15: 0
A16: 7 | B16: 07 - Numbers and Counters | C16: 14 | D16: Chưa bắt đầu | E16: 0
A17: 8 | B17: 08 - Time, Dates, and Sentence Patterns | C17: 8 | D17: Chưa bắt đầu | E17: 0
A18: 9 | B18: 09 - Useful Everyday Questions | C18: 12 | D18: Chưa bắt đầu | E18: 0
A19: 10 | B19: 10 - Listening - Everyday Places and Services | C19: 12 | D19: Chưa bắt đầu | E19: 0
A20: 11 | B20: 11 - Listening - Daily Life and Plans | C20: 14 | D20: Chưa bắt đầu | E20: 0
A21: 12 | B21: 12 - Listening - Personal Topics and Shopping | C21: 14 | D21: Chưa bắt đầu | E21: 0
... A24: 15 | B24: 15 - Listening - Home, Time, and Travel | C24: 8 | D24: Chưa bắt đầu | E24: 0

Sheet C63 Mandarin Mastery Path — Tiế
A1: THEO DÕI KHÓA HỌC — Mandarin Mastery Path — Tiếng Trung từ Nền tảng đến HSK 3
A2: Mã khóa | B2: C63 | C2: Lĩnh vực | D2: 06 - Ngôn ngữ | E2: Chuyên ngành | F2: 02 - Tiếng Trung
A3: Thư mục nguồn | B3: D:\Sao lưu\Udemy\Khóa học\06 - Ngôn ngữ\02 - Tiếng Trung\mandarin-mastery-path
A5: TỔNG MODULE | C5: ĐÃ HOÀN THÀNH | E5: TIẾN ĐỘ TRUNG BÌNH | G5: ĐIỂM TRUNG BÌNH
A6: =COUNTA(B10:B65) -> 56 | C6: =COUNTIF(D10:D65,"Đã hoàn thành") -> 0 | E6: =IFERROR(AVERAGE(E10:E65),0) -> 0 | G6: =IFERROR(AVERAGE(F10:F65),"")
A8: Nhập Trạng thái, Tiến độ và Điểm ở các ô nền vàng. Tiến độ nhập từ 0% đến 100%; điểm từ 0 đến 10.
A9: STT | B9: Module | C9: Số bài | D9: Trạng thái | E9: Tiến độ (%) | F9: Điểm /10 | G9: Ngày hoàn thành | H9: Ghi chú
A10: 1 | B10: module-01-khoi-dong-hanh-trinh | C10: 2 | D10: Chưa bắt đầu | E10: 0
A11: 2 | B11: module-02-nen-tang-phat-am-chu-han | C11: 7 | D11: Chưa bắt đầu | E11: 0
A12: 3 | B12: module-03-hsk1-01-nhung-cau-dau-tien | C12: 2 | D12: Chưa bắt đầu | E12: 0
A13: 4 | B13: module-04-hsk1-02-lam-quen-va-gioi-thieu-ban-than | C13: 5 | D13: Chưa bắt đầu | E13: 0
A14: 5 | B14: module-05-hsk1-03-gioi-thieu-nguoi-xung-quanh | C14: 3 | D14: Chưa bắt đầu | E14: 0
A15: 6 | B15: module-06-hsk1-04-con-so-gia-dinh-tuoi-tac | C15: 7 | D15: Chưa bắt đầu | E15: 0
A16: 7 | B16: module-07-hsk1-05-kha-nang-va-mieu-ta | C16: 6 | D16: Chưa bắt đầu | E16: 0
A17: 8 | B17: module-08-hsk1-06-ngay-thang-va-di-chuyen | C17: 4 | D17: Chưa bắt đầu | E17: 0
A18: 9 | B18: module-09-hsk1-07-mong-muon-so-luong-tien-bac | C18: 6 | D18: Chưa bắt đầu | E18: 0
A19: 10 | B19: module-10-hsk1-08-dia-diem-va-nghe-nghiep | C19: 7 | D19: Chưa bắt đầu | E19: 0
A20: 11 | B20: module-11-hsk1-09-su-ton-tai-va-loi-de-nghi | C20: 4 | D20: Chưa bắt đầu | E20: 0
A21: 12 | B21: module-12-hsk1-10-gio-giac-va-lich-sinh-hoat | C21: 4 | D21: Chưa bắt đầu | E21: 0
... A65: 56 | B65: module-56-hoan-thanh-hanh-trinh-hsk | C65: 1 | D65: Chưa bắt đầu | E65: 0

Sheet C62 Khóa học Tiếng Trung — Giáo
A1: THEO DÕI KHÓA HỌC — Khóa học Tiếng Trung — Giáo trình Hán Ngữ Quyển 1–6
A2: Mã khóa | B2: C62 | C2: Lĩnh vực | D2: 06 - Ngôn ngữ | E2: Chuyên ngành | F2: 02 - Tiếng Trung
A3: Thư mục nguồn | B3: D:\Sao lưu\Udemy\Khóa học\06 - Ngôn ngữ\02 - Tiếng Trung\khoa-hoc-tieng-trung
A5: TỔNG MODULE | C5: ĐÃ HOÀN THÀNH | E5: TIẾN ĐỘ TRUNG BÌNH | G5: ĐIỂM TRUNG BÌNH
A6: =COUNTA(B10:B15) -> 6 | C6: =COUNTIF(D10:D15,"Đã hoàn thành") -> 0 | E6: =IFERROR(AVERAGE(E10:E15),0) -> 0 | G6: =IFERROR(AVERAGE(F10:F15),"")
A8: Nhập Trạng thái, Tiến độ và Điểm ở các ô nền vàng. Tiến độ nhập từ 0% đến 100%; điểm từ 0 đến 10.
A9: STT | B9: Module | C9: Số bài | D9: Trạng thái | E9: Tiến độ (%) | F9: Điểm /10 | G9: Ngày hoàn thành | H9: Ghi chú
A10: 1 | B10: module-01-quyen-1 | C10: 15 | D10: Chưa bắt đầu | E10: 0
A11: 2 | B11: module-02-quyen-2 | C11: 15 | D11: Chưa bắt đầu | E11: 0
A12: 3 | B12: module-03-quyen-3 | C12: 10 | D12: Chưa bắt đầu | E12: 0
A13: 4 | B13: module-04-quyen-4 | C13: 10 | D13: Chưa bắt đầu | E13: 0
A14: 5 | B14: module-05-quyen-5 | C14: 13 | D14: Chưa bắt đầu | E14: 0
A15: 6 | B15: module-06-quyen-6 | C15: 13 | D15: Chưa bắt đầu | E15: 0

Sheet C61 Từ vựng tiếng Anh cơ bản
A1: THEO DÕI KHÓA HỌC — Từ vựng tiếng Anh cơ bản
A2: Mã khóa | B2: C61 | C2: Lĩnh vực | D2: 06 - Ngôn ngữ | E2: Chuyên ngành | F2: 01 - Tiếng Anh
A3: Thư mục nguồn | B3: D:\Sao lưu\Udemy\Khóa học\06 - Ngôn ngữ\01 - Tiếng Anh\tu-vung-tieng-anh-co-ban
A5: TỔNG MODULE | C5: ĐÃ HOÀN THÀNH | E5: TIẾN ĐỘ TRUNG BÌNH | G5: ĐIỂM TRUNG BÌNH
A6: =COUNTA(B10:B10) -> 1 | C6: =COUNTIF(D10:D10,"Đã hoàn thành") -> 0 | E6: =IFERROR(AVERAGE(E10:E10),0) -> 0 | G6: =IFERROR(AVERAGE(F10:F10),"")
A8: Nhập Trạng thái, Tiến độ và Điểm ở các ô nền vàng. Tiến độ nhập từ 0% đến 100%; điểm từ 0 đến 10.
A9: STT | B9: Module | C9: Số bài | D9: Trạng thái | E9: Tiến độ (%) | F9: Điểm /10 | G9: Ngày hoàn thành | H9: Ghi chú
A10: 1 | B10: lessons | C10: 25 | D10: Chưa bắt đầu | E10: 0

Sheet C60 Tự học 2.000 từ vựng tiếng
A1: THEO DÕI KHÓA HỌC — Tự học 2.000 từ vựng tiếng Anh
A2: Mã khóa | B2: C60 | C2: Lĩnh vực | D2: 06 - Ngôn ngữ | E2: Chuyên ngành | F2: 01 - Tiếng Anh
A3: Thư mục nguồn | B3: D:\Sao lưu\Udemy\Khóa học\06 - Ngôn ngữ\01 - Tiếng Anh\tu-hoc-2000-tu-vung-tieng-anh
A5: TỔNG MODULE | C5: ĐÃ HOÀN THÀNH | E5: TIẾN ĐỘ TRUNG BÌNH | G5: ĐIỂM TRUNG BÌNH
A6: =COUNTA(B10:B15) -> 6 | C6: =COUNTIF(D10:D15,"Đã hoàn thành") -> 0 | E6: =IFERROR(AVERAGE(E10:E15),0) -> 0 | G6: =IFERROR(AVERAGE(F10:F15),"")
A8: Nhập Trạng thái, Tiến độ và Điểm ở các ô nền vàng. Tiến độ nhập từ 0% đến 100%; điểm từ 0 đến 10.
A9: STT | B9: Module | C9: Số bài | D9: Trạng thái | E9: Tiến độ (%) | F9: Điểm /10 | G9: Ngày hoàn thành | H9: Ghi chú
A10: 1 | B10: Module 01 - People and Body | C10: 8 | D10: Chưa bắt đầu | E10: 0
A11: 2 | B11: Module 02 - Family and Daily Life | C11: 8 | D11: Chưa bắt đầu | E11: 0
A12: 3 | B12: Module 03 - Home and Food | C12: 11 | D12: Chưa bắt đầu | E12: 0
A13: 4 | B13: Module 04 - Animals and Nature | C13: 3 | D13: Chưa bắt đầu | E13: 0
A14: 5 | B14: Module 05 - Hobbies and Travel | C14: 6 | D14: Chưa bắt đầu | E14: 0
A15: 6 | B15: Module 06 - Work and World | C15: 3 | D15: Chưa bắt đầu | E15: 0

Sheet C59 The English Master Course-
A1: THEO DÕI KHÓA HỌC — The English Master Course: English Grammar, English Speaking
A2: Mã khóa | B2: C59 | C2: Lĩnh vực | D2: 06 - Ngôn ngữ | E2: Chuyên ngành | F2: 01 - Tiếng Anh
A3: Thư mục nguồn | B3: D:\Sao lưu\Udemy\Khóa học\06 - Ngôn ngữ\01 - Tiếng Anh\the-english-master-course-english-grammar-speaking
A5: TỔNG MODULE | C5: ĐÃ HOÀN THÀNH | E5: TIẾN ĐỘ TRUNG BÌNH | G5: ĐIỂM TRUNG BÌNH
A6: =COUNTA(B10:B15) -> 6 | C6: =COUNTIF(D10:D15,"Đã hoàn thành") -> 0 | E6: =IFERROR(AVERAGE(E10:E15),0) -> 0 | G6: =IFERROR(AVERAGE(F10:F15),"")
A8: Nhập Trạng thái, Tiến độ và Điểm ở các ô nền vàng. Tiến độ nhập từ 0% đến 100%; điểm từ 0 đến 10.
A9: STT | B9: Module | C9: Số bài | D9: Trạng thái | E9: Tiến độ (%) | F9: Điểm /10 | G9: Ngày hoàn thành | H9: Ghi chú
A10: 1 | B10: 001 - How English Works - A Quick Review | C10: 8 | D10: Chưa bắt đầu | E10: 0
A11: 2 | B11: 002 - English Grammar | C11: 384 | D11: Chưa bắt đầu | E11: 0
A12: 3 | B12: 003 - English Writing | C12: 18 | D12: Chưa bắt đầu | E12: 0
A13: 4 | B13: 004 - English Speaking | C13: 22 | D13: Chưa bắt đầu | E13: 0
A14: 5 | B14: 005 - Pronunciation and Accent | C14: 49 | D14: Chưa bắt đầu | E14: 0
A15: 6 | B15: 006 - IELTS Upgrade and Practice | C15: 4 | D15: Chưa bắt đầu | E15: 0

Sheet C58 Pixel Art Master Course - B
A1: THEO DÕI KHÓA HỌC — Pixel Art Master Course - Beginner to Professional/Freelance
A2: Mã khóa | B2: C58 | C2: Lĩnh vực | D2: 05 - Phát triển game | E2: Chuyên ngành | F2: 05 - Game Art
A3: Thư mục nguồn | B3: D:\Sao lưu\Udemy\Khóa học\05 - Phát triển game\05 - Game Art\pixel-art-master-course-beginner-to-professional-freelance
A5: TỔNG MODULE | C5: ĐÃ HOÀN THÀNH | E5: TIẾN ĐỘ TRUNG BÌNH | G5: ĐIỂM TRUNG BÌNH
A6: =COUNTA(B10:B29) -> 20 | C6: =COUNTIF(D10:D29,"Đã hoàn thành") -> 0 | E6: =IFERROR(AVERAGE(E10:E29),0) -> 0 | G6: =IFERROR(AVERAGE(F10:F29),"")
A8: Nhập Trạng thái, Tiến độ và Điểm ở các ô nền vàng. Tiến độ nhập từ 0% đến 100%; điểm từ 0 đến 10.
A9: STT | B9: Module | C9: Số bài | D9: Trạng thái | E9: Tiến độ (%) | F9: Điểm /10 | G9: Ngày hoàn thành | H9: Ghi chú
A10: 1 | B10: 01 - Getting Started | C10: 8 | D10: Chưa bắt đầu | E10: 0
A11: 2 | B11: 02 - Lines and Shapes `[B]` | C11: 5 | D11: Chưa bắt đầu | E11: 0
A12: 3 | B12: 03 - Shading and Lighting `[B]` | C12: 12 | D12: Chưa bắt đầu | E12: 0
A13: 4 | B13: 04 - Colours and Textures `[B]` | C13: 11 | D13: Chưa bắt đầu | E13: 0
A14: 5 | B14: 05 - Drawing Simple Objects `[B]` | C14: 9 | D14: Chưa bắt đầu | E14: 0
A15: 6 | B15: 06 - Tiles `[B]` | C15: 8 | D15: Chưa bắt đầu | E15: 0
A16: 7 | B16: 07 - Backgrounds `[B]` | C16: 5 | D16: Chưa bắt đầu | E16: 0
A17: 8 | B17: 08 - Basic Characters `[B]` | C17: 5 | D17: Chưa bắt đầu | E17: 0
A18: 9 | B18: 09 - Simple Animation `[B]` | C18: 11 | D18: Chưa bắt đầu | E18: 0
A19: 10 | B19: 10 - Platformer View `[I]` | C19: 14 | D19: Chưa bắt đầu | E19: 0
A20: 11 | B20: 11 - Top Down View `[I]` | C20: 14 | D20: Chưa bắt đầu | E20: 0
A21: 12 | B21: 12 - RPG View `[I]` | C21: 12 | D21: Chưa bắt đầu | E21: 0
... A29: 20 | B29: 20 - Freelancing `[A]` | C29: 18 | D29: Chưa bắt đầu | E29: 0

Sheet C57 server-side-game-developer-
A1: THEO DÕI KHÓA HỌC — server-side-game-developer-roadmap
A2: Mã khóa | B2: C57 | C2: Lĩnh vực | D2: 05 - Phát triển game | E2: Chuyên ngành | F2: 04 - Game Development Roadmaps
A3: Thư mục nguồn | B3: D:\Sao lưu\Udemy\Khóa học\05 - Phát triển game\04 - Game Development Roadmaps\server-side-game-developer-roadmap
A5: TỔNG MODULE | C5: ĐÃ HOÀN THÀNH | E5: TIẾN ĐỘ TRUNG BÌNH | G5: ĐIỂM TRUNG BÌNH
A6: =COUNTA(B10:B10) -> 1 | C6: =COUNTIF(D10:D10,"Đã hoàn thành") -> 0 | E6: =IFERROR(AVERAGE(E10:E10),0) -> 0 | G6: =IFERROR(AVERAGE(F10:F10),"")
A8: Nhập Trạng thái, Tiến độ và Điểm ở các ô nền vàng. Tiến độ nhập từ 0% đến 100%; điểm từ 0 đến 10.
A9: STT | B9: Module | C9: Số bài | D9: Trạng thái | E9: Tiến độ (%) | F9: Điểm /10 | G9: Ngày hoàn thành | H9: Ghi chú
A10: 1 | B10: 00 - Roadmap.sh Server-Side Game Developer Official | C10: 79 | D10: Chưa bắt đầu | E10: 0

Sheet C56 game-developer-roadmap
A1: THEO DÕI KHÓA HỌC — game-developer-roadmap
A2: Mã khóa | B2: C56 | C2: Lĩnh vực | D2: 05 - Phát triển game | E2: Chuyên ngành | F2: 04 - Game Development Roadmaps
A3: Thư mục nguồn | B3: D:\Sao lưu\Udemy\Khóa học\05 - Phát triển game\04 - Game Development Roadmaps\game-developer-roadmap
A5: TỔNG MODULE | C5: ĐÃ HOÀN THÀNH | E5: TIẾN ĐỘ TRUNG BÌNH | G5: ĐIỂM TRUNG BÌNH
A6: =COUNTA(B10:B10) -> 1 | C6: =COUNTIF(D10:D10,"Đã hoàn thành") -> 0 | E6: =IFERROR(AVERAGE(E10:E10),0) -> 0 | G6: =IFERROR(AVERAGE(F10:F10),"")
A8: Nhập Trạng thái, Tiến độ và Điểm ở các ô nền vàng. Tiến độ nhập từ 0% đến 100%; điểm từ 0 đến 10.
A9: STT | B9: Module | C9: Số bài | D9: Trạng thái | E9: Tiến độ (%) | F9: Điểm /10 | G9: Ngày hoàn thành | H9: Ghi chú
A10: 1 | B10: 00 - Roadmap.sh Game Developer Official | C10: 32 | D10: Chưa bắt đầu | E10: 0

Sheet C55 Indie Game Design - Build Y
A1: THEO DÕI KHÓA HỌC — Indie Game Design - Build Your Game's Core System
A2: Mã khóa | B2: C55 | C2: Lĩnh vực | D2: 05 - Phát triển game | E2: Chuyên ngành | F2: 03 - Game Design
A3: Thư mục nguồn | B3: D:\Sao lưu\Udemy\Khóa học\05 - Phát triển game\03 - Game Design\indie-game-design-build-your-games-core-system
A5: TỔNG MODULE | C5: ĐÃ HOÀN THÀNH | E5: TIẾN ĐỘ TRUNG BÌNH | G5: ĐIỂM TRUNG BÌNH
A6: =COUNTA(B10:B17) -> 8 | C6: =COUNTIF(D10:D17,"Đã hoàn thành") -> 0 | E6: =IFERROR(AVERAGE(E10:E17),0) -> 0 | G6: =IFERROR(AVERAGE(F10:F17),"")
A8: Nhập Trạng thái, Tiến độ và Điểm ở các ô nền vàng. Tiến độ nhập từ 0% đến 100%; điểm từ 0 đến 10.
A9: STT | B9: Module | C9: Số bài | D9: Trạng thái | E9: Tiến độ (%) | F9: Điểm /10 | G9: Ngày hoàn thành | H9: Ghi chú
A10: 1 | B10: 01 - Introduction | C10: 2 | D10: Chưa bắt đầu | E10: 0
A11: 2 | B11: 02 - Understand How to Build a Core Gameplay | C11: 6 | D11: Chưa bắt đầu | E11: 0
A12: 3 | B12: 03 - Workshop - Define Your Game System, Part 1 | C12: 1 | D12: Chưa bắt đầu | E12: 0
A13: 4 | B13: 04 - Build Your Engagement Gameplay to Keep Your Players | C13: 7 | D13: Chưa bắt đầu | E13: 0
A14: 5 | B14: 05 - Workshop - Define Your Game System, Part 2 | C14: 1 | D14: Chưa bắt đầu | E14: 0
A15: 6 | B15: 06 - Design Support Features That Will Make Your Game Shine | C15: 5 | D15: Chưa bắt đầu | E15: 0
A16: 7 | B16: 07 - Workshop - Define Your Game System, Part 3 | C16: 1 | D16: Chưa bắt đầu | E16: 0
A17: 8 | B17: 08 - Conclusion | C17: 1 | D17: Chưa bắt đầu | E17: 0

Sheet C54 Ren'Py Minigames 101
A1: THEO DÕI KHÓA HỌC — Ren'Py Minigames 101
A2: Mã khóa | B2: C54 | C2: Lĩnh vực | D2: 05 - Phát triển game | E2: Chuyên ngành | F2: 02 - Ren'Py & Visual Novels
A3: Thư mục nguồn | B3: D:\Sao lưu\Udemy\Khóa học\05 - Phát triển game\02 - Ren'Py & Visual Novels\renpy-minigames-101
A5: TỔNG MODULE | C5: ĐÃ HOÀN THÀNH | E5: TIẾN ĐỘ TRUNG BÌNH | G5: ĐIỂM TRUNG BÌNH
A6: =COUNTA(B10:B13) -> 4 | C6: =COUNTIF(D10:D13,"Đã hoàn thành") -> 0 | E6: =IFERROR(AVERAGE(E10:E13),0) -> 0 | G6: =IFERROR(AVERAGE(F10:F13),"")
A8: Nhập Trạng thái, Tiến độ và Điểm ở các ô nền vàng. Tiến độ nhập từ 0% đến 100%; điểm từ 0 đến 10.
A9: STT | B9: Module | C9: Số bài | D9: Trạng thái | E9: Tiến độ (%) | F9: Điểm /10 | G9: Ngày hoàn thành | H9: Ghi chú
A10: 1 | B10: 01 - Introduction | C10: 3 | D10: Chưa bắt đầu | E10: 0
A11: 2 | B11: 02 - Rendering the Game View | C11: 6 | D11: Chưa bắt đầu | E11: 0
A12: 3 | B12: 03 - Detecting Player Interaction Events | C12: 3 | D12: Chưa bắt đầu | E12: 0
A13: 4 | B13: 04 - Bonus Features Course Recap and Conclusion | C13: 3 | D13: Chưa bắt đầu | E13: 0

Sheet C53 Python Basics for Ren'Py De
A1: THEO DÕI KHÓA HỌC — Python Basics for Ren'Py Developers
A2: Mã khóa | B2: C53 | C2: Lĩnh vực | D2: 05 - Phát triển game | E2: Chuyên ngành | F2: 02 - Ren'Py & Visual Novels
A3: Thư mục nguồn | B3: D:\Sao lưu\Udemy\Khóa học\05 - Phát triển game\02 - Ren'Py & Visual Novels\python-basics-for-renpy-developers
A5: TỔNG MODULE | C5: ĐÃ HOÀN THÀNH | E5: TIẾN ĐỘ TRUNG BÌNH | G5: ĐIỂM TRUNG BÌNH
A6: =COUNTA(B10:B15) -> 6 | C6: =COUNTIF(D10:D15,"Đã hoàn thành") -> 0 | E6: =IFERROR(AVERAGE(E10:E15),0) -> 0 | G6: =IFERROR(AVERAGE(F10:F15),"")
A8: Nhập Trạng thái, Tiến độ và Điểm ở các ô nền vàng. Tiến độ nhập từ 0% đến 100%; điểm từ 0 đến 10.
A9: STT | B9: Module | C9: Số bài | D9: Trạng thái | E9: Tiến độ (%) | F9: Điểm /10 | G9: Ngày hoàn thành | H9: Ghi chú
A10: 1 | B10: 01 - Introduction | C10: 2 | D10: Chưa bắt đầu | E10: 0
A11: 2 | B11: 02 - Variables in Python | C11: 3 | D11: Chưa bắt đầu | E11: 0
A12: 3 | B12: 03 - Data Structures in Python | C12: 3 | D12: Chưa bắt đầu | E12: 0
A13: 4 | B13: 04 - Python Statements | C13: 3 | D13: Chưa bắt đầu | E13: 0
A14: 5 | B14: 05 - Advanced Topics Functions and Classes | C14: 2 | D14: Chưa bắt đầu | E14: 0
A15: 6 | B15: 06 - Python Resources | C15: 1 | D15: Chưa bắt đầu | E15: 0

Sheet C52 Mastering Ren'Py- Create Vi
A1: THEO DÕI KHÓA HỌC — Mastering Ren'Py: Create Visual Novels Like a Pro
A2: Mã khóa | B2: C52 | C2: Lĩnh vực | D2: 05 - Phát triển game | E2: Chuyên ngành | F2: 02 - Ren'Py & Visual Novels
A3: Thư mục nguồn | B3: D:\Sao lưu\Udemy\Khóa học\05 - Phát triển game\02 - Ren'Py & Visual Novels\mastering-renpy-create-visual-novels-like-a-pro
A5: TỔNG MODULE | C5: ĐÃ HOÀN THÀNH | E5: TIẾN ĐỘ TRUNG BÌNH | G5: ĐIỂM TRUNG BÌNH
A6: =COUNTA(B10:B11) -> 2 | C6: =COUNTIF(D10:D11,"Đã hoàn thành") -> 0 | E6: =IFERROR(AVERAGE(E10:E11),0) -> 0 | G6: =IFERROR(AVERAGE(F10:F11),"")
A8: Nhập Trạng thái, Tiến độ và Điểm ở các ô nền vàng. Tiến độ nhập từ 0% đến 100%; điểm từ 0 đến 10.
A9: STT | B9: Module | C9: Số bài | D9: Trạng thái | E9: Tiến độ (%) | F9: Điểm /10 | G9: Ngày hoàn thành | H9: Ghi chú
A10: 1 | B10: 01 - Installation and Interface of RenPy | C10: 4 | D10: Chưa bắt đầu | E10: 0
A11: 2 | B11: 02 - Creating Your First Game | C11: 11 | D11: Chưa bắt đầu | E11: 0

Sheet C51 Complete C# Unity 3D Game D
A1: THEO DÕI KHÓA HỌC — Complete C# Unity 3D Game Development in Unity 6
A2: Mã khóa | B2: C51 | C2: Lĩnh vực | D2: 05 - Phát triển game | E2: Chuyên ngành | F2: 01 - Unity & C#
A3: Thư mục nguồn | B3: D:\Sao lưu\Udemy\Khóa học\05 - Phát triển game\01 - Unity & C#\complete-csharp-unity-3d-game-development-unity-6
A5: TỔNG MODULE | C5: ĐÃ HOÀN THÀNH | E5: TIẾN ĐỘ TRUNG BÌNH | G5: ĐIỂM TRUNG BÌNH
A6: =COUNTA(B10:B16) -> 7 | C6: =COUNTIF(D10:D16,"Đã hoàn thành") -> 0 | E6: =IFERROR(AVERAGE(E10:E16),0) -> 0 | G6: =IFERROR(AVERAGE(F10:F16),"")
A8: Nhập Trạng thái, Tiến độ và Điểm ở các ô nền vàng. Tiến độ nhập từ 0% đến 100%; điểm từ 0 đến 10.
A9: STT | B9: Module | C9: Số bài | D9: Trạng thái | E9: Tiến độ (%) | F9: Điểm /10 | G9: Ngày hoàn thành | H9: Ghi chú
A10: 1 | B10: 01 - Introduction and Setup | C10: 8 | D10: Chưa bắt đầu | E10: 0
A11: 2 | B11: 02 - Obstacle Dodge | C11: 27 | D11: Chưa bắt đầu | E11: 0
A12: 3 | B12: 03 - Rocket Boost | C12: 34 | D12: Chưa bắt đầu | E12: 0
A13: 4 | B13: 04 - Galaxy Strike | C13: 41 | D13: Chưa bắt đầu | E13: 0
A14: 5 | B14: 05 - Royal Run | C14: 38 | D14: Chưa bắt đầu | E14: 0
A15: 6 | B15: 06 - Sharp Shooter | C15: 43 | D15: Chưa bắt đầu | E15: 0
A16: 7 | B16: 07 - Bonus- One Last Thing | C16: 1 | D16: Chưa bắt đầu | E16: 0

Sheet C50 Complete C# Unity 2D Game D
A1: THEO DÕI KHÓA HỌC — Complete C# Unity 2D Game Development - Updated To Unity 6
A2: Mã khóa | B2: C50 | C2: Lĩnh vực | D2: 05 - Phát triển game | E2: Chuyên ngành | F2: 01 - Unity & C#
A3: Thư mục nguồn | B3: D:\Sao lưu\Udemy\Khóa học\05 - Phát triển game\01 - Unity & C#\complete-csharp-unity-2d-game-development-unity-6
A5: TỔNG MODULE | C5: ĐÃ HOÀN THÀNH | E5: TIẾN ĐỘ TRUNG BÌNH | G5: ĐIỂM TRUNG BÌNH
A6: =COUNTA(B10:B15) -> 6 | C6: =COUNTIF(D10:D15,"Đã hoàn thành") -> 0 | E6: =IFERROR(AVERAGE(E10:E15),0) -> 0 | G6: =IFERROR(AVERAGE(F10:F15),"")
A8: Nhập Trạng thái, Tiến độ và Điểm ở các ô nền vàng. Tiến độ nhập từ 0% đến 100%; điểm từ 0 đến 10.
A9: STT | B9: Module | C9: Số bài | D9: Trạng thái | E9: Tiến độ (%) | F9: Điểm /10 | G9: Ngày hoàn thành | H9: Ghi chú
A10: 1 | B10: 01 - Introduction and Setup | C10: 6 | D10: Chưa bắt đầu | E10: 0
A11: 2 | B11: 02 - Delivery Dash | C11: 24 | D11: Chưa bắt đầu | E11: 0
A12: 3 | B12: 03 - Snow Surfer | C12: 29 | D12: Chưa bắt đầu | E12: 0
A13: 4 | B13: 04 - Tilemania | C13: 41 | D13: Chưa bắt đầu | E13: 0
A14: 5 | B14: 05 - Star Blaster | C14: 30 | D14: Chưa bắt đầu | E14: 0
A15: 6 | B15: 06 - Bonus One Last Thing | C15: 2 | D15: Chưa bắt đầu | E15: 0

Sheet C49 05 - Cơ học & thủy động lực
A1: THEO DÕI KHÓA HỌC — 05 - Cơ học & thủy động lực học bơi cá
A2: Mã khóa | B2: C49 | C2: Lĩnh vực | D2: 04 - Thiết kế & Sáng tạo số | E2: Chuyên ngành | F2: 03 - Blender & 3D
A3: Thư mục nguồn | B3: D:\Sao lưu\Udemy\Khóa học\04 - Thiết kế & Sáng tạo số\03 - Blender & 3D\05 - Cơ học & thủy động lực học bơi cá
A5: TỔNG MODULE | C5: ĐÃ HOÀN THÀNH | E5: TIẾN ĐỘ TRUNG BÌNH | G5: ĐIỂM TRUNG BÌNH
A6: =COUNTA(B10:B28) -> 19 | C6: =COUNTIF(D10:D28,"Đã hoàn thành") -> 0 | E6: =IFERROR(AVERAGE(E10:E28),0) -> 0 | G6: =IFERROR(AVERAGE(F10:F28),"")
A8: Nhập Trạng thái, Tiến độ và Điểm ở các ô nền vàng. Tiến độ nhập từ 0% đến 100%; điểm từ 0 đến 10.
A9: STT | B9: Module | C9: Số bài | D9: Trạng thái | E9: Tiến độ (%) | F9: Điểm /10 | G9: Ngày hoàn thành | H9: Ghi chú
A10: 1 | B10: hydrodynamics-of-fishlike-swimming — 01-nen-tang | C10: 1 | D10: Chưa bắt đầu | E10: 0
A11: 2 | B11: hydrodynamics-of-fishlike-swimming — 02-canh-dao-dong | C11: 2 | D11: Chưa bắt đầu | E11: 0
A12: 3 | B12: hydrodynamics-of-fishlike-swimming — 03-boi-on-dinh | C12: 2 | D12: Chưa bắt đầu | E12: 0
A13: 4 | B13: hydrodynamics-of-fishlike-swimming — 04-co-dong | C13: 1 | D13: Chưa bắt đầu | E13: 0
A14: 5 | B14: hydrodynamics-of-fishlike-swimming — 05-biomimetic | C14: 2 | D14: Chưa bắt đầu | E14: 0
A15: 6 | B15: hydrodynamics-of-fishlike-swimming — 06-on-tap | C15: 2 | D15: Chưa bắt đầu | E15: 0
A16: 7 | B16: hydrodynamics-of-fishlike-swimming — 07-phu-luc | C16: 3 | D16: Chưa bắt đầu | E16: 0
A17: 8 | B17: lauder-tytell-2006-hydrodynamics — 01 - Propulsion Foundations | C17: 4 | D17: Chưa bắt đầu | E17: 0
A18: 9 | B18: lauder-tytell-2006-hydrodynamics — 02 - Mathematical Models | C18: 2 | D18: Chưa bắt đầu | E18: 0
A19: 10 | B19: lauder-tytell-2006-hydrodynamics — 03 - Experimental Methods and Wakes | C19: 4 | D19: Chưa bắt đầu | E19: 0
A20: 11 | B20: lauder-tytell-2006-hydrodynamics — 04 - Whole-body Hydrodynamics and Turbulence | C20: 3 | D20: Chưa bắt đầu | E20: 0
A21: 12 | B21: lauder-tytell-2006-hydrodynamics — 05 - Theory, Evidence, and Future Work | C21: 3 | D21: Chưa bắt đầu | E21: 0
... A28: 19 | B28: review-of-fish-swimming-modes — 06 - References and Study Tools | C28: 4 | D28: Chưa bắt đầu | E28: 0

Sheet C48 04 - Giải phẫu & phát triển
A1: THEO DÕI KHÓA HỌC — 04 - Giải phẫu & phát triển bộ xương cá
A2: Mã khóa | B2: C48 | C2: Lĩnh vực | D2: 04 - Thiết kế & Sáng tạo số | E2: Chuyên ngành | F2: 03 - Blender & 3D
A3: Thư mục nguồn | B3: D:\Sao lưu\Udemy\Khóa học\04 - Thiết kế & Sáng tạo số\03 - Blender & 3D\04 - Giải phẫu & phát triển bộ xương cá
A5: TỔNG MODULE | C5: ĐÃ HOÀN THÀNH | E5: TIẾN ĐỘ TRUNG BÌNH | G5: ĐIỂM TRUNG BÌNH
A6: =COUNTA(B10:B21) -> 12 | C6: =COUNTIF(D10:D21,"Đã hoàn thành") -> 0 | E6: =IFERROR(AVERAGE(E10:E21),0) -> 0 | G6: =IFERROR(AVERAGE(F10:F21),"")
A8: Nhập Trạng thái, Tiến độ và Điểm ở các ô nền vàng. Tiến độ nhập từ 0% đến 100%; điểm từ 0 đến 10.
A9: STT | B9: Module | C9: Số bài | D9: Trạng thái | E9: Tiến độ (%) | F9: Điểm /10 | G9: Ngày hoàn thành | H9: Ghi chú
A10: 1 | B10: astatotilapia-burtoni-skeletal-ontogeny — 01 - Foundations and Study Guide | C10: 3 | D10: Chưa bắt đầu | E10: 0
A11: 2 | B11: astatotilapia-burtoni-skeletal-ontogeny — 02 - Embryonic Development | C11: 2 | D11: Chưa bắt đầu | E11: 0
A12: 3 | B12: astatotilapia-burtoni-skeletal-ontogeny — 03 - Axial and Median Fins | C12: 3 | D12: Chưa bắt đầu | E12: 0
A13: 4 | B13: astatotilapia-burtoni-skeletal-ontogeny — 04 - Paired Fins | C13: 3 | D13: Chưa bắt đầu | E13: 0
A14: 5 | B14: astatotilapia-burtoni-skeletal-ontogeny — 05 - Caudal, Scales, and Cranium | C14: 3 | D14: Chưa bắt đầu | E14: 0
A15: 6 | B15: astatotilapia-burtoni-skeletal-ontogeny — 06 - Methods and Evo-Devo | C15: 4 | D15: Chưa bắt đầu | E15: 0
A16: 7 | B16: astatotilapia-burtoni-skeletal-ontogeny — 07 - Figures and Study Tools | C16: 4 | D16: Chưa bắt đầu | E16: 0
A17: 8 | B17: astatotilapia-burtoni-skeletal-ontogeny — 03 - Axial and Median Fins | C17: 0 | D17: Chưa bắt đầu | E17: 0
A18: 9 | B18: astatotilapia-burtoni-skeletal-ontogeny — 06 - Methods and Evo-Devo | C18: 0 | D18: Chưa bắt đầu | E18: 0
A19: 10 | B19: astatotilapia-burtoni-skeletal-ontogeny — 07 - Figures and Study Tools | C19: 0 | D19: Chưa bắt đầu | E19: 0
A20: 11 | B20: astatotilia-burtoni-skeletal-ontogeny — 03 - Axial and Median Fins | C20: 0 | D20: Chưa bắt đầu | E20: 0
A21: 12 | B21: astatotilia-burtoni-skeletal-ontogeny — 07 - Figures and Study Tools | C21: 0 | D21: Chưa bắt đầu | E21: 0

Sheet C47 03 - VFX & mô phỏng Blender
A1: THEO DÕI KHÓA HỌC — 03 - VFX & mô phỏng Blender
A2: Mã khóa | B2: C47 | C2: Lĩnh vực | D2: 04 - Thiết kế & Sáng tạo số | E2: Chuyên ngành | F2: 03 - Blender & 3D
A3: Thư mục nguồn | B3: D:\Sao lưu\Udemy\Khóa học\04 - Thiết kế & Sáng tạo số\03 - Blender & 3D\03 - VFX & mô phỏng Blender
A5: TỔNG MODULE | C5: ĐÃ HOÀN THÀNH | E5: TIẾN ĐỘ TRUNG BÌNH | G5: ĐIỂM TRUNG BÌNH
A6: =COUNTA(B10:B13) -> 4 | C6: =COUNTIF(D10:D13,"Đã hoàn thành") -> 0 | E6: =IFERROR(AVERAGE(E10:E13),0) -> 0 | G6: =IFERROR(AVERAGE(F10:F13),"")
A8: Nhập Trạng thái, Tiến độ và Điểm ở các ô nền vàng. Tiến độ nhập từ 0% đến 100%; điểm từ 0 đến 10.
A9: STT | B9: Module | C9: Số bài | D9: Trạng thái | E9: Tiến độ (%) | F9: Điểm /10 | G9: Ngày hoàn thành | H9: Ghi chú
A10: 1 | B10: blender-2-8-tutorial-cell-fracture-explosion | C10: 1 | D10: Chưa bắt đầu | E10: 0
A11: 2 | B11: blender-tutorial-quick-explosion-simulation-with-mantaflow-in-cycles | C11: 1 | D11: Chưa bắt đầu | E11: 0
A12: 3 | B12: blender-tutorial-surface-cracks | C12: 1 | D12: Chưa bắt đầu | E12: 0
A13: 4 | B13: how-to-create-glowing-surface-cracks-blender-tutorial | C13: 1 | D13: Chưa bắt đầu | E13: 0

Sheet C46 02 - Animation cá trong Ble
A1: THEO DÕI KHÓA HỌC — 02 - Animation cá trong Blender
A2: Mã khóa | B2: C46 | C2: Lĩnh vực | D2: 04 - Thiết kế & Sáng tạo số | E2: Chuyên ngành | F2: 03 - Blender & 3D
A3: Thư mục nguồn | B3: D:\Sao lưu\Udemy\Khóa học\04 - Thiết kế & Sáng tạo số\03 - Blender & 3D\02 - Animation cá trong Blender
A5: TỔNG MODULE | C5: ĐÃ HOÀN THÀNH | E5: TIẾN ĐỘ TRUNG BÌNH | G5: ĐIỂM TRUNG BÌNH
A6: =COUNTA(B10:B13) -> 4 | C6: =COUNTIF(D10:D13,"Đã hoàn thành") -> 0 | E6: =IFERROR(AVERAGE(E10:E13),0) -> 0 | G6: =IFERROR(AVERAGE(F10:F13),"")
A8: Nhập Trạng thái, Tiến độ và Điểm ở các ô nền vàng. Tiến độ nhập từ 0% đến 100%; điểm từ 0 đến 10.
A9: STT | B9: Module | C9: Số bài | D9: Trạng thái | E9: Tiến độ (%) | F9: Điểm /10 | G9: Ngày hoàn thành | H9: Ghi chú
A10: 1 | B10: animate-and-render-a-fish-in-blender | C10: 11 | D10: Chưa bắt đầu | E10: 0
A11: 2 | B11: blender-2-8-particle-school-of-fish-following-a-leader | C11: 8 | D11: Chưa bắt đầu | E11: 0
A12: 3 | B12: creating-an-animated-school-of-fish-in-blender | C12: 12 | D12: Chưa bắt đầu | E12: 0
A13: 4 | B13: the-secret-to-easy-fish-animation-in-blender | C13: 9 | D13: Chưa bắt đầu | E13: 0

Sheet C45 01 - Blender tổng quát
A1: THEO DÕI KHÓA HỌC — 01 - Blender tổng quát
A2: Mã khóa | B2: C45 | C2: Lĩnh vực | D2: 04 - Thiết kế & Sáng tạo số | E2: Chuyên ngành | F2: 03 - Blender & 3D
A3: Thư mục nguồn | B3: D:\Sao lưu\Udemy\Khóa học\04 - Thiết kế & Sáng tạo số\03 - Blender & 3D\01 - Blender tổng quát
A5: TỔNG MODULE | C5: ĐÃ HOÀN THÀNH | E5: TIẾN ĐỘ TRUNG BÌNH | G5: ĐIỂM TRUNG BÌNH
A6: =COUNTA(B10:B59) -> 50 | C6: =COUNTIF(D10:D59,"Đã hoàn thành") -> 0 | E6: =IFERROR(AVERAGE(E10:E59),0) -> 0 | G6: =IFERROR(AVERAGE(F10:F59),"")
A8: Nhập Trạng thái, Tiến độ và Điểm ở các ô nền vàng. Tiến độ nhập từ 0% đến 100%; điểm từ 0 đến 10.
A9: STT | B9: Module | C9: Số bài | D9: Trạng thái | E9: Tiến độ (%) | F9: Điểm /10 | G9: Ngày hoàn thành | H9: Ghi chú
A10: 1 | B10: c — 01 - Introduction to Blender | C10: 9 | D10: Chưa bắt đầu | E10: 0
A11: 2 | B11: c — 02 - Modeling in Blender | C11: 10 | D11: Chưa bắt đầu | E11: 0
A12: 3 | B12: c — 03 - Materials | C12: 13 | D12: Chưa bắt đầu | E12: 0
A13: 4 | B13: c — 04 - Lights | C13: 9 | D13: Chưa bắt đầu | E13: 0
A14: 5 | B14: c — 05 - Sculpting | C14: 4 | D14: Chưa bắt đầu | E14: 0
A15: 6 | B15: c — 06 - Camera & Rendering | C15: 3 | D15: Chưa bắt đầu | E15: 0
A16: 7 | B16: c — 07 - Animation | C16: 5 | D16: Chưa bắt đầu | E16: 0
A17: 8 | B17: c — 08 - Practice | C17: 9 | D17: Chưa bắt đầu | E17: 0
A18: 9 | B18: complete-blender-creator-3d-modelling — 01 - Introduction & Setup | C18: 22 | D18: Chưa bắt đầu | E18: 0
A19: 10 | B19: complete-blender-creator-3d-modelling — 02 - Modular Dungeon | C19: 18 | D19: Chưa bắt đầu | E19: 0
A20: 11 | B20: complete-blender-creator-3d-modelling — 03 - Low-Poly Dinosaur | C20: 13 | D20: Chưa bắt đầu | E20: 0
A21: 12 | B21: complete-blender-creator-3d-modelling — 04 - UV Mapping | C21: 18 | D21: Chưa bắt đầu | E21: 0
... A59: 50 | B59: c — 36 - Bonus- Fast Learning | C59: 16 | D59: Chưa bắt đầu | E59: 0

Sheet C44 From Figma to Cursor & Clau
A1: THEO DÕI KHÓA HỌC — From Figma to Cursor & Claude Code with MCP — Building Sidebling.com
A2: Mã khóa | B2: C44 | C2: Lĩnh vực | D2: 04 - Thiết kế & Sáng tạo số | E2: Chuyên ngành | F2: 02 - Figma & Design-to-Code
A3: Thư mục nguồn | B3: D:\Sao lưu\Udemy\Khóa học\04 - Thiết kế & Sáng tạo số\02 - Figma & Design-to-Code\figma-to-cursor-claude-code-mcp
A5: TỔNG MODULE | C5: ĐÃ HOÀN THÀNH | E5: TIẾN ĐỘ TRUNG BÌNH | G5: ĐIỂM TRUNG BÌNH
A6: =COUNTA(B10:B10) -> 1 | C6: =COUNTIF(D10:D10,"Đã hoàn thành") -> 0 | E6: =IFERROR(AVERAGE(E10:E10),0) -> 0 | G6: =IFERROR(AVERAGE(F10:F10),"")
A8: Nhập Trạng thái, Tiến độ và Điểm ở các ô nền vàng. Tiến độ nhập từ 0% đến 100%; điểm từ 0 đến 10.
A9: STT | B9: Module | C9: Số bài | D9: Trạng thái | E9: Tiến độ (%) | F9: Điểm /10 | G9: Ngày hoàn thành | H9: Ghi chú
A10: 1 | B10: Lessons | C10: 15 | D10: Chưa bắt đầu | E10: 0

Sheet C43 Converting Figma Designs to
A1: THEO DÕI KHÓA HỌC — Converting Figma Designs to Code with Cursor + Figma MCP
A2: Mã khóa | B2: C43 | C2: Lĩnh vực | D2: 04 - Thiết kế & Sáng tạo số | E2: Chuyên ngành | F2: 02 - Figma & Design-to-Code
A3: Thư mục nguồn | B3: D:\Sao lưu\Udemy\Khóa học\04 - Thiết kế & Sáng tạo số\02 - Figma & Design-to-Code\figma-to-code-cursor-mcp
A5: TỔNG MODULE | C5: ĐÃ HOÀN THÀNH | E5: TIẾN ĐỘ TRUNG BÌNH | G5: ĐIỂM TRUNG BÌNH
A6: =COUNTA(B10:B10) -> 1 | C6: =COUNTIF(D10:D10,"Đã hoàn thành") -> 0 | E6: =IFERROR(AVERAGE(E10:E10),0) -> 0 | G6: =IFERROR(AVERAGE(F10:F10),"")
A8: Nhập Trạng thái, Tiến độ và Điểm ở các ô nền vàng. Tiến độ nhập từ 0% đến 100%; điểm từ 0 đến 10.
A9: STT | B9: Module | C9: Số bài | D9: Trạng thái | E9: Tiến độ (%) | F9: Điểm /10 | G9: Ngày hoàn thành | H9: Ghi chú
A10: 1 | B10: Lessons | C10: 9 | D10: Chưa bắt đầu | E10: 0

Sheet C42 Figma to Angular Mastery- D
A1: THEO DÕI KHÓA HỌC — Figma to Angular Mastery: Design to Code with AI
A2: Mã khóa | B2: C42 | C2: Lĩnh vực | D2: 04 - Thiết kế & Sáng tạo số | E2: Chuyên ngành | F2: 02 - Figma & Design-to-Code
A3: Thư mục nguồn | B3: D:\Sao lưu\Udemy\Khóa học\04 - Thiết kế & Sáng tạo số\02 - Figma & Design-to-Code\figma-to-angular-mastery
A5: TỔNG MODULE | C5: ĐÃ HOÀN THÀNH | E5: TIẾN ĐỘ TRUNG BÌNH | G5: ĐIỂM TRUNG BÌNH
A6: =COUNTA(B10:B18) -> 9 | C6: =COUNTIF(D10:D18,"Đã hoàn thành") -> 0 | E6: =IFERROR(AVERAGE(E10:E18),0) -> 0 | G6: =IFERROR(AVERAGE(F10:F18),"")
A8: Nhập Trạng thái, Tiến độ và Điểm ở các ô nền vàng. Tiến độ nhập từ 0% đến 100%; điểm từ 0 đến 10.
A9: STT | B9: Module | C9: Số bài | D9: Trạng thái | E9: Tiến độ (%) | F9: Điểm /10 | G9: Ngày hoàn thành | H9: Ghi chú
A10: 1 | B10: 01 - Welcome and Setup | C10: 5 | D10: Chưa bắt đầu | E10: 0
A11: 2 | B11: 02 - Crash Course - Figma for Non-Designers | C11: 7 | D11: Chưa bắt đầu | E11: 0
A12: 3 | B12: 03 - AI plus Windsurf Editor Magic | C12: 6 | D12: Chưa bắt đầu | E12: 0
A13: 4 | B13: 04 - Reading Figma Like a Developer | C13: 3 | D13: Chưa bắt đầu | E13: 0
A14: 5 | B14: 05 - Atoms in Angular | C14: 1 | D14: Chưa bắt đầu | E14: 0
A15: 6 | B15: 06 - Molecules in Angular | C15: 1 | D15: Chưa bắt đầu | E15: 0
A16: 7 | B16: 07 - Organisms in Angular | C16: 1 | D16: Chưa bắt đầu | E16: 0
A17: 8 | B17: 08 - Templates and Pages | C17: 2 | D17: Chưa bắt đầu | E17: 0
A18: 9 | B18: 09 - Final Wrap-Up and Project | C18: 1 | D18: Chưa bắt đầu | E18: 0

Sheet C41 Vibe-Coding Figma Design Sy
A1: THEO DÕI KHÓA HỌC — Vibe-Coding Figma Design System Components with Cursor & Figma MCP
A2: Mã khóa | B2: C41 | C2: Lĩnh vực | D2: 04 - Thiết kế & Sáng tạo số | E2: Chuyên ngành | F2: 02 - Figma & Design-to-Code
A3: Thư mục nguồn | B3: D:\Sao lưu\Udemy\Khóa học\04 - Thiết kế & Sáng tạo số\02 - Figma & Design-to-Code\figma-mcp-cursor-vibe-coding
A5: TỔNG MODULE | C5: ĐÃ HOÀN THÀNH | E5: TIẾN ĐỘ TRUNG BÌNH | G5: ĐIỂM TRUNG BÌNH
A6: =COUNTA(B10:B10) -> 1 | C6: =COUNTIF(D10:D10,"Đã hoàn thành") -> 0 | E6: =IFERROR(AVERAGE(E10:E10),0) -> 0 | G6: =IFERROR(AVERAGE(F10:F10),"")
A8: Nhập Trạng thái, Tiến độ và Điểm ở các ô nền vàng. Tiến độ nhập từ 0% đến 100%; điểm từ 0 đến 10.
A9: STT | B9: Module | C9: Số bài | D9: Trạng thái | E9: Tiến độ (%) | F9: Điểm /10 | G9: Ngày hoàn thành | H9: Ghi chú
A10: 1 | B10: Lessons | C10: 8 | D10: Chưa bắt đầu | E10: 0

Sheet C40 Design to Code with Figma M
A1: THEO DÕI KHÓA HỌC — Design to Code with Figma MCP and Cursor
A2: Mã khóa | B2: C40 | C2: Lĩnh vực | D2: 04 - Thiết kế & Sáng tạo số | E2: Chuyên ngành | F2: 02 - Figma & Design-to-Code
A3: Thư mục nguồn | B3: D:\Sao lưu\Udemy\Khóa học\04 - Thiết kế & Sáng tạo số\02 - Figma & Design-to-Code\design-to-code-figma-mcp-cursor
A5: TỔNG MODULE | C5: ĐÃ HOÀN THÀNH | E5: TIẾN ĐỘ TRUNG BÌNH | G5: ĐIỂM TRUNG BÌNH
A6: =COUNTA(B10:B10) -> 1 | C6: =COUNTIF(D10:D10,"Đã hoàn thành") -> 0 | E6: =IFERROR(AVERAGE(E10:E10),0) -> 0 | G6: =IFERROR(AVERAGE(F10:F10),"")
A8: Nhập Trạng thái, Tiến độ và Điểm ở các ô nền vàng. Tiến độ nhập từ 0% đến 100%; điểm từ 0 đến 10.
A9: STT | B9: Module | C9: Số bài | D9: Trạng thái | E9: Tiến độ (%) | F9: Điểm /10 | G9: Ngày hoàn thành | H9: Ghi chú
A10: 1 | B10: Lessons | C10: 13 | D10: Chưa bắt đầu | E10: 0

Sheet C39 Claude Code + Figma MCP Ser
A1: THEO DÕI KHÓA HỌC — Claude Code + Figma MCP Server for Design to Code
A2: Mã khóa | B2: C39 | C2: Lĩnh vực | D2: 04 - Thiết kế & Sáng tạo số | E2: Chuyên ngành | F2: 02 - Figma & Design-to-Code
A3: Thư mục nguồn | B3: D:\Sao lưu\Udemy\Khóa học\04 - Thiết kế & Sáng tạo số\02 - Figma & Design-to-Code\claude-code-figma-mcp-design-to-code
A5: TỔNG MODULE | C5: ĐÃ HOÀN THÀNH | E5: TIẾN ĐỘ TRUNG BÌNH | G5: ĐIỂM TRUNG BÌNH
A6: =COUNTA(B10:B10) -> 1 | C6: =COUNTIF(D10:D10,"Đã hoàn thành") -> 0 | E6: =IFERROR(AVERAGE(E10:E10),0) -> 0 | G6: =IFERROR(AVERAGE(F10:F10),"")
A8: Nhập Trạng thái, Tiến độ và Điểm ở các ô nền vàng. Tiến độ nhập từ 0% đến 100%; điểm từ 0 đến 10.
A9: STT | B9: Module | C9: Số bài | D9: Trạng thái | E9: Tiến độ (%) | F9: Điểm /10 | G9: Ngày hoàn thành | H9: Ghi chú
A10: 1 | B10: Lessons | C10: 8 | D10: Chưa bắt đầu | E10: 0

Sheet C38 The Complete Vibe coding fo
A1: THEO DÕI KHÓA HỌC — The Complete Vibe coding for UX/UI Designers
A2: Mã khóa | B2: C38 | C2: Lĩnh vực | D2: 04 - Thiết kế & Sáng tạo số | E2: Chuyên ngành | F2: 01 - UX-UI & Design Systems
A3: Thư mục nguồn | B3: D:\Sao lưu\Udemy\Khóa học\04 - Thiết kế & Sáng tạo số\01 - UX-UI & Design Systems\vibe-coding-for-ux-ui-designers
A5: TỔNG MODULE | C5: ĐÃ HOÀN THÀNH | E5: TIẾN ĐỘ TRUNG BÌNH | G5: ĐIỂM TRUNG BÌNH
A6: =COUNTA(B10:B23) -> 14 | C6: =COUNTIF(D10:D23,"Đã hoàn thành") -> 0 | E6: =IFERROR(AVERAGE(E10:E23),0) -> 0 | G6: =IFERROR(AVERAGE(F10:F23),"")
A8: Nhập Trạng thái, Tiến độ và Điểm ở các ô nền vàng. Tiến độ nhập từ 0% đến 100%; điểm từ 0 đến 10.
A9: STT | B9: Module | C9: Số bài | D9: Trạng thái | E9: Tiến độ (%) | F9: Điểm /10 | G9: Ngày hoàn thành | H9: Ghi chú
A10: 1 | B10: 01 - Introduction to Vibe Coding for UX-UI Designers | C10: 7 | D10: Chưa bắt đầu | E10: 0
A11: 2 | B11: 02 - Mastering Prompts | C11: 8 | D11: Chưa bắt đầu | E11: 0
A12: 3 | B12: 03 - AI as Your Design Partner | C12: 6 | D12: Chưa bắt đầu | E12: 0
A13: 4 | B13: 04 - Figma Project - Prototyping and animation | C13: 8 | D13: Chưa bắt đầu | E13: 0
A14: 5 | B14: 05 - Building Design systems | C14: 8 | D14: Chưa bắt đầu | E14: 0
A15: 6 | B15: 06 - Using Lovable AI | C15: 7 | D15: Chưa bắt đầu | E15: 0
A16: 7 | B16: 07 - Using Cursor | C16: 4 | D16: Chưa bắt đầu | E16: 0
A17: 8 | B17: 08 - Using Windsurf | C17: 4 | D17: Chưa bắt đầu | E17: 0
A18: 9 | B18: 09 - Using V0 | C18: 10 | D18: Chưa bắt đầu | E18: 0
A19: 10 | B19: 10 - Build, Test, Deploy | C19: 7 | D19: Chưa bắt đầu | E19: 0
A20: 11 | B20: 11 - GenAI for Vibe Coding and Development | C20: 1 | D20: Chưa bắt đầu | E20: 0
A21: 12 | B21: 12 - AI Ethics and Career Growth with AI | C21: 9 | D21: Chưa bắt đầu | E21: 0
... A23: 14 | B23: 14 - Final | C23: 7 | D23: Chưa bắt đầu | E23: 0

Sheet C37 ux-design-roadmap
A1: THEO DÕI KHÓA HỌC — ux-design-roadmap
A2: Mã khóa | B2: C37 | C2: Lĩnh vực | D2: 04 - Thiết kế & Sáng tạo số | E2: Chuyên ngành | F2: 01 - UX-UI & Design Systems
A3: Thư mục nguồn | B3: D:\Sao lưu\Udemy\Khóa học\04 - Thiết kế & Sáng tạo số\01 - UX-UI & Design Systems\ux-design-roadmap
A5: TỔNG MODULE | C5: ĐÃ HOÀN THÀNH | E5: TIẾN ĐỘ TRUNG BÌNH | G5: ĐIỂM TRUNG BÌNH
A6: =COUNTA(B10:B10) -> 1 | C6: =COUNTIF(D10:D10,"Đã hoàn thành") -> 0 | E6: =IFERROR(AVERAGE(E10:E10),0) -> 0 | G6: =IFERROR(AVERAGE(F10:F10),"")
A8: Nhập Trạng thái, Tiến độ và Điểm ở các ô nền vàng. Tiến độ nhập từ 0% đến 100%; điểm từ 0 đến 10.
A9: STT | B9: Module | C9: Số bài | D9: Trạng thái | E9: Tiến độ (%) | F9: Điểm /10 | G9: Ngày hoàn thành | H9: Ghi chú
A10: 1 | B10: 00 - Roadmap.sh UX Design Official | C10: 41 | D10: Chưa bắt đầu | E10: 0

Sheet C36 Design System & Figma Varia
A1: THEO DÕI KHÓA HỌC — Design System & Figma Variable Set Up - Full Tutorial
A2: Mã khóa | B2: C36 | C2: Lĩnh vực | D2: 04 - Thiết kế & Sáng tạo số | E2: Chuyên ngành | F2: 01 - UX-UI & Design Systems
A3: Thư mục nguồn | B3: D:\Sao lưu\Udemy\Khóa học\04 - Thiết kế & Sáng tạo số\01 - UX-UI & Design Systems\design-system-figma-variable-setup-full-tutorial
A5: TỔNG MODULE | C5: ĐÃ HOÀN THÀNH | E5: TIẾN ĐỘ TRUNG BÌNH | G5: ĐIỂM TRUNG BÌNH
A6: =COUNTA(B10:B19) -> 10 | C6: =COUNTIF(D10:D19,"Đã hoàn thành") -> 0 | E6: =IFERROR(AVERAGE(E10:E19),0) -> 0 | G6: =IFERROR(AVERAGE(F10:F19),"")
A8: Nhập Trạng thái, Tiến độ và Điểm ở các ô nền vàng. Tiến độ nhập từ 0% đến 100%; điểm từ 0 đến 10.
A9: STT | B9: Module | C9: Số bài | D9: Trạng thái | E9: Tiến độ (%) | F9: Điểm /10 | G9: Ngày hoàn thành | H9: Ghi chú
A10: 1 | B10: 01 - Introduction to Figma Variables & Design Token Architecture | C10: 2 | D10: Chưa bắt đầu | E10: 0
A11: 2 | B11: 02 - Brand Collection Setup | C11: 4 | D11: Chưa bắt đầu | E11: 0
A12: 3 | B12: 03 - Scale System | C12: 2 | D12: Chưa bắt đầu | E12: 0
A13: 4 | B13: 04 - Alias Collection | C13: 7 | D13: Chưa bắt đầu | E13: 0
A14: 5 | B14: 05 - Multi-Brand Token Setup | C14: 2 | D14: Chưa bắt đầu | E14: 0
A15: 6 | B15: 06 - Mapped Collection | C15: 10 | D15: Chưa bắt đầu | E15: 0
A16: 7 | B16: 07 - Dark Mode Variables | C16: 1 | D16: Chưa bắt đầu | E16: 0
A17: 8 | B17: 08 - Responsive Variables | C17: 6 | D17: Chưa bắt đầu | E17: 0
A18: 9 | B18: 09 - Spacing & Jumper Variables | C18: 2 | D18: Chưa bắt đầu | E18: 0
A19: 10 | B19: 10 - Course Wrap-Up | C19: 1 | D19: Chưa bắt đầu | E19: 0

Sheet C35 Build a Design System - Ful
A1: THEO DÕI KHÓA HỌC — Build a Design System - Full Course
A2: Mã khóa | B2: C35 | C2: Lĩnh vực | D2: 04 - Thiết kế & Sáng tạo số | E2: Chuyên ngành | F2: 01 - UX-UI & Design Systems
A3: Thư mục nguồn | B3: D:\Sao lưu\Udemy\Khóa học\04 - Thiết kế & Sáng tạo số\01 - UX-UI & Design Systems\build-a-design-system-full-course
A5: TỔNG MODULE | C5: ĐÃ HOÀN THÀNH | E5: TIẾN ĐỘ TRUNG BÌNH | G5: ĐIỂM TRUNG BÌNH
A6: =COUNTA(B10:B18) -> 9 | C6: =COUNTIF(D10:D18,"Đã hoàn thành") -> 0 | E6: =IFERROR(AVERAGE(E10:E18),0) -> 0 | G6: =IFERROR(AVERAGE(F10:F18),"")
A8: Nhập Trạng thái, Tiến độ và Điểm ở các ô nền vàng. Tiến độ nhập từ 0% đến 100%; điểm từ 0 đến 10.
A9: STT | B9: Module | C9: Số bài | D9: Trạng thái | E9: Tiến độ (%) | F9: Điểm /10 | G9: Ngày hoàn thành | H9: Ghi chú
A10: 1 | B10: 01 - Introduction | C10: 1 | D10: Chưa bắt đầu | E10: 0
A11: 2 | B11: 02 - Design Tokens & Variables Setup | C11: 10 | D11: Chưa bắt đầu | E11: 0
A12: 3 | B12: 03 - Multi-Brand, Themes & Mapped Variables | C12: 8 | D12: Chưa bắt đầu | E12: 0
A13: 4 | B13: 04 - Typography & Responsive System | C13: 3 | D13: Chưa bắt đầu | E13: 0
A14: 5 | B14: 05 - Icons, Variable Scoping & First Component | C14: 4 | D14: Chưa bắt đầu | E14: 0
A15: 6 | B15: 06 - Form Components | C15: 8 | D15: Chưa bắt đầu | E15: 0
A16: 7 | B16: 07 - Navigation & Layout Components | C16: 5 | D16: Chưa bắt đầu | E16: 0
A17: 8 | B17: 08 - Display & Feedback Components | C17: 10 | D17: Chưa bắt đầu | E17: 0
A18: 9 | B18: 09 - Publishing & Scaling | C18: 1 | D18: Chưa bắt đầu | E18: 0

Sheet C34 blockchain-roadmap
A1: THEO DÕI KHÓA HỌC — blockchain-roadmap
A2: Mã khóa | B2: C34 | C2: Lĩnh vực | D2: 03 - Hạ tầng, Mạng & An ninh | E2: Chuyên ngành | F2: 03 - Blockchain & Web3
A3: Thư mục nguồn | B3: D:\Sao lưu\Udemy\Khóa học\03 - Hạ tầng, Mạng & An ninh\03 - Blockchain & Web3\blockchain-roadmap
A5: TỔNG MODULE | C5: ĐÃ HOÀN THÀNH | E5: TIẾN ĐỘ TRUNG BÌNH | G5: ĐIỂM TRUNG BÌNH
A6: =COUNTA(B10:B10) -> 1 | C6: =COUNTIF(D10:D10,"Đã hoàn thành") -> 0 | E6: =IFERROR(AVERAGE(E10:E10),0) -> 0 | G6: =IFERROR(AVERAGE(F10:F10),"")
A8: Nhập Trạng thái, Tiến độ và Điểm ở các ô nền vàng. Tiến độ nhập từ 0% đến 100%; điểm từ 0 đến 10.
A9: STT | B9: Module | C9: Số bài | D9: Trạng thái | E9: Tiến độ (%) | F9: Điểm /10 | G9: Ngày hoàn thành | H9: Ghi chú
A10: 1 | B10: 00 - Roadmap.sh Blockchain Developer Official | C10: 385 | D10: Chưa bắt đầu | E10: 0

Sheet C33 devsecops-roadmap
A1: THEO DÕI KHÓA HỌC — devsecops-roadmap
A2: Mã khóa | B2: C33 | C2: Lĩnh vực | D2: 03 - Hạ tầng, Mạng & An ninh | E2: Chuyên ngành | F2: 02 - An ninh mạng & DevSecOps
A3: Thư mục nguồn | B3: D:\Sao lưu\Udemy\Khóa học\03 - Hạ tầng, Mạng & An ninh\02 - An ninh mạng & DevSecOps\devsecops-roadmap
A5: TỔNG MODULE | C5: ĐÃ HOÀN THÀNH | E5: TIẾN ĐỘ TRUNG BÌNH | G5: ĐIỂM TRUNG BÌNH
A6: =COUNTA(B10:B10) -> 1 | C6: =COUNTIF(D10:D10,"Đã hoàn thành") -> 0 | E6: =IFERROR(AVERAGE(E10:E10),0) -> 0 | G6: =IFERROR(AVERAGE(F10:F10),"")
A8: Nhập Trạng thái, Tiến độ và Điểm ở các ô nền vàng. Tiến độ nhập từ 0% đến 100%; điểm từ 0 đến 10.
A9: STT | B9: Module | C9: Số bài | D9: Trạng thái | E9: Tiến độ (%) | F9: Điểm /10 | G9: Ngày hoàn thành | H9: Ghi chú
A10: 1 | B10: 00 - Roadmap.sh DevSecOps Official | C10: 84 | D10: Chưa bắt đầu | E10: 0

Sheet C32 Cyber Security Expert Roadm
A1: THEO DÕI KHÓA HỌC — Cyber Security Expert Roadmap 2026
A2: Mã khóa | B2: C32 | C2: Lĩnh vực | D2: 03 - Hạ tầng, Mạng & An ninh | E2: Chuyên ngành | F2: 02 - An ninh mạng & DevSecOps
A3: Thư mục nguồn | B3: D:\Sao lưu\Udemy\Khóa học\03 - Hạ tầng, Mạng & An ninh\02 - An ninh mạng & DevSecOps\cyber-security-roadmap
A5: TỔNG MODULE | C5: ĐÃ HOÀN THÀNH | E5: TIẾN ĐỘ TRUNG BÌNH | G5: ĐIỂM TRUNG BÌNH
A6: =COUNTA(B10:B10) -> 1 | C6: =COUNTIF(D10:D10,"Đã hoàn thành") -> 0 | E6: =IFERROR(AVERAGE(E10:E10),0) -> 0 | G6: =IFERROR(AVERAGE(F10:F10),"")
A8: Nhập Trạng thái, Tiến độ và Điểm ở các ô nền vàng. Tiến độ nhập từ 0% đến 100%; điểm từ 0 đến 10.
A9: STT | B9: Module | C9: Số bài | D9: Trạng thái | E9: Tiến độ (%) | F9: Điểm /10 | G9: Ngày hoàn thành | H9: Ghi chú
A10: 1 | B10: 00 - Cyber Security Expert Roadmap 2026 | C10: 114 | D10: Chưa bắt đầu | E10: 0

Sheet C31 network-engineer-roadmap
A1: THEO DÕI KHÓA HỌC — network-engineer-roadmap
A2: Mã khóa | B2: C31 | C2: Lĩnh vực | D2: 03 - Hạ tầng, Mạng & An ninh | E2: Chuyên ngành | F2: 01 - Mạng & Giao tiếp hệ thống
A3: Thư mục nguồn | B3: D:\Sao lưu\Udemy\Khóa học\03 - Hạ tầng, Mạng & An ninh\01 - Mạng & Giao tiếp hệ thống\network-engineer-roadmap
A5: TỔNG MODULE | C5: ĐÃ HOÀN THÀNH | E5: TIẾN ĐỘ TRUNG BÌNH | G5: ĐIỂM TRUNG BÌNH
A6: =COUNTA(B10:B11) -> 2 | C6: =COUNTIF(D10:D11,"Đã hoàn thành") -> 0 | E6: =IFERROR(AVERAGE(E10:E11),0) -> 0 | G6: =IFERROR(AVERAGE(F10:F11),"")
A8: Nhập Trạng thái, Tiến độ và Điểm ở các ô nền vàng. Tiến độ nhập từ 0% đến 100%; điểm từ 0 đến 10.
A9: STT | B9: Module | C9: Số bài | D9: Trạng thái | E9: Tiến độ (%) | F9: Điểm /10 | G9: Ngày hoàn thành | H9: Ghi chú
A10: 1 | B10: 00 - Roadmap.sh Network Engineer Official | C10: 40 | D10: Chưa bắt đầu | E10: 0
A11: 2 | B11: 99 - Network Engineering Labs | C11: 5 | D11: Chưa bắt đầu | E11: 0

Sheet C30 Fundamentals of Backend Com
A1: THEO DÕI KHÓA HỌC — Fundamentals of Backend Communications & Protocols
A2: Mã khóa | B2: C30 | C2: Lĩnh vực | D2: 03 - Hạ tầng, Mạng & An ninh | E2: Chuyên ngành | F2: 01 - Mạng & Giao tiếp hệ thống
A3: Thư mục nguồn | B3: D:\Sao lưu\Udemy\Khóa học\03 - Hạ tầng, Mạng & An ninh\01 - Mạng & Giao tiếp hệ thống\fundamentals-of-backend-communications-and-protocols
A5: TỔNG MODULE | C5: ĐÃ HOÀN THÀNH | E5: TIẾN ĐỘ TRUNG BÌNH | G5: ĐIỂM TRUNG BÌNH
A6: =COUNTA(B10:B17) -> 8 | C6: =COUNTIF(D10:D17,"Đã hoàn thành") -> 0 | E6: =IFERROR(AVERAGE(E10:E17),0) -> 0 | G6: =IFERROR(AVERAGE(F10:F17),"")
A8: Nhập Trạng thái, Tiến độ và Điểm ở các ô nền vàng. Tiến độ nhập từ 0% đến 100%; điểm từ 0 đến 10.
A9: STT | B9: Module | C9: Số bài | D9: Trạng thái | E9: Tiến độ (%) | F9: Điểm /10 | G9: Ngày hoàn thành | H9: Ghi chú
A10: 1 | B10: 01 - Introduction | C10: 5 | D10: Chưa bắt đầu | E10: 0
A11: 2 | B11: 02 - Backend Communication Design Patterns | C11: 11 | D11: Chưa bắt đầu | E11: 0
A12: 3 | B12: 03 - Protocols | C12: 14 | D12: Chưa bắt đầu | E12: 0
A13: 4 | B13: 04 - Many Ways to HTTPS | C13: 7 | D13: Chưa bắt đầu | E13: 0
A14: 5 | B14: 05 - Backend Execution Patterns | C14: 13 | D14: Chưa bắt đầu | E14: 0
A15: 6 | B15: 06 - Proxying and Load Balancing | C15: 3 | D15: Chưa bắt đầu | E15: 0
A16: 7 | B16: 07 - Extras | C16: 6 | D16: Chưa bắt đầu | E16: 0
A17: 8 | B17: 08 - Bonus Content | C17: 4 | D17: Chưa bắt đầu | E17: 0

Sheet C29 qa-roadmap
A1: THEO DÕI KHÓA HỌC — qa-roadmap
A2: Mã khóa | B2: C29 | C2: Lĩnh vực | D2: 02 - Lập trình & Phát triển phần mềm | E2: Chuyên ngành | F2: 04 - Kiểm thử phần mềm
A3: Thư mục nguồn | B3: D:\Sao lưu\Udemy\Khóa học\02 - Lập trình & Phát triển phần mềm\04 - Kiểm thử phần mềm\qa-roadmap
A5: TỔNG MODULE | C5: ĐÃ HOÀN THÀNH | E5: TIẾN ĐỘ TRUNG BÌNH | G5: ĐIỂM TRUNG BÌNH
A6: =COUNTA(B10:B10) -> 1 | C6: =COUNTIF(D10:D10,"Đã hoàn thành") -> 0 | E6: =IFERROR(AVERAGE(E10:E10),0) -> 0 | G6: =IFERROR(AVERAGE(F10:F10),"")
A8: Nhập Trạng thái, Tiến độ và Điểm ở các ô nền vàng. Tiến độ nhập từ 0% đến 100%; điểm từ 0 đến 10.
A9: STT | B9: Module | C9: Số bài | D9: Trạng thái | E9: Tiến độ (%) | F9: Điểm /10 | G9: Ngày hoàn thành | H9: Ghi chú
A10: 1 | B10: 00 - Roadmap.sh QA Engineer Official | C10: 498 | D10: Chưa bắt đầu | E10: 0

Sheet C28 software-architect-roadmap
A1: THEO DÕI KHÓA HỌC — software-architect-roadmap
A2: Mã khóa | B2: C28 | C2: Lĩnh vực | D2: 02 - Lập trình & Phát triển phần mềm | E2: Chuyên ngành | F2: 03 - Kiến trúc & Tích hợp
A3: Thư mục nguồn | B3: D:\Sao lưu\Udemy\Khóa học\02 - Lập trình & Phát triển phần mềm\03 - Kiến trúc & Tích hợp\software-architect-roadmap
A5: TỔNG MODULE | C5: ĐÃ HOÀN THÀNH | E5: TIẾN ĐỘ TRUNG BÌNH | G5: ĐIỂM TRUNG BÌNH
A6: =COUNTA(B10:B10) -> 1 | C6: =COUNTIF(D10:D10,"Đã hoàn thành") -> 0 | E6: =IFERROR(AVERAGE(E10:E10),0) -> 0 | G6: =IFERROR(AVERAGE(F10:F10),"")
A8: Nhập Trạng thái, Tiến độ và Điểm ở các ô nền vàng. Tiến độ nhập từ 0% đến 100%; điểm từ 0 đến 10.
A9: STT | B9: Module | C9: Số bài | D9: Trạng thái | E9: Tiến độ (%) | F9: Điểm /10 | G9: Ngày hoàn thành | H9: Ghi chú
A10: 1 | B10: 00 - Roadmap.sh Software Architect Official | C10: 105 | D10: Chưa bắt đầu | E10: 0

Sheet C27 Enterprise Integration Engi
A1: THEO DÕI KHÓA HỌC — Enterprise Integration Engineer Course
A2: Mã khóa | B2: C27 | C2: Lĩnh vực | D2: 02 - Lập trình & Phát triển phần mềm | E2: Chuyên ngành | F2: 03 - Kiến trúc & Tích hợp
A3: Thư mục nguồn | B3: D:\Sao lưu\Udemy\Khóa học\02 - Lập trình & Phát triển phần mềm\03 - Kiến trúc & Tích hợp\enterprise-integration-engineer-roadmap
A5: TỔNG MODULE | C5: ĐÃ HOÀN THÀNH | E5: TIẾN ĐỘ TRUNG BÌNH | G5: ĐIỂM TRUNG BÌNH
A6: =COUNTA(B10:B16) -> 7 | C6: =COUNTIF(D10:D16,"Đã hoàn thành") -> 0 | E6: =IFERROR(AVERAGE(E10:E16),0) -> 0 | G6: =IFERROR(AVERAGE(F10:F16),"")
A8: Nhập Trạng thái, Tiến độ và Điểm ở các ô nền vàng. Tiến độ nhập từ 0% đến 100%; điểm từ 0 đến 10.
A9: STT | B9: Module | C9: Số bài | D9: Trạng thái | E9: Tiến độ (%) | F9: Điểm /10 | G9: Ngày hoàn thành | H9: Ghi chú
A10: 1 | B10: 01 - Phase 1 - Backend Foundations and Integration | C10: 38 | D10: Chưa bắt đầu | E10: 0
A11: 2 | B11: 02 - Phase 2 - SOAP, XML, WSDL and Legacy Integration | C11: 16 | D11: Chưa bắt đầu | E11: 0
A12: 3 | B12: 03 - Phase 3 - TIBCO BW6 In Depth | C12: 40 | D12: Chưa bắt đầu | E12: 0
A13: 4 | B13: 04 - Phase 4 - API Gateway Kong and WSO2 | C13: 17 | D13: Chưa bắt đầu | E13: 0
A14: 5 | B14: 05 - Phase 5 - Kafka, Redis and Async Architecture | C14: 22 | D14: Chưa bắt đầu | E14: 0
A15: 6 | B15: 06 - Phase 6 - Production Engineering | C15: 29 | D15: Chưa bắt đầu | E15: 0
A16: 7 | B16: 07 - Phase 7 - Capstone Project | C16: 5 | D16: Chưa bắt đầu | E16: 0

Sheet C26 ios-roadmap
A1: THEO DÕI KHÓA HỌC — ios-roadmap
A2: Mã khóa | B2: C26 | C2: Lĩnh vực | D2: 02 - Lập trình & Phát triển phần mềm | E2: Chuyên ngành | F2: 02 - Mobile
A3: Thư mục nguồn | B3: D:\Sao lưu\Udemy\Khóa học\02 - Lập trình & Phát triển phần mềm\02 - Mobile\ios-roadmap
A5: TỔNG MODULE | C5: ĐÃ HOÀN THÀNH | E5: TIẾN ĐỘ TRUNG BÌNH | G5: ĐIỂM TRUNG BÌNH
A6: =COUNTA(B10:B10) -> 1 | C6: =COUNTIF(D10:D10,"Đã hoàn thành") -> 0 | E6: =IFERROR(AVERAGE(E10:E10),0) -> 0 | G6: =IFERROR(AVERAGE(F10:F10),"")
A8: Nhập Trạng thái, Tiến độ và Điểm ở các ô nền vàng. Tiến độ nhập từ 0% đến 100%; điểm từ 0 đến 10.
A9: STT | B9: Module | C9: Số bài | D9: Trạng thái | E9: Tiến độ (%) | F9: Điểm /10 | G9: Ngày hoàn thành | H9: Ghi chú
A10: 1 | B10: 00 - Roadmap.sh iOS Developer Official | C10: 457 | D10: Chưa bắt đầu | E10: 0

Sheet C25 Flutter & Dart- The Complet
A1: THEO DÕI KHÓA HỌC — Flutter & Dart: The Complete Guide
A2: Mã khóa | B2: C25 | C2: Lĩnh vực | D2: 02 - Lập trình & Phát triển phần mềm | E2: Chuyên ngành | F2: 02 - Mobile
A3: Thư mục nguồn | B3: D:\Sao lưu\Udemy\Khóa học\02 - Lập trình & Phát triển phần mềm\02 - Mobile\flutter-dart-the-complete-guide
A5: TỔNG MODULE | C5: ĐÃ HOÀN THÀNH | E5: TIẾN ĐỘ TRUNG BÌNH | G5: ĐIỂM TRUNG BÌNH
A6: =COUNTA(B10:B24) -> 15 | C6: =COUNTIF(D10:D24,"Đã hoàn thành") -> 0 | E6: =IFERROR(AVERAGE(E10:E24),0) -> 0 | G6: =IFERROR(AVERAGE(F10:F24),"")
A8: Nhập Trạng thái, Tiến độ và Điểm ở các ô nền vàng. Tiến độ nhập từ 0% đến 100%; điểm từ 0 đến 10.
A9: STT | B9: Module | C9: Số bài | D9: Trạng thái | E9: Tiến độ (%) | F9: Điểm /10 | G9: Ngày hoàn thành | H9: Ghi chú
A10: 1 | B10: 01 - Introduction | C10: 12 | D10: Chưa bắt đầu | E10: 0
A11: 2 | B11: 02 - Flutter & Dart Basics I - Getting a Solid Foundation [ROLL DICE APP] | C11: 40 | D11: Chưa bắt đầu | E11: 0
A12: 3 | B12: 03 - Flutter & Dart Basics II - Fundamentals Deep Dive [QUIZ APP] | C12: 40 | D12: Chưa bắt đầu | E12: 0
A13: 4 | B13: 04 - Debugging Flutter Apps | C13: 6 | D13: Chưa bắt đầu | E13: 0
A14: 5 | B14: 05 - Adding Interactivity, More Widgets & Theming [EXPENSE TRACKER APP] | C14: 38 | D14: Chưa bắt đầu | E14: 0
A15: 6 | B15: 06 - Building Responsive & Adaptive User Interfaces [EXPENSE TRACKER APP] | C15: 10 | D15: Chưa bắt đầu | E15: 0
A16: 7 | B16: 07 - Flutter & Dart Internals [TODO APP] | C16: 9 | D16: Chưa bắt đầu | E16: 0
A17: 8 | B17: 08 - Building Multi-Screen Apps & Navigating Between Screens [MEALS APP] | C17: 28 | D17: Chưa bắt đầu | E17: 0
A18: 9 | B18: 09 - State Management with Riverpod | C18: 17 | D18: Chưa bắt đầu | E18: 0
A19: 10 | B19: 10 - Animations | C19: 9 | D19: Chưa bắt đầu | E19: 0
A20: 11 | B20: 11 - Forms & User Input [SHOPPING LIST APP] | C20: 14 | D20: Chưa bắt đầu | E20: 0
A21: 12 | B21: 12 - HTTP, Networking & Backend Communication | C21: 16 | D21: Chưa bắt đầu | E21: 0
... A24: 15 | B24: 15 - Course Roundup & Bonus | C24: 5 | D24: Chưa bắt đầu | E24: 0

Sheet C24 3-in-1 Flutter AI Mastercla
A1: THEO DÕI KHÓA HỌC — 3-in-1 Flutter AI Masterclass: 15 Apps with Cursor & Figma
A2: Mã khóa | B2: C24 | C2: Lĩnh vực | D2: 02 - Lập trình & Phát triển phần mềm | E2: Chuyên ngành | F2: 02 - Mobile
A3: Thư mục nguồn | B3: D:\Sao lưu\Udemy\Khóa học\02 - Lập trình & Phát triển phần mềm\02 - Mobile\flutter-ai-masterclass-cursor-figma
A5: TỔNG MODULE | C5: ĐÃ HOÀN THÀNH | E5: TIẾN ĐỘ TRUNG BÌNH | G5: ĐIỂM TRUNG BÌNH
A6: =COUNTA(B10:B31) -> 22 | C6: =COUNTIF(D10:D31,"Đã hoàn thành") -> 0 | E6: =IFERROR(AVERAGE(E10:E31),0) -> 0 | G6: =IFERROR(AVERAGE(F10:F31),"")
A8: Nhập Trạng thái, Tiến độ và Điểm ở các ô nền vàng. Tiến độ nhập từ 0% đến 100%; điểm từ 0 đến 10.
A9: STT | B9: Module | C9: Số bài | D9: Trạng thái | E9: Tiến độ (%) | F9: Điểm /10 | G9: Ngày hoàn thành | H9: Ghi chú
A10: 1 | B10: 01 - Introduction | C10: 3 | D10: Chưa bắt đầu | E10: 0
A11: 2 | B11: 02 - Flutter Setup on macOS - Build Android & iOS Apps | C11: 5 | D11: Chưa bắt đầu | E11: 0
A12: 3 | B12: 03 - Flutter Setup on Windows | C12: 3 | D12: Chưa bắt đầu | E12: 0
A13: 4 | B13: 04 - Expense Tracker - Your First App with Cursor | C13: 7 | D13: Chưa bắt đầu | E13: 0
A14: 5 | B14: 05 - Figma | C14: 2 | D14: Chưa bắt đầu | E14: 0
A15: 6 | B15: 06 - Calculator - Design with Figma, Build with Cursor | C15: 4 | D15: Chưa bắt đầu | E15: 0
A16: 7 | B16: 07 - Notes App - First Multi-Screen App | C16: 4 | D16: Chưa bắt đầu | E16: 0
A17: 8 | B17: 08 - Weather App with Cursor AI | C17: 9 | D17: Chưa bắt đầu | E17: 0
A18: 9 | B18: 09 - Design & Build AI Meal Planner | C18: 15 | D18: Chưa bắt đầu | E18: 0
A19: 10 | B19: 10 - WhatsApp Clone with Cursor | C19: 7 | D19: Chưa bắt đầu | E19: 0
A20: 11 | B20: 11 - WhatsApp Clone - Media, Groups & Figma UI | C20: 4 | D20: Chưa bắt đầu | E20: 0
A21: 12 | B21: 12 - WhatsApp Clone - App Enhancements | C21: 6 | D21: Chưa bắt đầu | E21: 0
... A31: 22 | B31: 22 - Grocery Delivery App UI | C31: 1 | D31: Chưa bắt đầu | E31: 0

Sheet C23 Android Developer Roadmap C
A1: THEO DÕI KHÓA HỌC — Android Developer Roadmap Course
A2: Mã khóa | B2: C23 | C2: Lĩnh vực | D2: 02 - Lập trình & Phát triển phần mềm | E2: Chuyên ngành | F2: 02 - Mobile
A3: Thư mục nguồn | B3: D:\Sao lưu\Udemy\Khóa học\02 - Lập trình & Phát triển phần mềm\02 - Mobile\android-roadmap
A5: TỔNG MODULE | C5: ĐÃ HOÀN THÀNH | E5: TIẾN ĐỘ TRUNG BÌNH | G5: ĐIỂM TRUNG BÌNH
A6: =COUNTA(B10:B10) -> 1 | C6: =COUNTIF(D10:D10,"Đã hoàn thành") -> 0 | E6: =IFERROR(AVERAGE(E10:E10),0) -> 0 | G6: =IFERROR(AVERAGE(F10:F10),"")
A8: Nhập Trạng thái, Tiến độ và Điểm ở các ô nền vàng. Tiến độ nhập từ 0% đến 100%; điểm từ 0 đến 10.
A9: STT | B9: Module | C9: Số bài | D9: Trạng thái | E9: Tiến độ (%) | F9: Điểm /10 | G9: Ngày hoàn thành | H9: Ghi chú
A10: 1 | B10: 00 - Roadmap.sh Android Developer Official | C10: 351 | D10: Chưa bắt đầu | E10: 0

Sheet C22 postgresql-dba-roadmap
A1: THEO DÕI KHÓA HỌC — postgresql-dba-roadmap
A2: Mã khóa | B2: C22 | C2: Lĩnh vực | D2: 02 - Lập trình & Phát triển phần mềm | E2: Chuyên ngành | F2: 01 - Web & Backend
A3: Thư mục nguồn | B3: D:\Sao lưu\Udemy\Khóa học\02 - Lập trình & Phát triển phần mềm\01 - Web & Backend\postgresql-dba-roadmap
A5: TỔNG MODULE | C5: ĐÃ HOÀN THÀNH | E5: TIẾN ĐỘ TRUNG BÌNH | G5: ĐIỂM TRUNG BÌNH
A6: =COUNTA(B10:B10) -> 1 | C6: =COUNTIF(D10:D10,"Đã hoàn thành") -> 0 | E6: =IFERROR(AVERAGE(E10:E10),0) -> 0 | G6: =IFERROR(AVERAGE(F10:F10),"")
A8: Nhập Trạng thái, Tiến độ và Điểm ở các ô nền vàng. Tiến độ nhập từ 0% đến 100%; điểm từ 0 đến 10.
A9: STT | B9: Module | C9: Số bài | D9: Trạng thái | E9: Tiến độ (%) | F9: Điểm /10 | G9: Ngày hoàn thành | H9: Ghi chú
A10: 1 | B10: 00 - Roadmap.sh PostgreSQL DBA Official | C10: 390 | D10: Chưa bắt đầu | E10: 0

Sheet C21 NodeJS - The Complete Guide
A1: THEO DÕI KHÓA HỌC — NodeJS - The Complete Guide
A2: Mã khóa | B2: C21 | C2: Lĩnh vực | D2: 02 - Lập trình & Phát triển phần mềm | E2: Chuyên ngành | F2: 01 - Web & Backend
A3: Thư mục nguồn | B3: D:\Sao lưu\Udemy\Khóa học\02 - Lập trình & Phát triển phần mềm\01 - Web & Backend\nodejs-the-complete-guide
A5: TỔNG MODULE | C5: ĐÃ HOÀN THÀNH | E5: TIẾN ĐỘ TRUNG BÌNH | G5: ĐIỂM TRUNG BÌNH
A6: =COUNTA(B10:B45) -> 36 | C6: =COUNTIF(D10:D45,"Đã hoàn thành") -> 0 | E6: =IFERROR(AVERAGE(E10:E45),0) -> 0 | G6: =IFERROR(AVERAGE(F10:F45),"")
A8: Nhập Trạng thái, Tiến độ và Điểm ở các ô nền vàng. Tiến độ nhập từ 0% đến 100%; điểm từ 0 đến 10.
A9: STT | B9: Module | C9: Số bài | D9: Trạng thái | E9: Tiến độ (%) | F9: Điểm /10 | G9: Ngày hoàn thành | H9: Ghi chú
A10: 1 | B10: 01 - Introduction | C10: 9 | D10: Chưa bắt đầu | E10: 0
A11: 2 | B11: 02 - Optional JavaScript - A Quick Refresher | C11: 14 | D11: Chưa bắt đầu | E11: 0
A12: 3 | B12: 03 - Understanding the Basics | C12: 18 | D12: Chưa bắt đầu | E12: 0
A13: 4 | B13: 04 - Improved Development Workflow and Debugging | C13: 16 | D13: Chưa bắt đầu | E13: 0
A14: 5 | B14: 05 - Working with Express.js | C14: 23 | D14: Chưa bắt đầu | E14: 0
A15: 6 | B15: 06 - Working with Dynamic Content & Adding Templating Engines | C15: 19 | D15: Chưa bắt đầu | E15: 0
A16: 7 | B16: 07 - The Model View Controller (MVC) | C16: 10 | D16: Chưa bắt đầu | E16: 0
A17: 8 | B17: 08 - Optional Enhancing the App | C17: 9 | D17: Chưa bắt đầu | E17: 0
A18: 9 | B18: 09 - Dynamic Routes & Advanced Models | C18: 20 | D18: Chưa bắt đầu | E18: 0
A19: 10 | B19: 10 - SQL Introduction | C19: 14 | D19: Chưa bắt đầu | E19: 0
A20: 11 | B20: 11 - Understanding Sequelize | C20: 27 | D20: Chưa bắt đầu | E20: 0
A21: 12 | B21: 12 - Working with NoSQL & Using MongoDB | C21: 33 | D21: Chưa bắt đầu | E21: 0
... A45: 36 | B45: 36 - Roundup | C45: 3 | D45: Chưa bắt đầu | E45: 0

Sheet C20 full-stack-developer-roadma
A1: THEO DÕI KHÓA HỌC — full-stack-developer-roadmap
A2: Mã khóa | B2: C20 | C2: Lĩnh vực | D2: 02 - Lập trình & Phát triển phần mềm | E2: Chuyên ngành | F2: 01 - Web & Backend
A3: Thư mục nguồn | B3: D:\Sao lưu\Udemy\Khóa học\02 - Lập trình & Phát triển phần mềm\01 - Web & Backend\full-stack-developer-roadmap
A5: TỔNG MODULE | C5: ĐÃ HOÀN THÀNH | E5: TIẾN ĐỘ TRUNG BÌNH | G5: ĐIỂM TRUNG BÌNH
A6: =COUNTA(B10:B10) -> 1 | C6: =COUNTIF(D10:D10,"Đã hoàn thành") -> 0 | E6: =IFERROR(AVERAGE(E10:E10),0) -> 0 | G6: =IFERROR(AVERAGE(F10:F10),"")
A8: Nhập Trạng thái, Tiến độ và Điểm ở các ô nền vàng. Tiến độ nhập từ 0% đến 100%; điểm từ 0 đến 10.
A9: STT | B9: Module | C9: Số bài | D9: Trạng thái | E9: Tiến độ (%) | F9: Điểm /10 | G9: Ngày hoàn thành | H9: Ghi chú
A10: 1 | B10: 00 - Roadmap.sh Full Stack Official | C10: 48 | D10: Chưa bắt đầu | E10: 0

Sheet C19 frontend-developer-roadmap
A1: THEO DÕI KHÓA HỌC — frontend-developer-roadmap
A2: Mã khóa | B2: C19 | C2: Lĩnh vực | D2: 02 - Lập trình & Phát triển phần mềm | E2: Chuyên ngành | F2: 01 - Web & Backend
A3: Thư mục nguồn | B3: D:\Sao lưu\Udemy\Khóa học\02 - Lập trình & Phát triển phần mềm\01 - Web & Backend\frontend-developer-roadmap
A5: TỔNG MODULE | C5: ĐÃ HOÀN THÀNH | E5: TIẾN ĐỘ TRUNG BÌNH | G5: ĐIỂM TRUNG BÌNH
A6: =COUNTA(B10:B10) -> 1 | C6: =COUNTIF(D10:D10,"Đã hoàn thành") -> 0 | E6: =IFERROR(AVERAGE(E10:E10),0) -> 0 | G6: =IFERROR(AVERAGE(F10:F10),"")
A8: Nhập Trạng thái, Tiến độ và Điểm ở các ô nền vàng. Tiến độ nhập từ 0% đến 100%; điểm từ 0 đến 10.
A9: STT | B9: Module | C9: Số bài | D9: Trạng thái | E9: Tiến độ (%) | F9: Điểm /10 | G9: Ngày hoàn thành | H9: Ghi chú
A10: 1 | B10: 00 - Roadmap.sh Frontend Official | C10: 166 | D10: Chưa bắt đầu | E10: 0

Sheet C18 Backend Developer Roadmap W
A1: THEO DÕI KHÓA HỌC — Backend Developer Roadmap Workspace
A2: Mã khóa | B2: C18 | C2: Lĩnh vực | D2: 02 - Lập trình & Phát triển phần mềm | E2: Chuyên ngành | F2: 01 - Web & Backend
A3: Thư mục nguồn | B3: D:\Sao lưu\Udemy\Khóa học\02 - Lập trình & Phát triển phần mềm\01 - Web & Backend\backend-developer-roadmap
A5: TỔNG MODULE | C5: ĐÃ HOÀN THÀNH | E5: TIẾN ĐỘ TRUNG BÌNH | G5: ĐIỂM TRUNG BÌNH
A6: =COUNTA(B10:B11) -> 2 | C6: =COUNTIF(D10:D11,"Đã hoàn thành") -> 0 | E6: =IFERROR(AVERAGE(E10:E11),0) -> 0 | G6: =IFERROR(AVERAGE(F10:F11),"")
A8: Nhập Trạng thái, Tiến độ và Điểm ở các ô nền vàng. Tiến độ nhập từ 0% đến 100%; điểm từ 0 đến 10.
A9: STT | B9: Module | C9: Số bài | D9: Trạng thái | E9: Tiến độ (%) | F9: Điểm /10 | G9: Ngày hoàn thành | H9: Ghi chú
A10: 1 | B10: B — 00 - Roadmap.sh Backend Official | C10: 159 | D10: Chưa bắt đầu | E10: 0
A11: 2 | B11: D — 00 - Roadmap.sh DevOps Official | C11: 142 | D11: Chưa bắt đầu | E11: 0

Sheet C17 Khóa Học Vibe Coding Cơ Bản
A1: THEO DÕI KHÓA HỌC — Khóa Học Vibe Coding Cơ Bản Cho Người Mới Bắt Đầu
A2: Mã khóa | B2: C17 | C2: Lĩnh vực | D2: 01 - AI & Dữ liệu | E2: Chuyên ngành | F2: 03 - AI hỗ trợ phát triển phần mềm
A3: Thư mục nguồn | B3: D:\Sao lưu\Udemy\Khóa học\01 - AI & Dữ liệu\03 - AI hỗ trợ phát triển phần mềm\khoa-hoc-vibe-coding-co-ban
A5: TỔNG MODULE | C5: ĐÃ HOÀN THÀNH | E5: TIẾN ĐỘ TRUNG BÌNH | G5: ĐIỂM TRUNG BÌNH
A6: =COUNTA(B10:B15) -> 6 | C6: =COUNTIF(D10:D15,"Đã hoàn thành") -> 0 | E6: =IFERROR(AVERAGE(E10:E15),0) -> 0 | G6: =IFERROR(AVERAGE(F10:F15),"")
A8: Nhập Trạng thái, Tiến độ và Điểm ở các ô nền vàng. Tiến độ nhập từ 0% đến 100%; điểm từ 0 đến 10.
A9: STT | B9: Module | C9: Số bài | D9: Trạng thái | E9: Tiến độ (%) | F9: Điểm /10 | G9: Ngày hoàn thành | H9: Ghi chú
A10: 1 | B10: Module 01 - Gioi Thieu | C10: 2 | D10: Chưa bắt đầu | E10: 0
A11: 2 | B11: Module 02 - Tong Quan Va Khai Niem Co Ban Ve Vibe Coding | C11: 2 | D11: Chưa bắt đầu | E11: 0
A12: 3 | B12: Module 03 - Tu No-Code Den Vibe Coding | C12: 4 | D12: Chưa bắt đầu | E12: 0
A13: 4 | B13: Module 04 - Ky Nang Prompting Vibe Code | C13: 5 | D13: Chưa bắt đầu | E13: 0
A14: 5 | B14: Module 05 - Thuc Hanh Du An Vibe Code | C14: 4 | D14: Chưa bắt đầu | E14: 0
A15: 6 | B15: Module 06 - Tong Ket Va Qua Tang | C15: 2 | D15: Chưa bắt đầu | E15: 0

Sheet C16 khoa-hoc-vibe-coding
A1: THEO DÕI KHÓA HỌC — khoa-hoc-vibe-coding
A2: Mã khóa | B2: C16 | C2: Lĩnh vực | D2: 01 - AI & Dữ liệu | E2: Chuyên ngành | F2: 03 - AI hỗ trợ phát triển phần mềm
A3: Thư mục nguồn | B3: D:\Sao lưu\Udemy\Khóa học\01 - AI & Dữ liệu\03 - AI hỗ trợ phát triển phần mềm\khoa-hoc-vibe-coding
A5: TỔNG MODULE | C5: ĐÃ HOÀN THÀNH | E5: TIẾN ĐỘ TRUNG BÌNH | G5: ĐIỂM TRUNG BÌNH
A6: =COUNTA(B10:B21) -> 12 | C6: =COUNTIF(D10:D21,"Đã hoàn thành") -> 0 | E6: =IFERROR(AVERAGE(E10:E21),0) -> 0 | G6: =IFERROR(AVERAGE(F10:F21),"")
A8: Nhập Trạng thái, Tiến độ và Điểm ở các ô nền vàng. Tiến độ nhập từ 0% đến 100%; điểm từ 0 đến 10.
A9: STT | B9: Module | C9: Số bài | D9: Trạng thái | E9: Tiến độ (%) | F9: Điểm /10 | G9: Ngày hoàn thành | H9: Ghi chú
A10: 1 | B10: Chuong 01 - Cach Mang Vibe Coding | C10: 1 | D10: Chưa bắt đầu | E10: 0
A11: 2 | B11: Chuong 02 - Gioi Thieu Moi Truong | C11: 1 | D11: Chưa bắt đầu | E11: 0
A12: 3 | B12: Chuong 03 - Cai Dat Moi Truong | C12: 2 | D12: Chưa bắt đầu | E12: 0
A13: 4 | B13: Chuong 04 - Chon Model AI | C13: 1 | D13: Chưa bắt đầu | E13: 0
A14: 5 | B14: Chuong 05 - Nghe Thuat Viet Prompt | C14: 1 | D14: Chưa bắt đầu | E14: 0
A15: 6 | B15: Chuong 06 - Tao Landing Page Dau Tien | C15: 1 | D15: Chưa bắt đầu | E15: 0
A16: 7 | B16: Chuong 06 - Xay App Desktop Dau Tien | C16: 1 | D16: Chưa bắt đầu | E16: 0
A17: 8 | B17: Chuong 07 - Cach Xu Ly Loi Reverse Debugging | C17: 1 | D17: Chưa bắt đầu | E17: 0
A18: 9 | B18: Chuong 08 - Refactor Va Toi Uu | C18: 1 | D18: Chưa bắt đầu | E18: 0
A19: 10 | B19: Chuong 09 - UI UX Polish | C19: 1 | D19: Chưa bắt đầu | E19: 0
A20: 11 | B20: Chuong 10-1 - Dong Goi Va Phat Hanh | C20: 1 | D20: Chưa bắt đầu | E20: 0
A21: 12 | B21: Chuong 10-2 - Ra Mat San Pham | C21: 1 | D21: Chưa bắt đầu | E21: 0

Sheet C15 Claude Code - The Practical
A1: THEO DÕI KHÓA HỌC — Claude Code - The Practical Guide
A2: Mã khóa | B2: C15 | C2: Lĩnh vực | D2: 01 - AI & Dữ liệu | E2: Chuyên ngành | F2: 03 - AI hỗ trợ phát triển phần mềm
A3: Thư mục nguồn | B3: D:\Sao lưu\Udemy\Khóa học\01 - AI & Dữ liệu\03 - AI hỗ trợ phát triển phần mềm\claude-code-the-practical-guide
A5: TỔNG MODULE | C5: ĐÃ HOÀN THÀNH | E5: TIẾN ĐỘ TRUNG BÌNH | G5: ĐIỂM TRUNG BÌNH
A6: =COUNTA(B10:B12) -> 3 | C6: =COUNTIF(D10:D12,"Đã hoàn thành") -> 0 | E6: =IFERROR(AVERAGE(E10:E12),0) -> 0 | G6: =IFERROR(AVERAGE(F10:F12),"")
A8: Nhập Trạng thái, Tiến độ và Điểm ở các ô nền vàng. Tiến độ nhập từ 0% đến 100%; điểm từ 0 đến 10.
A9: STT | B9: Module | C9: Số bài | D9: Trạng thái | E9: Tiến độ (%) | F9: Điểm /10 | G9: Ngày hoàn thành | H9: Ghi chú
A10: 1 | B10: 01 - Getting Started | C10: 18 | D10: Chưa bắt đầu | E10: 0
A11: 2 | B11: 02 - Key Features & Efficient Usage | C11: 27 | D11: Chưa bắt đầu | E11: 0
A12: 3 | B12: 03 - Beyond Local CLI Usage | C12: 9 | D12: Chưa bắt đầu | E12: 0

Sheet C14 The Complete Claude Code &
A1: THEO DÕI KHÓA HỌC — The Complete Claude Code & Claude Cowork Masterclass [2026]
A2: Mã khóa | B2: C14 | C2: Lĩnh vực | D2: 01 - AI & Dữ liệu | E2: Chuyên ngành | F2: 03 - AI hỗ trợ phát triển phần mềm
A3: Thư mục nguồn | B3: D:\Sao lưu\Udemy\Khóa học\01 - AI & Dữ liệu\03 - AI hỗ trợ phát triển phần mềm\claude-code-cowork-masterclass-2026
A5: TỔNG MODULE | C5: ĐÃ HOÀN THÀNH | E5: TIẾN ĐỘ TRUNG BÌNH | G5: ĐIỂM TRUNG BÌNH
A6: =COUNTA(B10:B22) -> 13 | C6: =COUNTIF(D10:D22,"Đã hoàn thành") -> 0 | E6: =IFERROR(AVERAGE(E10:E22),0) -> 0 | G6: =IFERROR(AVERAGE(F10:F22),"")
A8: Nhập Trạng thái, Tiến độ và Điểm ở các ô nền vàng. Tiến độ nhập từ 0% đến 100%; điểm từ 0 đến 10.
A9: STT | B9: Module | C9: Số bài | D9: Trạng thái | E9: Tiến độ (%) | F9: Điểm /10 | G9: Ngày hoàn thành | H9: Ghi chú
A10: 1 | B10: 01 - Course Introduction & Claude Cowork Fundamentals | C10: 14 | D10: Chưa bắt đầu | E10: 0
A11: 2 | B11: 02 - Claude Plugins, Data Plugin & Data Visualization | C11: 8 | D11: Chưa bắt đầu | E11: 0
A12: 3 | B12: 03 - Build Finance Plugin & Analyze Data Plugin | C12: 6 | D12: Chưa bắt đầu | E12: 0
A13: 4 | B13: 04 - Claude Chat, Prompt Engineering, Research & Creative Work | C13: 12 | D13: Chưa bắt đầu | E13: 0
A14: 5 | B14: 05 - Claude in Excel | C14: 9 | D14: Chưa bắt đầu | E14: 0
A15: 6 | B15: 06 - Financial Modeling with Claude Cowork & Excel | C15: 7 | D15: Chưa bắt đầu | E15: 0
A16: 7 | B16: 07 - Claude in PowerPoint | C16: 10 | D16: Chưa bắt đầu | E16: 0
A17: 8 | B17: 08 - Claude Code Setup & Landing Page Project | C17: 11 | D17: Chưa bắt đầu | E17: 0
A18: 9 | B18: 09 - Claude Slash Commands, Plugins, CLAUDE.md & Context Management | C18: 14 | D18: Chưa bắt đầu | E18: 0
A19: 10 | B19: 10 - Calorie Tracker Project with Claude Code + Gemini AI | C19: 7 | D19: Chưa bắt đầu | E19: 0
A20: 11 | B20: 11 - AI Agents, MCP & OpenAI Agents SDK | C20: 20 | D20: Chưa bắt đầu | E20: 0
A21: 12 | B21: 12 - Build Your Personal AI Agent with Claude Code & Cowork | C21: 17 | D21: Chưa bắt đầu | E21: 0
A22: 13 | B22: 13 - 10 Automation Blueprints with Claude Code & Cowork | C22: 23 | D22: Chưa bắt đầu | E22: 0

Sheet C13 claude-aiagents-cowork-mast
A1: THEO DÕI KHÓA HỌC — claude-aiagents-cowork-masterclass
A2: Mã khóa | B2: C13 | C2: Lĩnh vực | D2: 01 - AI & Dữ liệu | E2: Chuyên ngành | F2: 03 - AI hỗ trợ phát triển phần mềm
A3: Thư mục nguồn | B3: D:\Sao lưu\Udemy\Khóa học\01 - AI & Dữ liệu\03 - AI hỗ trợ phát triển phần mềm\claude-aiagents-cowork-masterclass
A5: TỔNG MODULE | C5: ĐÃ HOÀN THÀNH | E5: TIẾN ĐỘ TRUNG BÌNH | G5: ĐIỂM TRUNG BÌNH
A6: =COUNTA(B10:B22) -> 13 | C6: =COUNTIF(D10:D22,"Đã hoàn thành") -> 0 | E6: =IFERROR(AVERAGE(E10:E22),0) -> 0 | G6: =IFERROR(AVERAGE(F10:F22),"")
A8: Nhập Trạng thái, Tiến độ và Điểm ở các ô nền vàng. Tiến độ nhập từ 0% đến 100%; điểm từ 0 đến 10.
A9: STT | B9: Module | C9: Số bài | D9: Trạng thái | E9: Tiến độ (%) | F9: Điểm /10 | G9: Ngày hoàn thành | H9: Ghi chú
A10: 1 | B10: 01 - Masterclass Introduction, Success Tips & Welcome Message | C10: 4 | D10: Chưa bắt đầu | E10: 0
A11: 2 | B11: 02 - Claude Cowork, Skills & Plugins Mastery for Workflow Automation | C11: 23 | D11: Chưa bắt đầu | E11: 0
A12: 3 | B12: 03 - Claude Chat Mastery | C12: 13 | D12: Chưa bắt đầu | E12: 0
A13: 4 | B13: 04 - Claude in Microsoft Excel | C13: 16 | D13: Chưa bắt đầu | E13: 0
A14: 5 | B14: 05 - Claude in PowerPoint | C14: 10 | D14: Chưa bắt đầu | E14: 0
A15: 6 | B15: 06 - Claude Code Foundations | C15: 23 | D15: Chưa bắt đầu | E15: 0
A16: 7 | B16: 07 - Claude Code for Building Apps | C16: 9 | D16: Chưa bắt đầu | E16: 0
A17: 8 | B17: 08 - Claude Code for Building AI Agents | C17: 20 | D17: Chưa bắt đầu | E17: 0
A18: 9 | B18: 09 - Building Your Personal AI Agent with Claude Code & Cowork | C18: 1 | D18: Chưa bắt đầu | E18: 0
A19: 10 | B19: 10 - Your Personal AI Agent Architecture in Claude Code & Cowork | C19: 11 | D19: Chưa bắt đầu | E19: 0
A20: 11 | B20: 11 - Personal AI Agent Setup Process | C20: 5 | D20: Chưa bắt đầu | E20: 0
A21: 12 | B21: 12 - Automation Blueprints Part 1 | C21: 8 | D21: Chưa bắt đầu | E21: 0
A22: 13 | B22: 13 - Automation Blueprints Part 2 | C22: 15 | D22: Chưa bắt đầu | E22: 0

Sheet C12 AI Coder- Complete Claude C
A1: THEO DÕI KHÓA HỌC — AI Coder: Complete Claude Code & Coding Agents Course
A2: Mã khóa | B2: C12 | C2: Lĩnh vực | D2: 01 - AI & Dữ liệu | E2: Chuyên ngành | F2: 03 - AI hỗ trợ phát triển phần mềm
A3: Thư mục nguồn | B3: D:\Sao lưu\Udemy\Khóa học\01 - AI & Dữ liệu\03 - AI hỗ trợ phát triển phần mềm\ai-coder-complete-claude-code-coding-agents
A5: TỔNG MODULE | C5: ĐÃ HOÀN THÀNH | E5: TIẾN ĐỘ TRUNG BÌNH | G5: ĐIỂM TRUNG BÌNH
A6: =COUNTA(B10:B25) -> 16 | C6: =COUNTIF(D10:D25,"Đã hoàn thành") -> 0 | E6: =IFERROR(AVERAGE(E10:E25),0) -> 0 | G6: =IFERROR(AVERAGE(F10:F25),"")
A8: Nhập Trạng thái, Tiến độ và Điểm ở các ô nền vàng. Tiến độ nhập từ 0% đến 100%; điểm từ 0 đến 10.
A9: STT | B9: Module | C9: Số bài | D9: Trạng thái | E9: Tiến độ (%) | F9: Điểm /10 | G9: Ngày hoàn thành | H9: Ghi chú
A10: 1 | B10: 01 - Week 1 Day 1 - Introduction to AI Coding Agents | C10: 8 | D10: Chưa bắt đầu | E10: 0
A11: 2 | B11: 02 - Week 1 Day 2 - LLMs, Agents, Context Engineering | C11: 6 | D11: Chưa bắt đầu | E11: 0
A12: 3 | B12: 03 - Week 1 Day 3 - Hands-On with Cursor, Copilot, Codex, Antigravity | C12: 7 | D12: Chưa bắt đầu | E12: 0
A13: 4 | B13: 04 - Week 1 Day 4 - YOLO Mode, Model Choice, OpenRouter | C13: 6 | D13: Chưa bắt đầu | E13: 0
A14: 5 | B14: 05 - Week 1 Day 5 - Commercial MVP & Full-Stack Kanban | C14: 7 | D14: Chưa bắt đầu | E14: 0
A15: 6 | B15: 06 - Week 2 Day 1 - Claude Code Fundamentals | C15: 6 | D15: Chưa bắt đầu | E15: 0
A16: 7 | B16: 07 - Week 2 Day 2 - Claude Code Workflow | C16: 5 | D16: Chưa bắt đầu | E16: 0
A17: 8 | B17: 08 - Week 2 Day 3 - MCP, Skills, Plugins | C17: 7 | D17: Chưa bắt đầu | E17: 0
A18: 9 | B18: 09 - Week 2 Day 4 - Jira, GitHub, Professional Workflow | C18: 6 | D18: Chưa bắt đầu | E18: 0
A19: 10 | B19: 10 - Week 2 Day 5 - SaaS Legal Assistant | C19: 6 | D19: Chưa bắt đầu | E19: 0
A20: 11 | B20: 11 - Week 3 Day 1 - Sub-Agents, Hooks, Plugins | C20: 7 | D20: Chưa bắt đầu | E20: 0
A21: 12 | B21: 12 - Week 3 Day 2 - Sandboxing & Remote Execution | C21: 6 | D21: Chưa bắt đầu | E21: 0
... A25: 16 | B25: 16 - Bonus | C25: 1 | D25: Chưa bắt đầu | E25: 0

Sheet C11 machine-learning-roadmap
A1: THEO DÕI KHÓA HỌC — machine-learning-roadmap
A2: Mã khóa | B2: C11 | C2: Lĩnh vực | D2: 01 - AI & Dữ liệu | E2: Chuyên ngành | F2: 02 - Data Science, Analytics & ML
A3: Thư mục nguồn | B3: D:\Sao lưu\Udemy\Khóa học\01 - AI & Dữ liệu\02 - Data Science, Analytics & ML\machine-learning-roadmap
A5: TỔNG MODULE | C5: ĐÃ HOÀN THÀNH | E5: TIẾN ĐỘ TRUNG BÌNH | G5: ĐIỂM TRUNG BÌNH
A6: =COUNTA(B10:B10) -> 1 | C6: =COUNTIF(D10:D10,"Đã hoàn thành") -> 0 | E6: =IFERROR(AVERAGE(E10:E10),0) -> 0 | G6: =IFERROR(AVERAGE(F10:F10),"")
A8: Nhập Trạng thái, Tiến độ và Điểm ở các ô nền vàng. Tiến độ nhập từ 0% đến 100%; điểm từ 0 đến 10.
A9: STT | B9: Module | C9: Số bài | D9: Trạng thái | E9: Tiến độ (%) | F9: Điểm /10 | G9: Ngày hoàn thành | H9: Ghi chú
A10: 1 | B10: 00 - Roadmap.sh Machine Learning Official | C10: 367 | D10: Chưa bắt đầu | E10: 0

Sheet C10 Khóa Học Tính Toán Tiến Hóa
A1: THEO DÕI KHÓA HỌC — Khóa Học Tính Toán Tiến Hóa (Evolutionary Computation)
A2: Mã khóa | B2: C10 | C2: Lĩnh vực | D2: 01 - AI & Dữ liệu | E2: Chuyên ngành | F2: 02 - Data Science, Analytics & ML
A3: Thư mục nguồn | B3: D:\Sao lưu\Udemy\Khóa học\01 - AI & Dữ liệu\02 - Data Science, Analytics & ML\khoa-hoc-tinh-toan-tien-hoa
A5: TỔNG MODULE | C5: ĐÃ HOÀN THÀNH | E5: TIẾN ĐỘ TRUNG BÌNH | G5: ĐIỂM TRUNG BÌNH
A6: =COUNTA(B10:B19) -> 10 | C6: =COUNTIF(D10:D19,"Đã hoàn thành") -> 0 | E6: =IFERROR(AVERAGE(E10:E19),0) -> 0 | G6: =IFERROR(AVERAGE(F10:F19),"")
A8: Nhập Trạng thái, Tiến độ và Điểm ở các ô nền vàng. Tiến độ nhập từ 0% đến 100%; điểm từ 0 đến 10.
A9: STT | B9: Module | C9: Số bài | D9: Trạng thái | E9: Tiến độ (%) | F9: Điểm /10 | G9: Ngày hoàn thành | H9: Ghi chú
A10: 1 | B10: Chuong 01 - Gioi Thieu Tinh Toan Tien Hoa | C10: 1 | D10: Chưa bắt đầu | E10: 0
A11: 2 | B11: Chuong 02 - Giai Thuat Di Truyen | C11: 1 | D11: Chưa bắt đầu | E11: 0
A12: 3 | B12: Chuong 03 - Lap Trinh Di Truyen | C12: 1 | D12: Chưa bắt đầu | E12: 0
A13: 4 | B13: Chuong 04 - Lap Trinh Tien Hoa | C13: 1 | D13: Chưa bắt đầu | E13: 0
A14: 5 | B14: Chuong 05 - Chien Luoc Tien Hoa | C14: 1 | D14: Chưa bắt đầu | E14: 0
A15: 6 | B15: Chuong 06 - Tien Hoa Da Nhiem | C15: 1 | D15: Chưa bắt đầu | E15: 0
A16: 7 | B16: Chuong 07 - Tien Hoa Sai Phan | C16: 1 | D16: Chưa bắt đầu | E16: 0
A17: 8 | B17: Chuong 08 - Toi Uu Bay Dan | C17: 1 | D17: Chưa bắt đầu | E17: 0
A18: 9 | B18: Chuong 09 - Toi Uu Dan Kien | C18: 1 | D18: Chưa bắt đầu | E18: 0
A19: 10 | B19: Chuong 10 - Toi Uu Da Muc Tieu | C19: 1 | D19: Chưa bắt đầu | E19: 0

Sheet C09 data-engineer-roadmap
A1: THEO DÕI KHÓA HỌC — data-engineer-roadmap
A2: Mã khóa | B2: C09 | C2: Lĩnh vực | D2: 01 - AI & Dữ liệu | E2: Chuyên ngành | F2: 02 - Data Science, Analytics & ML
A3: Thư mục nguồn | B3: D:\Sao lưu\Udemy\Khóa học\01 - AI & Dữ liệu\02 - Data Science, Analytics & ML\data-engineer-roadmap
A5: TỔNG MODULE | C5: ĐÃ HOÀN THÀNH | E5: TIẾN ĐỘ TRUNG BÌNH | G5: ĐIỂM TRUNG BÌNH
A6: =COUNTA(B10:B10) -> 1 | C6: =COUNTIF(D10:D10,"Đã hoàn thành") -> 0 | E6: =IFERROR(AVERAGE(E10:E10),0) -> 0 | G6: =IFERROR(AVERAGE(F10:F10),"")
A8: Nhập Trạng thái, Tiến độ và Điểm ở các ô nền vàng. Tiến độ nhập từ 0% đến 100%; điểm từ 0 đến 10.
A9: STT | B9: Module | C9: Số bài | D9: Trạng thái | E9: Tiến độ (%) | F9: Điểm /10 | G9: Ngày hoàn thành | H9: Ghi chú
A10: 1 | B10: 00 - Roadmap.sh Data Engineer Official | C10: 347 | D10: Chưa bắt đầu | E10: 0

Sheet C08 data-analyst-roadmap
A1: THEO DÕI KHÓA HỌC — data-analyst-roadmap
A2: Mã khóa | B2: C08 | C2: Lĩnh vực | D2: 01 - AI & Dữ liệu | E2: Chuyên ngành | F2: 02 - Data Science, Analytics & ML
A3: Thư mục nguồn | B3: D:\Sao lưu\Udemy\Khóa học\01 - AI & Dữ liệu\02 - Data Science, Analytics & ML\data-analyst-roadmap
A5: TỔNG MODULE | C5: ĐÃ HOÀN THÀNH | E5: TIẾN ĐỘ TRUNG BÌNH | G5: ĐIỂM TRUNG BÌNH
A6: =COUNTA(B10:B10) -> 1 | C6: =COUNTIF(D10:D10,"Đã hoàn thành") -> 0 | E6: =IFERROR(AVERAGE(E10:E10),0) -> 0 | G6: =IFERROR(AVERAGE(F10:F10),"")
A8: Nhập Trạng thái, Tiến độ và Điểm ở các ô nền vàng. Tiến độ nhập từ 0% đến 100%; điểm từ 0 đến 10.
A9: STT | B9: Module | C9: Số bài | D9: Trạng thái | E9: Tiến độ (%) | F9: Điểm /10 | G9: Ngày hoàn thành | H9: Ghi chú
A10: 1 | B10: 00 - Roadmap.sh Data Analyst Official | C10: 100 | D10: Chưa bắt đầu | E10: 0

Sheet C07 bi-analyst-roadmap
A1: THEO DÕI KHÓA HỌC — bi-analyst-roadmap
A2: Mã khóa | B2: C07 | C2: Lĩnh vực | D2: 01 - AI & Dữ liệu | E2: Chuyên ngành | F2: 02 - Data Science, Analytics & ML
A3: Thư mục nguồn | B3: D:\Sao lưu\Udemy\Khóa học\01 - AI & Dữ liệu\02 - Data Science, Analytics & ML\bi-analyst-roadmap
A5: TỔNG MODULE | C5: ĐÃ HOÀN THÀNH | E5: TIẾN ĐỘ TRUNG BÌNH | G5: ĐIỂM TRUNG BÌNH
A6: =COUNTA(B10:B11) -> 2 | C6: =COUNTIF(D10:D11,"Đã hoàn thành") -> 0 | E6: =IFERROR(AVERAGE(E10:E11),0) -> 0 | G6: =IFERROR(AVERAGE(F10:F11),"")
A8: Nhập Trạng thái, Tiến độ và Điểm ở các ô nền vàng. Tiến độ nhập từ 0% đến 100%; điểm từ 0 đến 10.
A9: STT | B9: Module | C9: Số bài | D9: Trạng thái | E9: Tiến độ (%) | F9: Điểm /10 | G9: Ngày hoàn thành | H9: Ghi chú
A10: 1 | B10: 00 - Roadmap.sh BI Analyst Official | C10: 68 | D10: Chưa bắt đầu | E10: 0
A11: 2 | B11: 99 - Portfolio Projects | C11: 5 | D11: Chưa bắt đầu | E11: 0

Sheet C06 AI & Data Scientist Roadmap
A1: THEO DÕI KHÓA HỌC — AI & Data Scientist Roadmap Course
A2: Mã khóa | B2: C06 | C2: Lĩnh vực | D2: 01 - AI & Dữ liệu | E2: Chuyên ngành | F2: 02 - Data Science, Analytics & ML
A3: Thư mục nguồn | B3: D:\Sao lưu\Udemy\Khóa học\01 - AI & Dữ liệu\02 - Data Science, Analytics & ML\ai-data-scientist-roadmap
A5: TỔNG MODULE | C5: ĐÃ HOÀN THÀNH | E5: TIẾN ĐỘ TRUNG BÌNH | G5: ĐIỂM TRUNG BÌNH
A6: =COUNTA(B10:B10) -> 1 | C6: =COUNTIF(D10:D10,"Đã hoàn thành") -> 0 | E6: =IFERROR(AVERAGE(E10:E10),0) -> 0 | G6: =IFERROR(AVERAGE(F10:F10),"")
A8: Nhập Trạng thái, Tiến độ và Điểm ở các ô nền vàng. Tiến độ nhập từ 0% đến 100%; điểm từ 0 đến 10.
A9: STT | B9: Module | C9: Số bài | D9: Trạng thái | E9: Tiến độ (%) | F9: Điểm /10 | G9: Ngày hoàn thành | H9: Ghi chú
A10: 1 | B10: 00 - Roadmap.sh AI Data Scientist Official | C10: 203 | D10: Chưa bắt đầu | E10: 0

Sheet C05 Ultimate RAG Bootcamp Using
A1: THEO DÕI KHÓA HỌC — Ultimate RAG Bootcamp Using LangChain, LangGraph & LangSmith
A2: Mã khóa | B2: C05 | C2: Lĩnh vực | D2: 01 - AI & Dữ liệu | E2: Chuyên ngành | F2: 01 - AI Engineering & LLM
A3: Thư mục nguồn | B3: D:\Sao lưu\Udemy\Khóa học\01 - AI & Dữ liệu\01 - AI Engineering & LLM\ultimate-rag-bootcamp
A5: TỔNG MODULE | C5: ĐÃ HOÀN THÀNH | E5: TIẾN ĐỘ TRUNG BÌNH | G5: ĐIỂM TRUNG BÌNH
A6: =COUNTA(B10:B38) -> 29 | C6: =COUNTIF(D10:D38,"Đã hoàn thành") -> 0 | E6: =IFERROR(AVERAGE(E10:E38),0) -> 0 | G6: =IFERROR(AVERAGE(F10:F38),"")
A8: Nhập Trạng thái, Tiến độ và Điểm ở các ô nền vàng. Tiến độ nhập từ 0% đến 100%; điểm từ 0 đến 10.
A9: STT | B9: Module | C9: Số bài | D9: Trạng thái | E9: Tiến độ (%) | F9: Điểm /10 | G9: Ngày hoàn thành | H9: Ghi chú
A10: 1 | B10: 01 - Introduction | C10: 1 | D10: Chưa bắt đầu | E10: 0
A11: 2 | B11: 02 - Introduction To RAG | C11: 4 | D11: Chưa bắt đầu | E11: 0
A12: 3 | B12: 03 - Core Components In RAG | C12: 2 | D12: Chưa bắt đầu | E12: 0
A13: 4 | B13: 04 - VS Code And Anaconda Installation | C13: 1 | D13: Chưa bắt đầu | E13: 0
A14: 5 | B14: 05 - Data Ingestion And Data Parsing Techniques | C14: 4 | D14: Chưa bắt đầu | E14: 0
A15: 6 | B15: 06 - Vector Embedding And Vector Databases | C15: 0 | D15: Chưa bắt đầu | E15: 0
A16: 7 | B16: 07 - Vector Stores And Vector Databases | C16: 0 | D16: Chưa bắt đầu | E16: 0
A17: 8 | B17: 08 - Advanced Chunking And Preprocessing Techniques | C17: 0 | D17: Chưa bắt đầu | E17: 0
A18: 9 | B18: 09 - Hybrid Search Strategies | C18: 0 | D18: Chưa bắt đầu | E18: 0
A19: 10 | B19: 10 - Query Enhancement | C19: 0 | D19: Chưa bắt đầu | E19: 0
A20: 11 | B20: 11 - MultiModal RAG | C20: 0 | D20: Chưa bắt đầu | E20: 0
A21: 12 | B21: 12 - Getting Started With AI Agents And Agentic AI | C21: 0 | D21: Chưa bắt đầu | E21: 0
... A38: 29 | B38: 29 - RolePlay | C38: 0 | D38: Chưa bắt đầu | E38: 0

Sheet C04 Basic to Advanced- Retrieva
A1: THEO DÕI KHÓA HỌC — Basic to Advanced: Retrieval-Augmented Generation — RAG
A2: Mã khóa | B2: C04 | C2: Lĩnh vực | D2: 01 - AI & Dữ liệu | E2: Chuyên ngành | F2: 01 - AI Engineering & LLM
A3: Thư mục nguồn | B3: D:\Sao lưu\Udemy\Khóa học\01 - AI & Dữ liệu\01 - AI Engineering & LLM\rag-basic-to-advanced
A5: TỔNG MODULE | C5: ĐÃ HOÀN THÀNH | E5: TIẾN ĐỘ TRUNG BÌNH | G5: ĐIỂM TRUNG BÌNH
A6: =COUNTA(B10:B18) -> 9 | C6: =COUNTIF(D10:D18,"Đã hoàn thành") -> 0 | E6: =IFERROR(AVERAGE(E10:E18),0) -> 0 | G6: =IFERROR(AVERAGE(F10:F18),"")
A8: Nhập Trạng thái, Tiến độ và Điểm ở các ô nền vàng. Tiến độ nhập từ 0% đến 100%; điểm từ 0 đến 10.
A9: STT | B9: Module | C9: Số bài | D9: Trạng thái | E9: Tiến độ (%) | F9: Điểm /10 | G9: Ngày hoàn thành | H9: Ghi chú
A10: 1 | B10: 01 - Introduction | C10: 2 | D10: Chưa bắt đầu | E10: 0
A11: 2 | B11: 02 - RAG Fundamentals | C11: 5 | D11: Chưa bắt đầu | E11: 0
A12: 3 | B12: 03 - Introduction to Large Language Models | C12: 6 | D12: Chưa bắt đầu | E12: 0
A13: 4 | B13: 04 - VS Code & GitHub Repo Setup | C13: 3 | D13: Chưa bắt đầu | E13: 0
A14: 5 | B14: 05 - Vector Databases & Embeddings | C14: 7 | D14: Chưa bắt đầu | E14: 0
A15: 6 | B15: 06 - LangChain Framework & Building a Simple RAG Pipeline | C15: 5 | D15: Chưa bắt đầu | E15: 0
A16: 7 | B16: 07 - LangChain RAG Advanced | C16: 3 | D16: Chưa bắt đầu | E16: 0
A17: 8 | B17: 08 - Advanced Projects with LangChain | C17: 5 | D17: Chưa bắt đầu | E17: 0
A18: 9 | B18: 09 - Completion | C18: 2 | D18: Chưa bắt đầu | E18: 0

Sheet C03 LangChain - Agentic AI Engi
A1: THEO DÕI KHÓA HỌC — LangChain - Agentic AI Engineering with LangChain & LangGraph
A2: Mã khóa | B2: C03 | C2: Lĩnh vực | D2: 01 - AI & Dữ liệu | E2: Chuyên ngành | F2: 01 - AI Engineering & LLM
A3: Thư mục nguồn | B3: D:\Sao lưu\Udemy\Khóa học\01 - AI & Dữ liệu\01 - AI Engineering & LLM\langchain
A5: TỔNG MODULE | C5: ĐÃ HOÀN THÀNH | E5: TIẾN ĐỘ TRUNG BÌNH | G5: ĐIỂM TRUNG BÌNH
A6: =COUNTA(B10:B37) -> 28 | C6: =COUNTIF(D10:D37,"Đã hoàn thành") -> 0 | E6: =IFERROR(AVERAGE(E10:E37),0) -> 0 | G6: =IFERROR(AVERAGE(F10:F37),"")
A8: Nhập Trạng thái, Tiến độ và Điểm ở các ô nền vàng. Tiến độ nhập từ 0% đến 100%; điểm từ 0 đến 10.
A9: STT | B9: Module | C9: Số bài | D9: Trạng thái | E9: Tiến độ (%) | F9: Điểm /10 | G9: Ngày hoàn thành | H9: Ghi chú
A10: 1 | B10: 01 - Introduction | C10: 5 | D10: Chưa bắt đầu | E10: 0
A11: 2 | B11: 02 - The GIST of LangChain - Get started with your Hello World chain | C11: 9 | D11: Chưa bắt đầu | E11: 0
A12: 3 | B12: 03 - THE GIST of AI Agents | C12: 9 | D12: Chưa bắt đầu | E12: 0
A13: 4 | B13: 04 - Agents Under The Hood 1-4 | C13: 4 | D13: Chưa bắt đầu | E13: 0
A14: 5 | B14: 05 - Layer 1 - The ReAct Loop | C14: 5 | D14: Chưa bắt đầu | E14: 0
A15: 6 | B15: 06 - Layer 2 - Raw Function Calling | C15: 4 | D15: Chưa bắt đầu | E15: 0
A16: 7 | B16: 07 - Layer 3 - The ReAct Prompt - The Foundation of Function Calling | C16: 6 | D16: Chưa bắt đầu | E16: 0
A17: 8 | B17: 08 - Function Calling | C17: 2 | D17: Chưa bắt đầu | E17: 0
A18: 9 | B18: 09 - The GIST of RAG - Embeddings, Vector Databases and Retrieval | C18: 10 | D18: Chưa bắt đầu | E18: 0
A19: 10 | B19: 10 - Building a Documentation Assistant - Embeddings, VectorDBs, Retrieval, Memory | C19: 16 | D19: Chưa bắt đầu | E19: 0
A20: 11 | B20: 11 - Agents Under The Hood 2-4 - Agent Internals Deep Dive | C20: 6 | D20: Chưa bắt đầu | E20: 0
A21: 12 | B21: 12 - Agents Under The Hood 3-4 - Advanced Agent Patterns | C21: 5 | D21: Chưa bắt đầu | E21: 0
... A37: 28 | B37: 28 - Conclusion and Next Steps | C37: 4 | D37: Chưa bắt đầu | E37: 0

Sheet C02 AI Engineer Roadmap Course
A1: THEO DÕI KHÓA HỌC — AI Engineer Roadmap Course
A2: Mã khóa | B2: C02 | C2: Lĩnh vực | D2: 01 - AI & Dữ liệu | E2: Chuyên ngành | F2: 01 - AI Engineering & LLM
A3: Thư mục nguồn | B3: D:\Sao lưu\Udemy\Khóa học\01 - AI & Dữ liệu\01 - AI Engineering & LLM\ai-engineer-roadmap
A5: TỔNG MODULE | C5: ĐÃ HOÀN THÀNH | E5: TIẾN ĐỘ TRUNG BÌNH | G5: ĐIỂM TRUNG BÌNH
A6: =COUNTA(B10:B10) -> 1 | C6: =COUNTIF(D10:D10,"Đã hoàn thành") -> 0 | E6: =IFERROR(AVERAGE(E10:E10),0) -> 0 | G6: =IFERROR(AVERAGE(F10:F10),"")
A8: Nhập Trạng thái, Tiến độ và Điểm ở các ô nền vàng. Tiến độ nhập từ 0% đến 100%; điểm từ 0 đến 10.
A9: STT | B9: Module | C9: Số bài | D9: Trạng thái | E9: Tiến độ (%) | F9: Điểm /10 | G9: Ngày hoàn thành | H9: Ghi chú
A10: 1 | B10: 00 - Roadmap.sh AI Engineer Official | C10: 201 | D10: Chưa bắt đầu | E10: 0

Sheet C01 AI Agent 365 Ngày
A1: THEO DÕI KHÓA HỌC — AI Agent 365 Ngày
A2: Mã khóa | B2: C01 | C2: Lĩnh vực | D2: 01 - AI & Dữ liệu | E2: Chuyên ngành | F2: 01 - AI Engineering & LLM
A3: Thư mục nguồn | B3: D:\Sao lưu\Udemy\Khóa học\01 - AI & Dữ liệu\01 - AI Engineering & LLM\Ai-engineer
A5: TỔNG MODULE | C5: ĐÃ HOÀN THÀNH | E5: TIẾN ĐỘ TRUNG BÌNH | G5: ĐIỂM TRUNG BÌNH
A6: =COUNTA(B10:B17) -> 8 | C6: =COUNTIF(D10:D17,"Đã hoàn thành") -> 0 | E6: =IFERROR(AVERAGE(E10:E17),0) -> 0 | G6: =IFERROR(AVERAGE(F10:F17),"")
A8: Nhập Trạng thái, Tiến độ và Điểm ở các ô nền vàng. Tiến độ nhập từ 0% đến 100%; điểm từ 0 đến 10.
A9: STT | B9: Module | C9: Số bài | D9: Trạng thái | E9: Tiến độ (%) | F9: Điểm /10 | G9: Ngày hoàn thành | H9: Ghi chú
A10: 1 | B10: 01 - Tuan 1 - Gioi Thieu va Cai Dat | C10: 5 | D10: Chưa bắt đầu | E10: 0
A11: 2 | B11: 02 - Tuan 2 - Gradio va Transformers | C11: 5 | D11: Chưa bắt đầu | E11: 0
A12: 3 | B12: 03 - Tuan 3 - Open Source Models | C12: 5 | D12: Chưa bắt đầu | E12: 0
A13: 4 | B13: 04 - Tuan 4 - Danh Gia Mo Hinh | C13: 5 | D13: Chưa bắt đầu | E13: 0
A14: 5 | B14: 05 - Tuan 5 - RAG Pipeline | C14: 5 | D14: Chưa bắt đầu | E14: 0
A15: 6 | B15: 06 - Tuan 6 - Data va Machine Learning | C15: 5 | D15: Chưa bắt đầu | E15: 0
A16: 7 | B16: 07 - Tuan 7 - Fine-tuning va Chuyen Nghiep | C16: 5 | D16: Chưa bắt đầu | E16: 0
A17: 8 | B17: 08 - Tuan 8 - Trien Khai Production | C17: 5 | D17: Chưa bắt đầu | E17: 0

Sheet C75 English Pronunciation
A1: THEO DÕI KHÓA HỌC — English Pronunciation — Khóa học Markdown
A2: Mã khóa | B2: C75 | C2: Lĩnh vực | D2: 06 - Ngôn ngữ | E2: Chuyên ngành | F2: 01 - Tiếng Anh
A3: Thư mục nguồn | B3: D:\Sao lưu\Udemy\Khóa học\06 - Ngôn ngữ\01 - Tiếng Anh\english-pronunciation-course.zip
A5: TỔNG MODULE | C5: ĐÃ HOÀN THÀNH | E5: TIẾN ĐỘ TRUNG BÌNH | G5: ĐIỂM TRUNG BÌNH
A6: =COUNTA(B10:B16) -> 7 | C6: =COUNTIF(D10:D16,"Đã hoàn thành") -> 0 | E6: =IFERROR(AVERAGE(E10:E16),0) -> 0 | G6: =IFERROR(AVERAGE(F10:F16),"")
A8: Sao chép sheet này khi thêm khóa mới. Mỗi dòng là một module; nhập trạng thái, tiến độ, điểm và ngày hoàn thành.
A9: STT | B9: Module | C9: Số bài | D9: Trạng thái | E9: Tiến độ (%) | F9: Điểm /10 | G9: Ngày hoàn thành | H9: Ghi chú
A10: =1 -> 1 | B10: Module 01 — Letters and Sounds | C10: =20 -> 20 | D10: Chưa bắt đầu | E10: =0 -> 0
A11: =2 -> 2 | B11: Module 02 — Syllables | C11: =7 -> 7 | D11: Chưa bắt đầu | E11: =0 -> 0
A12: =3 -> 3 | B12: Module 03 — Word Stress | C12: =4 -> 4 | D12: Chưa bắt đầu | E12: =0 -> 0
A13: =4 -> 4 | B13: Module 04 — Sentence Stress & Linking | C13: =9 -> 9 | D13: Chưa bắt đầu | E13: =0 -> 0
A14: =5 -> 5 | B14: Module 05 — Conversation Flow | C14: =8 -> 8 | D14: Chưa bắt đầu | E14: =0 -> 0
A15: =6 -> 6 | B15: Module 06 — Emphasis & Intonation | C15: =12 -> 12 | D15: Chưa bắt đầu | E15: =0 -> 0
A16: =7 -> 7 | B16: Module 07 — Reference & Assessment | C16: =6 -> 6 | D16: Chưa bắt đầu | E16: =0 -> 0

Sheet C76 Phát âm — Kỹ năng đọc
A1: THEO DÕI KHÓA HỌC — Tự học phát âm tiếng Anh — Nền tảng cho kỹ năng đọc
A2: Mã khóa | B2: C76 | C2: Lĩnh vực | D2: 06 - Ngôn ngữ | E2: Chuyên ngành | F2: 01 - Tiếng Anh
A3: Thư mục nguồn | B3: D:\Sao lưu\Udemy\Khóa học\06 - Ngôn ngữ\01 - Tiếng Anh\tu-hoc-phat-am-tieng-anh-nen-tang-ky-nang-doc.zip
A5: TỔNG MODULE | C5: ĐÃ HOÀN THÀNH | E5: TIẾN ĐỘ TRUNG BÌNH | G5: ĐIỂM TRUNG BÌNH
A6: =COUNTA(B10:B18) -> 9 | C6: =COUNTIF(D10:D18,"Đã hoàn thành") -> 0 | E6: =IFERROR(AVERAGE(E10:E18),0) -> 0 | G6: =IFERROR(AVERAGE(F10:F18),"")
A8: Sao chép sheet này khi thêm khóa mới. Mỗi dòng là một module; nhập trạng thái, tiến độ, điểm và ngày hoàn thành.
A9: STT | B9: Module | C9: Số bài | D9: Trạng thái | E9: Tiến độ (%) | F9: Điểm /10 | G9: Ngày hoàn thành | H9: Ghi chú
A10: =1 -> 1 | B10: Module 00 — Khởi động và định hướng | C10: =2 -> 2 | D10: Chưa bắt đầu | E10: =0 -> 0
A11: =2 -> 2 | B11: Module 01 — Nền tảng âm và chữ cái | C11: =1 -> 1 | D11: Chưa bắt đầu | E11: =0 -> 0
A12: =3 -> 3 | B12: Module 02 — Nguyên âm đơn | C12: =6 -> 6 | D12: Chưa bắt đầu | E12: =0 -> 0
A13: =4 -> 4 | B13: Module 03 — Nguyên âm đôi và ôn tập nguyên âm | C13: =4 -> 4 | D13: Chưa bắt đầu | E13: =0 -> 0
A14: =5 -> 5 | B14: Module 04 — Phụ âm — Nhóm đối lập cơ bản | C14: =8 -> 8 | D14: Chưa bắt đầu | E14: =0 -> 0
A15: =6 -> 6 | B15: Module 05 — Phụ âm — Mũi, hầu và âm tiếp cận | C15: =3 -> 3 | D15: Chưa bắt đầu | E15: =0 -> 0
A16: =7 -> 7 | B16: Module 06 — Quy tắc phát âm thực hành | C16: =4 -> 4 | D16: Chưa bắt đầu | E16: =0 -> 0
A17: =8 -> 8 | B17: Module 07 — Trọng âm và ngữ điệu | C17: =2 -> 2 | D17: Chưa bắt đầu | E17: =0 -> 0
A18: =9 -> 9 | B18: Module 08 — Ôn tập và thực hành tổng hợp | C18: =1 -> 1 | D18: Chưa bắt đầu | E18: =0 -> 0

Sheet C77 AlphaAgent — Alpha Mining
A1: THEO DÕI KHÓA HỌC — AlphaAgent — LLM-Driven Alpha Mining và chống Alpha Decay
A2: Mã khóa | B2: C77 | C2: Lĩnh vực | D2: 01 - AI & Dữ liệu | E2: Chuyên ngành | F2: 01 - AI Engineering & LLM
A3: Thư mục nguồn | B3: D:\Sao lưu\Udemy\Khóa học\01 - AI & Dữ liệu\01 - AI Engineering & LLM\alphaagent-llm-driven-alpha-mining.zip
A5: TỔNG MODULE | C5: ĐÃ HOÀN THÀNH | E5: TIẾN ĐỘ TRUNG BÌNH | G5: ĐIỂM TRUNG BÌNH
A6: =COUNTA(B10:B10) -> 1 | C6: =COUNTIF(D10:D10,"Đã hoàn thành") -> 0 | E6: =IFERROR(AVERAGE(E10:E10),0) -> 0 | G6: =IFERROR(AVERAGE(F10:F10),"")
A8: Sao chép sheet này khi thêm khóa mới. Mỗi dòng là một module; nhập trạng thái, tiến độ, điểm và ngày hoàn thành.
A9: STT | B9: Module | C9: Số bài | D9: Trạng thái | E9: Tiến độ (%) | F9: Điểm /10 | G9: Ngày hoàn thành | H9: Ghi chú
A10: =1 -> 1 | B10: Module 01 — AlphaAgent: LLM-Driven Alpha Mining | C10: =10 -> 10 | D10: Chưa bắt đầu | E10: =0 -> 0
